Workbook

Sheet Marketing Starter Kit
A1: 📝 | B1: Marketing Starter Kit | C1: Status | D1: Difficulty | E1: Impact
A3: STEP 1 | B3: Create your marketing strategy
B4: Create a buyer persona | C4: Not Started | D4: Hard | E4: High
B5: Enrich your personas | C5: Not Started | D5: Medium | E5: High
B6: Create your digital marketing strategy | C6: Not Started | D6: Hard | E6: High
B7: Prioritize your funnel initiatives | C7: Not Started | D7: Hard | E7: Medium
A9: STEP 2 | B9: Kickstart your SEO engine
B10: Find your website's most important pages for SEO | C10: Not Started | D10: Medium | E10: High
B11: Perform an SEO audit on your most important pages | C11: Not Started | D11: Hard | E11: Medium
B12: Optimize your most important pages | C12: Not Started | D12: Hard | E12: High
A14: STEP 3 | B14: Kickstart your social media engine
B15: Audit your social media accounts | C15: Not Started | D15: Medium | E15: Medium
B16: Create great content for social media | C16: Not Started | D16: Hard | E16: High
B17: Starting a social media calendar | C17: Not Started | D17: Medium | E17: Medium
B18: Create amazing social media content | C18: Not Started | D18: Hard | E18: High
A20: STEP 4 | B20: Kickstart your content engine
B21: Copy proven content templates to generate traffic | C21: Not Started | D21: Easy | E21: High
B22: Create engaging and effective content with AI | C22: Not Started | D22: Easy | E22: High
A24: STEP 5 | B24: Kickstart your email engine
B25: Reverse-engineer a competitor's email marketing strategy | C25: Not Started | D25: Hard | E25: High
B26: Implement email automation templates that drive sales | C26: Not Started | D26: Medium | E26: High
B27: Create high-converting email content | C27: Not Started | D27: Hard | E27: High
A29: STEP 6 | B29: Kickstart your paid ads engine
B30: Reverse engineer your competitor's Facebook Ads Strategy | C30: Not Started | D30: Medium | E30: High
B31: Reverse engineer your competitor's Google Ads Strategy | C31: Not Started | D31: Hard | E31: High
B32: Create high-converting ads | C32: Not Started | D32: Hard | E32: High

Sheet Link Building Checklist - SEO B
C1: The Link Building Checklist
A4: Finding Link Building Opportunities
B5: Main Checklist | C5: Resources
B6: Find backlink opportunities using an SEO tool like Semrush | C6: https://www.semrush.com/blog/find-backlinks/
B7: Check competitors’ content and find the sites linking to them | C7: https://userp.io/find-competitor-backlinks/
B8: Reclaim broken competitor links by providing your updated links | C8: https://ahrefs.com/blog/fix-broken-links/
B9: Get backlinks for any unlinked mentions for your brand | C9: https://www.searchenginejournal.com/link-building-guide/unlinked-brand-mentions/
B10: Make a list of guest posting sites in your niche and pitch to them | C10: https://bloggerspassion.com/guest-posting-sites-list/
B11: Find all relevant directories and get listings/citations | C11: https://www.searchenginejournal.com/citations-local-seo-guide/347380/
B12: Start an affiliate marketing program to build backlinks | C12: https://www.searchenginejournal.com/link-building-guide/affiliate/
A13: Vetting the Websites for Link Building
B14: Main Checklist
B15: Check the site’s domain authority score | C15: https://moz.com/learn/seo/domain-authority
B16: Make sure that it is a relevant site within your niche | C16: https://www.searchenginejournal.com/find-related-sites/9086/
B17: Ensure that the site is not on any blacklists | C17: https://geekflare.com/find-remove-blacklist-site/
B18: Read the site’s content to make sure it’s:
B19: ---- Relevant to your audience | C19: https://contentmarketinginstitute.com/2015/10/content-strategy-questions-answered/
B20: ---- High quality | C20: https://www.searchenginejournal.com/how-to-create-high-quality-content/254511/
B21: ---- Not spammy | C21: https://neilpatel.com/blog/spammers-and-negative-seo/
B22: Ensure that it is not a link farm | C22: https://www.rogeracuna.com/wordpress/site-link-farm/ https://www.rosemontmedia.com/surgeons-blog/industry-jargon-explained-link-farms/
B23: Check if they allow guest posts | C23: https://seo-hacker.com/find-sites-guest-blogging/
B24: Prefer sites that have a high organic search traffic | C24: https://www.incomediary.com/how-much-traffic-website-gets/
A25: Creating Content for Link Building - Basic Checklist for Creating Link Building Content
B26: Main Checklist
B27: Select topics according to the website | C27: https://neilpatel.com/blog/how-to-come-up-with-blog-ideas/ https://www.semrush.com/blog/how-to-find-blog-post-ideas/
B28: Meet the target site content guidelines | C28: https://www.semrush.com/blog/14-tips-for-writing-awesome-website-content/ https://blog.alexa.com/the-complete-guide-how-to-write-content-for-a-website/
B29: Use a relevant anchor text to add your link | C29: https://www.semrush.com/blog/what-is-anchor-text-and-how-can-i-optimize-it/
B30: Create unique, plagiarism-free content | C30: https://www.webdew.com/blog/content-writing-tips
B31: Add some internal links to the target site as a nice gesture | C31: https://neilpatel.com/blog/the-complete-guide-to-internal-linking/
B32: Add other contextual external links so that yours doesn’t stand out | C32: https://postaga.com/contextual-links/
B33: Place the link towards the top of the content and not the bottom | C33: https://uplandsoftware.com/kapost/resources/blog/link-strategy-blog-posts/
A34: Creating Content for Link Building - Types of Content You Can Create for Link Building
B35: Main Checklist
B36: Articles for guest posting | C36: https://blog.alexa.com/guest-posting/
B37: Infographics that can be distributed to multiple sites | C37: https://visme.co/blog/how-to-build-links-with-infographics/
B38: Research studies that many sites would want to cite | C38: https://blog.hubspot.com/marketing/case-studies-marketing
B39: Quora answers to industry-related questions | C39: https://neilpatel.com/blog/blog-quora-marketing-guide/
B40: HARO answers and expert quotes for roundups | C40: https://www.elegantthemes.com/blog/marketing/a-guide-to-haro-for-content-creators-and-marketers
A41: Assessing the Quality of Backlinks
B42: Main Checklist
B43: Try to get dofollow links over nofollow links | C43: https://blog.alexa.com/dofollow-vs-nofollow-links/
B44: Ensure that the link is not tagged as UGC or sponsored | C44: https://moz.com/blog/everything-you-need-to-know-about-sponsored-content
B45: Make sure that the page does not have a noindex tag | C45: https://www.pageonepower.com/search-glossary/noindex
B46: Avoid pages that are excluded by the robots.txt file | C46: https://ignitevisibility.com/the-newbies-guide-to-blocking-content-with-robots-txt/
B47: Prefer backlinks from popular pages that get many incoming links | C47: https://www.searchenginejournal.com/inbound-links-beginners-guide/373408/
B48: Check that the page that’s linking to you does not have too many external links | C48: https://www.accuranker.com/learn-seo/beginner/guide-to-external-links-for-seo

Sheet Brand Information
B2: Foundational Network
B4: Brand Information
A5: 1 | B5: Website | C5: https://www.vitalmobility.ca/
A6: 3 | B6: Company Owner | C6: Bruno Rzeznikieiwiz
A7: 4 | B7: Business Name | C7: Vital Mobility
A8: 5 | B8: Address Line 1 | C8: 130 Bass Pro Mills Drive #62, Concord, ON L4K 5X2
A9: 6 | B9: City | C9: Concord
A10: 7 | B10: Province/State | C10: ON
A11: 8 | B11: Zip Code | C11: 94518
A12: 9 | B12: Phone (local) | C12: (905) 532-9494
A13: 10 | B13: Additional Business Information
A14: 11 | B14: Hours of operation | D14: Friday | E14: 9: 00am-5:00pm
A15: 12 | B15: Year Founded | C15: 39800 | D15: Saturday | E15: 10:00am-2:00pm
A16: 13 | B16: Headline/Tagline | C16: Vital Mobility | Medical Equipment Toronto | Medical Supply Toronto | Wheelchair Rental | D16: Sunday | E16: Closed
A17: 14 | B17: Business Description (minimum 400 characters) | C17: Introducing Vital Mobility Home Health Care Toronto, your premier source for hospital bed rentals, mobility scooter rentals, lift chairs rentals, and wheelchair rental. Elevate your comfort and independence—explore our top-notch rental solutions today! | D17: Monday | E17: 9: 00am-5:00pm
A18: 15 | B18: Payment Types Accepted | C18: All | D18: Tuesday | E18: 9: 00am-5:00pm
A19: 16 | B19: Contractor #/License # | C19: They dont have one - Business license they do | D19: Wednesday | E19: 9: 00am-5:00pm
A20: 17 | B20: Keyword #1 | C20: Hospital bed rentals | D20: Thursday | E20: 9: 00am-5:00pm
A21: 18 | B21: Keyword #2 | C21: hospital bed
A22: 19 | B22: Keyword #3 | C22: mobility scooter
A23: 20 | B23: Keyword #4 | C23: lift chairs,wheel chair rental
A24: 22 | B24: Company Logo: | C24: https://www.vitalmobility.ca/blog/wp-content/uploads/2016/01/vital-logo-new-pdf.pdf-2115.608-x-600-mm-1.png | D24: I will add the transparent logo too
A25: 23 | B25: Image 1 | C25: https://www.vitalmobility.ca/blog/wp-content/uploads/2024/01/IMG_6270.jpg | D25: Front store - Toronto / North York Store
A26: 24 | B26: Image 2 | C26: https://www.vitalmobility.ca/blog/wp-content/uploads/2024/01/IMG_6260.jpg | D26: Delivery Van
A27: 25 | B27: Image 3 | C27: https://www.vitalmobility.ca/blog/wp-content/uploads/2024/01/IMG_6266.jpg | D27: Home Hospital Beds
B28: Image 4 | C28: https://www.vitalmobility.ca/blog/wp-content/uploads/2024/01/IMG_6267.jpg | D28: Mobility Scooters
B29: Image 5 | C29: https://www.vitalmobility.ca/blog/wp-content/uploads/2024/01/IMG_3123.jpg | D29: Concord / Vaughan Store
A30: 26 | B30: Existing Account Information | C30: No
A31: 27 | B31: Any notes or special instructions for us? | C31: No

Sheet Social Essential Network
A1: Social Essential Network
A4: Website
B5: Email Address | C5: Password | D5: Recovery Email | E5: Phone #
A6: Gmail
A7: Social Accounts | B7: Profile URL | C7: Username | D7: Password | E7: Email | F7: Notes
A8: Blogger | B8: https://vitalmobility.blogspot.com/2023/12/rolling-freedom-unlocking-adventures.html | C8: Vital mobility | D8: auto login | E8: seo@thespeedtrain.com
A9: Gravatar | B9: https://gravatar.com/seo7e35dc32c2c8 | C9: Vital Mobility | D9: auto login | E9: seo@thespeedtrain.com
A10: Pinterest | B10: https://pin.it/7clqTjlXc | C10: Vital Mobility | D10: auto login | E10: seo@thespeedtrain.com
A11: Tumblr | B11: https://www.tumblr.com/vitalmobality/740879303765557248/vital-mobility-medical-equipment-toronto?source=share | C11: vitalmobality | E11: seo@thespeedtrain.com | F11: open with vpn
A12: Wordpress | B12: https://vitalmobility9.wordpress.com/2024/01/16/vital-mobility/ | C12: Vital Mobility | D12: auto login | E12: seo@thespeedtrain.com
A13: Youtube | B13: https://www.youtube.com/@vitalmobility | C13: Vital Mobility | D13: auto login | E13: seo@thespeedtrain.com
A14: Coub.com | B14: https://coub.com/vitalmobility1 | C14: Vital Mobility | D14: vital321 | E14: seo@thespeedtrain.com
A15: Buzzfeed | B15: https://www.buzzfeed.com/oldskull68/vital-mobility-desp82vjo5?utm_source=dynamic&utm_campaign=bfsharecopy | C15: Vital Mobility | D15: auto login | E15: seo@thespeedtrain.com
A16: Diigo | B16: https://diigo.com/0v2dxc | C16: Vital Mobility | D16: vital321 | E16: seo@thespeedtrain.com
A17: Disqus | B17: https://disqus.com/by/vital_mobility/about/ | C17: Vital Mobility | D17: auto login | E17: seo@thespeedtrain.com
A18: Medium | B18: https://medium.com/@vitalmobility | C18: Vital Mobility | D18: auto login | E18: seo@thespeedtrain.com
A19: Minds.com | B19: https://www.minds.com/vitalmobility/ | C19: Vital Mobility | D19: @Vital321 | E19: seo@thespeedtrain.com
A20: Quora | B20: https://www.quora.com/profile/Vital-Mobility-2 | C20: Vital Mobility | D20: auto login | E20: seo@thespeedtrain.com
A21: Facebook | B21: https://www.facebook.com/VitalMobility/ | C21: Vital Mobility | D21: vital321 | E21: seo@thespeedtrain.com
A22: Wikidot | B22: https://www.wikidot.com/user:info/vital-mobility | C22: Vital Mobility | D22: vital321 | E22: seo@thespeedtrain.com
A23: Issuu | B23: https://issuu.com/vitalmobility1 | C23: Vital Mobility | D23: vital321 | E23: seo@thespeedtrain.com
... A26: fliphtml5 | B26: https://fliphtml5.com/homepage/xqvhf/seo-thespeedtrain/ | C26: Vital Mobility | D26: auto login | E26: seo@thespeedtrain.com

Sheet Social Fortress Upgrade
A1: Social Fortress Upgrade
A3: Website
B4: Email Address | C4: Password | D4: Recovery Email | E4: Phone #
A5: Gmail
A6: Social Accounts | B6: Profile URL | C6: Username | D6: Password | E6: Email | F6: Notes
A7: pearltrees | B7: https://www.pearltrees.com/vitalmobility1 | C7: Vital Mobility | D7: vital321 | E7: seo@thespeedtrain.com
A8: bloglovin | B8: https://www.bloglovin.com/@vitalmobality | C8: Vital Mobility | D8: vital321 | E8: seo@thespeedtrain.com
A9: blurb | B9: https://www.blurb.com/user/vitalmobilit?profile_preview=true | C9: Vital Mobility | D9: vital321 | E9: seo@thespeedtrain.com
A10: instapaper | B10: https://www.instapaper.com/p/13597872 | C10: Vital Mobility | D10: vital321 | E10: seo@thespeedtrain.com
A11: penzu | B11: https://penzu.com/p/10c35e3622b84d13 | C11: Vital Mobility | D11: vital321 | E11: seo@thespeedtrain.com
A12: https://letterboxd.com/ | B12: https://letterboxd.com/vitalmobility1/ | C12: Vital Mobility | D12: vital321 | E12: seo@thespeedtrain.com
A13: https://www.goodreads.com/ | B13: https://www.goodreads.com/user/show/174515392-vitalmobility | C13: Vital Mobility | D13: vital321 | E13: seo@thespeedtrain.com
A14: https://triberr.com/ | B14: https://triberr.com/vitalmobility1 | C14: Vital Mobility | D14: vital321 | E14: seo@thespeedtrain.com
A15: https://sketchfab.com/ | B15: https://sketchfab.com/vitalmobility1 | C15: Vital Mobility | D15: vital321 | E15: seo@thespeedtrain.com
A16: https://slides.com/ | B16: https://slides.com/vitalmobility2 | C16: Vital Mobility | D16: auto login | E16: seo@thespeedtrain.com
A17: https://www.atlasobscura.com/ | B17: https://www.atlasobscura.com/users/vitalmobility2 | C17: Vital Mobility | D17: auto login | E17: seo@thespeedtrain.com
A18: https://substack.com/ | B18: https://substack.com/@vitalmobility | C18: Vital Mobility | D18: auto login | E18: seo@thespeedtrain.com
... A27: https://peatix.com/ | B27: https://peatix.com/user/20696729/view | C27: Vital Mobility | D27: auto login | E27: seo@thespeedtrain.com

Sheet Social Ultimate Upgrade
A1: Social Ultimate Upgrade
A3: Website
B4: Email Address | C4: Password | D4: Recovery Email | E4: Phone #
A5: Gmail
A6: Social Accounts | B6: Profile URL | C6: Username | D6: Password | E6: Email | F6: Notes
A7: magcloud | B7: https://www.magcloud.com/user/vitalmobility1 | C7: vitalmobility1 | D7: vital321 | E7: seo@thespeedtrain.com
A8: ted | B8: https://www.ted.com/profiles/45982849 | C8: vital mobility | D8: auto login | E8: seo@thespeedtrain.com
A9: 4shared | B9: https://www.4shared.com/u/Cud894R4/seo.html | C9: vital mobility | D9: auto login | E9: seo@thespeedtrain.com
A10: All4webs.com | B10: https://all4webs.com/vitalmobility1/home.htm?11157=13652 | C10: vital mobility | D10: vital321 | E10: seo@thespeedtrain.com
A11: giphy.com | B11: https://giphy.com/channel/vitalmobility1 | C11: vital mobility | D11: auto login | E11: seo@thespeedtrain.com
A12: https://padlet.com/ | B12: https://padlet.com/vitalmobility/my-fearless-padlet-ufq3jpn1hzcivktg | C12: vital mobility | D12: auto login | E12: seo@thespeedtrain.com
A13: behance | B13: https://www.behance.net/gallery/189706147/Vital-Mobility | C13: vital mobility | D13: auto login | E13: seo@thespeedtrain.com
A14: kickstarter | B14: https://www.kickstarter.com/profile/vitalmobility/about | C14: vital mobility | D14: vital321 | E14: seo@thespeedtrain.com
A15: skillshare | B15: https://www.skillshare.com/en/profile/Seo-TheSpeedTrain/264027658 | C15: vital mobility | D15: auto login | E15: seo@thespeedtrain.com
A16: Start.me | B16: https://start.me/p/YQMjbq/start-page | C16: vital mobility | D16: auto login | E16: seo@thespeedtrain.com

Sheet Project Detail
B4: Project Details
B5: Brand Name | C5: Vital Mobility
B6: Domain Name | C6: https://vitalmobility.ca/
B7: Location | C7: 3 locations
B8: Description of Brand | C8: Canada’s Leading Medical Equipment Supplier & Rental Company
B9: Working Hours | C9: Mon-Fri 9am-5pm | Sat 10am-2pm | Sun Closed
B10: Instagram | C10: https://www.instagram.com/vitalmobilityhome/
B11: Linkedin | C11: https://www.linkedin.com/company/vital-mobility-home-healthcare/
B12: Facebook | C12: https://www.facebook.com/VitalMobility/
B13: Phone No. | C13: 905-532-9494
B14: Target Location | C14: Canada with £ locations
B15: Business Email (for business Listing and Directory) | C15: info@vitalmobility.ca
B16: Off-Page Details
B17: Email | C17: seo@thespeedtrain.com
B18: Password(Gmail) | C18: pooyaseo@thespeedtrain
B19: Username | C19: Vital Mobility

Sheet Report Summary
B4: White Hat SEO Work as per Google Panda and Penguin Algorithm
B6: Website:https://www.vitalmobility.ca/
B8: Sr.No | C8: Task | D8: Status
B9: 1 | C9: Keywords Ranking | D9: Done
B10: 2 | C10: Profile Creation | D10: Live
B11: 3 | C11: Social Bookmarking | D11: Live
B12: 4 | C12: Image Sharing | D12: Live
B13: 5 | C13: Web 2.0 Submission | D13: Live
B14: 6 | C14: Web 2.0 Blog Promotion | D14: Live
B15: 7 | C15: Blog Social Bookmarking | D15: Live
B16: 8 | C16: Local Citation submissions | D16: Live
B17: 9 | C17: Classified Submission | D17: Live
B18: 10 | C18: SEO+SMO Conjugation | D18: Live
B19: 11 | C19: Quora | D19: Live
B20: 12 | C20: Article submission | D20: Live
... B25: 17 | C25: Infographic Promotion | D25: Live

Sheet URL Mapping
B3: Keywords
B4: Website: https://www.vitalmobility.ca/
B5: Sr.No | C5: Keywords | D5: Landing Page
B6: 1
B7: 2
B8: 3
B9: 4
B10: 5
B11: 6
B12: 7
B13: 8
B14: 9
B15: 10
B16: 11
B17: 12
... B35: 30

Sheet Keywords Ranking
B3: Keywords Ranking
B4: Website: https://www.vitalmobility.ca/
B5: Sr.No | C5: Keywords | D5: Landing Page | I5: 45247 | J5: 45237 | K5: Initial Ranking Nov 1 2023
B6: 1 | I6: 13 | J6: 13 | K6: 12
B7: 2 | I7: N/A | J7: 64 | K7: N/A
B8: 3 | I8: 87 | J8: 86 | K8: 80
B9: 4 | I9: 61 | J9: 59 | K9: 77
B10: 5 | I10: 70 | J10: 70 | K10: 74
B11: 6 | I11: 74 | J11: 138 | K11: N/A
B12: 7 | I12: 17 | J12: 17 | K12: 13
B13: 8 | I13: 18 | J13: 17 | K13: 14
B14: 9 | I14: 32 | J14: 23 | K14: N/A
B15: 10 | I15: 12 | J15: 11 | K15: 45
B16: 11 | I16: 25 | J16: 23 | K16: 28
B17: 12 | I17: 41 | J17: 56 | K17: 56
B18: 13 | I18: 64 | J18: 76 | K18: 72
B19: 14 | I19: 47 | J19: 45 | K19: 57
B20: 15 | I20: N/A | J20: N/A | K20: N/A
B21: 16 | I21: 63 | J21: 66 | K21: 75
B22: 17 | I22: N/A | J22: N/A | K22: N/A
B23: 18 | I23: N/A | J23: N/A | K23: N/A
B24: 19 | I24: N/A | J24: N/A | K24: N/A
B25: 20 | I25: 94 | J25: 92 | K25: 92
B26: 21 | I26: N/A | J26: N/A | K26: N/A
B27: 22 | I27: N/A | J27: N/A | K27: N/A
B28: 23 | I28: 44 | J28: 47 | K28: 65
B29: 24 | I29: 54 | J29: 60 | K29: 57
B30: 25 | I30: 66 | J30: 60 | K30: N/A
B31: 26 | I31: 68 | J31: 70 | K31: 81
B32: 27 | I32: 96 | J32: N/A | K32: N/A
B33: 28 | I33: N/A | J33: N/A | K33: N/A
B34: 29 | I34: N/A | J34: N/A | K34: N/A
B35: 30 | I35: N/A | J35: N/A | K35: N/A

Sheet All Backlinks
G1: Backlinks with issue | H1: Issue | I1: From The section
A2: Social Bookmarking
A3: https://www.scoop.it/topic/vital-mobility-by-seo-thespeedtrain-com-10 | B3: seo@thespeedtrain.com | C3: pooyaseo@thespeedtrain | D3: Vital Mobility | E3: Live
A4: https://medium.com/@vitalmobility | B4: seo@thespeedtrain.com | C4: pooyaseo@thespeedtrain | D4: Vital Mobility | E4: Live
A5: https://folkd.com/profile/vitalmobality | B5: seo@thespeedtrain.com | C5: pooyaseo@thespeedtrain | D5: Vital Mobility | E5: Live
A6: https://wakelet.com/@vitalmobility | B6: seo@thespeedtrain.com | C6: pooyaseo@thespeedtrain | D6: Vital Mobility | E6: Live
A7: https://www.tumblr.com/hospitalbedsvit/722098665182887936/medical-equipment-supplier-rental-store-in?source=share | B7: seo@thespeedtrain.com | C7: pooyaseo@thespeedtrain | D7: Vital Mobility | E7: Live | F7: vpn
A8: https://www.evernote.com/shard/s630/sh/23790f0b-3d29-ddf4-bda0-a69312c445f7/C8umoHaRePm7hU1bINXkE6j8_O7E5YXsiMsr4CFihGWmTjU_dpgpKWobqQ | B8: seo@thespeedtrain.com | C8: pooyaseo@thespeedtrain | D8: Vital Mobility | E8: Live
A9: https://padlet.com/vitalmobility/my-fearless-padlet-ufq3jpn1hzcivktg | B9: seo@thespeedtrain.com | C9: pooyaseo@thespeedtrain | D9: Vital Mobility | E9: Live
A10: https://miro.com/miroverse/vital-mobility-medical-equipment-toronto/ | B10: seo@thespeedtrain.com | C10: pooyaseo@thespeedtrain | D10: Vital Mobility | E10: Live
A11: https://flipboard.com/@vitalmobility?from=share&utm_source=flipboard&utm_medium=curator_share | B11: seo@thespeedtrain.com | C11: pooyaseo@thespeedtrain | D11: Vital Mobility | E11: Live
A12: https://anotepad.com/note/read/8w6yjw8f | B12: seo@thespeedtrain.com | C12: pooyaseo@thespeedtrain | D12: Vital Mobility | E12: Live
A13: https://www.pearltrees.com/vitalmoility | B13: seo@thespeedtrain.com | C13: pooyaseo@thespeedtrain | D13: Vital Mobility | E13: Live
A14: https://rentry.co/zduen3ha | B14: seo@thespeedtrain.com | C14: RZ8tWGKh | D14: Vital Mobility | E14: Live
A15: https://www.zupyak.com/profile | B15: seo@thespeedtrain.com | C15: pooyaseo@thespeedtrain | D15: Vital Mobility | E15: Live
A16: Clssified Adds
A17: https://www.classifiedads.com/health_wellness/881c73gcp3dbx | B17: seo@thespeedtrain.com | C17: pooyaseo@thespeedtrain | D17: Vital Mobility | E17: Live
A19: Article Submission | C19: pooyaseo@thespeedtrain | D19: Vital Mobility | E19: Live
A20: https://diigo.com/0v2dxc | B20: seo@thespeedtrain.com | C20: pooyaseo@thespeedtrain | D20: Vital Mobility | E20: Live
A21: https://vitalmobality.livejournal.com/750.html | B21: seo@thespeedtrain.com | C21: k$br5Zs89E@wRg- | D21: Vital Mobility | E21: Live
A22: https://medium.com/@seo_66432/the-ultimate-guide-to-cold-therapy-machine-rentals-0d5d86c7cae3 | B22: seo@thespeedtrain.com | C22: pooyaseo@thespeedtrain | D22: Vital Mobility | E22: Live
A23: https://click4r.com/posts/u/6122497/Author-Vital | B23: seo@thespeedtrain.com | C23: pooyaseo@thespeedtrain | D23: Vital Mobility | E23: Live
A24: Article Promotion
A25: https://linktr.ee/vitalmobility | B25: seo@thespeedtrain.com | C25: pooyaseo@thespeedtrain | D25: Vital Mobility | E25: Live
A26: https://start.me/w/RQe99m | B26: seo@thespeedtrain.com | C26: pooyaseo@thespeedtrain | D26: Vital Mobility | E26: Live
A27: https://wibki.com/vitalmobality?tab=SeoTheSpeedTrain# | B27: seo@thespeedtrain.com | C27: pooyaseo@thespeedtrain | D27: Vital Mobility | E27: Live
A28: https://www.instapaper.com/read/1653922788 | B28: seo@thespeedtrain.com | C28: pooyaseo@thespeedtrain | D28: Vital Mobility | E28: Live
A29: https://raindrop.io/vitalmobality/vital-41343443 | B29: seo@thespeedtrain.com | C29: pooyaseo@thespeedtrain | D29: Vital Mobility | E29: Live
A30: https://contentle.com/vitalmobality/items | B30: seo@thespeedtrain.com | C30: pooyaseo@thespeedtrain | D30: Vital Mobility | E30: Live
A31: https://list.ly/list/9U6Y-vital-mobility-medical-equipment-toronto-medical-supply-toronto-wheelchair-rental?make_list_mode=true | B31: seo@thespeedtrain.com | C31: pooyaseo@thespeedtrain | D31: Vital Mobility | E31: Live
A32: https://www.symbaloo.com/shared/AAAABV8hRZUAA41_0gNuLQ== | B32: seo@thespeedtrain.com | C32: pooyaseo@thespeedtrain | D32: Vital Mobility | E32: Live
A33: https://papaly.com/vitalmobility/akgjq/httpswww-vitalmobility-ca | B33: seo@thespeedtrain.com | C33: pooyaseo@thespeedtrain | D33: Vital Mobility | E33: Live
A34: https://Link.Gallery/vitalmobility | B34: seo@thespeedtrain.com | C34: pooyaseo@thespeedtrain | D34: Vital Mobility | E34: Live
A35: https://atavi.com/share/whbgbnz1l9wfx | B35: seo@thespeedtrain.com | C35: pooyaseo@thespeedtrain | D35: Vital Mobility | E35: Live
A36: https://www.exchangle.com/vitalmobility | B36: seo@thespeedtrain.com | C36: pooyaseo@thespeedtrain | D36: Vital Mobility | E36: Live
... A39: https://heylink.me/seo424 | B39: seo@thespeedtrain.com | C39: pooyaseo@thespeedtrain | D39: Vital Mobility | E39: Live
A40: Press Release submission
A41: https://pressnews.biz/@vitalmobality/vital-mobility-medical-equipment-toronto-medical-supply-toronto-wheelchair-rental-afhn4ahstxbt | B41: seo@thespeedtrain.com | C41: vital123 | D41: Vital Mobility | E41: Live
A42: Local Ciatation
A43: https://www.provenexpert.com/vital-mobility/?_gl=1*14rhb1t*_ga*NDYxMTA4OTA4LjE3MDM1MDU5NTc.*_ga_9JZ6KME51R*MTcwMzUwNTk1Ni4xLjEuMTcwMzUwNzQwNC42LjAuMA.. | B43: seo@thespeedtrain.com | C43: pooyaseo@thespeedtrain | D43: Vital Mobility | E43: Live
A44: https://www.brownbook.net/business/52338609/vital-mobility/ | B44: seo@thespeedtrain.com | C44: pooyaseo@thespeedtrain | D44: Vital Mobility | E44: Live
A45: https://www.techdirectory.io/canada/health-technology/vital-mobility | B45: seo@thespeedtrain.com | C45: pooyaseo@thespeedtrain | D45: Vital Mobility | E45: Live
A46: https://au.enrollbusiness.com/BusinessProfile/6506847/Vital%20Mobility | B46: seo@thespeedtrain.com | C46: pooyaseo@thespeedtrain | D46: Vital Mobility | E46: Live
A47: https://www.localbusinesslisting.org/vital-mobility | B47: seo@thespeedtrain.com | C47: pooyaseo@thespeedtrain | D47: Vital Mobility | E47: Live
A48: http://www.golocalezservices.com/canada/health-fitness/vital-mobility | B48: seo@thespeedtrain.com | C48: pooyaseo@thespeedtrain | D48: Vital Mobility | E48: Live
A49: https://foursquare.com/vitalm7735738/list/vital-mobility-home-health-care-equipment-supplier | B49: seo@thespeedtrain.com | C49: pooyaseo@thespeedtrain | D49: Vital Mobility | E49: Live
A50: https://www.cargodirectory.co/canada/health-care-services/vital-mobility | B50: seo@thespeedtrain.com | C50: pooyaseo@thespeedtrain | D50: Vital Mobility | E50: Live
A51: https://www.successcenter.com/ontario/concord/services/vital-mobility | B51: seo@thespeedtrain.com | C51: pooyaseo@thespeedtrain | D51: Vital Mobility | E51: Live
A52: https://www.localhomeservicepros.com/canada/health-care/vital-mobility | B52: seo@thespeedtrain.com | C52: pooyaseo@thespeedtrain | D52: Vital Mobility | E52: Live
A53: https://www.bestincom.com/canada/health-care/vital-mobility | B53: seo@thespeedtrain.com | C53: pooyaseo@thespeedtrain | D53: Vital Mobility | E53: Live
A54: Profile Creation
A55: https://medium.com/@seo_66432 | B55: seo@thespeedtrain.com | C55: pooyaseo@thespeedtrain | D55: Vital Mobility | E55: Live
A56: https://www.behance.net/vitalmobility | B56: seo@thespeedtrain.com | C56: pooyaseo@thespeedtrain | D56: Vital Mobility | E56: Live
A57: https://justpaste.it/u/Vital_Mobility | B57: seo@thespeedtrain.com | C57: pooyaseo@thespeedtrain | D57: Vital Mobility | E57: Live
A58: https://imgur.com/gallery/otT7uU8 | B58: seo@thespeedtrain.com | C58: pooyaseo@thespeedtrain | D58: Vital Mobility | E58: Live
A59: https://folkd.com/profile/vitalmobality | B59: seo@thespeedtrain.com | C59: pooyaseo@thespeedtrain | D59: Vital Mobility | E59: Live
A60: https://www.tumblr.com/hospitalbedsvit/722098665182887936/medical-equipment-supplier-rental-store-in?source=share | B60: seo@thespeedtrain.com | C60: pooyaseo@thespeedtrain | D60: Vital Mobility | E60: Live
A61: https://www.provenexpert.com/vital-mobility/?_gl=1*14rhb1t*_ga*NDYxMTA4OTA4LjE3MDM1MDU5NTc.*_ga_9JZ6KME51R*MTcwMzUwNTk1Ni4xLjEuMTcwMzUwNzQwNC42LjAuMA.. | B61: seo@thespeedtrain.com | C61: pooyaseo@thespeedtrain | D61: Vital Mobility | E61: Live
A62: https://www.reddit.com/user/vitalmobality/ | B62: seo@thespeedtrain.com | C62: pooyaseo@thespeedtrain | D62: Vital Mobility | E62: Live
A63: Profile Link Updation
A64: https://medium.com/@seo_66432 | B64: seo@thespeedtrain.com | C64: pooyaseo@thespeedtrain | D64: Vital Mobility | E64: Live
A65: https://www.behance.net/vitalmobility | B65: seo@thespeedtrain.com | C65: pooyaseo@thespeedtrain | D65: Vital Mobility | E65: Live
A66: https://justpaste.it/u/Vital_Mobility | B66: seo@thespeedtrain.com | C66: pooyaseo@thespeedtrain | D66: Vital Mobility | E66: Live
A67: https://imgur.com/gallery/otT7uU8 | B67: seo@thespeedtrain.com | C67: pooyaseo@thespeedtrain | D67: Vital Mobility | E67: Live
A68: https://folkd.com/profile/vitalmobality | B68: seo@thespeedtrain.com | C68: pooyaseo@thespeedtrain | D68: Vital Mobility | E68: Live
A69: https://www.tumblr.com/hospitalbedsvit/722098665182887936/medical-equipment-supplier-rental-store-in?source=share | B69: seo@thespeedtrain.com | C69: pooyaseo@thespeedtrain | D69: Vital Mobility | E69: Live
A70: https://www.provenexpert.com/vital-mobility/?_gl=1*14rhb1t*_ga*NDYxMTA4OTA4LjE3MDM1MDU5NTc.*_ga_9JZ6KME51R*MTcwMzUwNTk1Ni4xLjEuMTcwMzUwNzQwNC42LjAuMA.. | B70: seo@thespeedtrain.com | C70: pooyaseo@thespeedtrain | D70: Vital Mobility | E70: Live
A71: https://www.reddit.com/user/vitalmobality | B71: seo@thespeedtrain.com | C71: pooyaseo@thespeedtrain | D71: Vital Mobility | E71: Live
A72: Infographic Submission
A73: https://pin.it/75p05GLXA | B73: seo@thespeedtrain.com | C73: pooyaseo@thespeedtrain | D73: Vital Mobility | E73: Live
A74: https://www.4shared.com/s/flMlRJo0Cfa | B74: seo@thespeedtrain.com | C74: pooyaseo@thespeedtrain | D74: Vital Mobility | E74: Live
A75: https://www.mediafire.com/file/mx34z35w86rjtxo/Green_Modern_Medical_Service_Poster.pdf/file | B75: seo@thespeedtrain.com | C75: pooyaseo@thespeedtrain | D75: Vital Mobility | E75: Live
A76: https://www.dropbox.com/scl/fi/bupldepe5h15dppl6osbm/Green-Modern-Medical-Service-Poster.pdf?rlkey=myjt958b8nr2i0la8k5jx5poy&dl=0 | B76: seo@thespeedtrain.com | C76: pooyaseo@thespeedtrain | D76: Vital Mobility | E76: Live
A77: https://i.postimg.cc/44Qv6YmQ/Green-Modern-Medical-Service-Poster.png | B77: seo@thespeedtrain.com | C77: sPpxxZwFQKVr | D77: Vital Mobility | E77: Live
A78: https://wakelet.com/i/invite?code=3ruzahid | B78: seo@thespeedtrain.com | C78: pooyaseo@thespeedtrain | D78: Vital Mobility | E78: Live
A79: https://photos.app.goo.gl/RTej94ZqSjCqJB4d7 | B79: seo@thespeedtrain.com | C79: pooyaseo@thespeedtrain | D79: Vital Mobility | E79: Live
A80: https://workdrive.zoho.com/file/4594wf2e1a707178a4411966a01acc30e5c42 | B80: seo@thespeedtrain.com | C80: pooyaseo@thespeedtrain | D80: Vital Mobility | E80: Live
A81: https://www.edocr.com/v/9x7gmxb5/vitalmobility1/green-modern-medical-service-poster | B81: seo@thespeedtrain.com | C81: pooyaseo@thespeedtrain | D81: Vital Mobility | E81: Live
A82: https://diigo.com/0v7l0r | B82: seo@thespeedtrain.com | C82: pooyaseo@thespeedtrain | D82: Vital Mobility | E82: Live
A83: https://www.tumblr.com/vitalmobality/740949560387633152?source=share | B83: seo@thespeedtrain.com | C83: pooyaseo@thespeedtrain | D83: Vital Mobility | E83: Live
A84: https://www.4shared.com/s/flMlRJo0Cfa | B84: seo@thespeedtrain.com | C84: pooyaseo@thespeedtrain | D84: Vital Mobility | E84: Live
A85: https://photos.app.goo.gl/RTej94ZqSjCqJB4d7 | B85: seo@thespeedtrain.com | C85: pooyaseo@thespeedtrain | D85: Vital Mobility | E85: Live
A86: Infographics Promotions
A87: https://jpst.it/3zpeY | B87: seo@thespeedtrain.com | C87: pooyaseo@thespeedtrain | D87: Vital Mobility | E87: Live
A88: https://www.tumblr.com/vitalmobality/741044396498272256/vital-mobility-medical-equipment-toronto?source=share | B88: seo@thespeedtrain.com | C88: pooyaseo@thespeedtrain | D88: Vital Mobility | E88: Live
A89: https://www.pearltrees.com/vitalmoility | B89: seo@thespeedtrain.com | C89: pooyaseo@thespeedtrain | D89: Vital Mobility | E89: Live
A90: https://www.scribd.com/document/702727975/Blue-and-White-Home-based-Health-Service-Instagram-Post-1 | B90: seo@thespeedtrain.com | C90: pooyaseo@thespeedtrain | D90: Vital Mobility | E90: Live
A91: https://wakelet.com/wake/n2JuUciEJb21-Dx7oZTsR | B91: seo@thespeedtrain.com | C91: pooyaseo@thespeedtrain | D91: Vital Mobility | E91: Live
A92: https://www.diigo.com/user/vitalmoblity | B92: seo@thespeedtrain.com | C92: pooyaseo@thespeedtrain | D92: Vital Mobility | E92: Live
A93: https://vitalmobility.imgbb.com/ | B93: seo@thespeedtrain.com | C93: pooyaseo@thespeedtrain | D93: Vital Mobility | E93: Live
A94: https://500px.com/photo/1084798718/blue-and-white-home-based-health-service-instagram-post-1-by-vital-mobility | B94: seo@thespeedtrain.com | C94: pooyaseo@thespeedtrain | D94: Vital Mobility | E94: Live

Sheet Social Bookmarking
B2: Social Bookmarking
B3: https://www.vitalmobility.ca/
B6: Sr.No | C6: Website | D6: Gmail | E6: Password | F6: Target Keyword | G6: Target URL | H6: Live URL | I6: Status
B7: 1 | C7: https://www.scoop.it/ | D7: seo@thespeedtrain.com | E7: pooyaseo@thespeedtrain | F7: Vital mobility | G7: https://www.vitalmobility.ca/ | H7: https://sco.lt/6r0DD6 | I7: Live
B8: 2 | C8: https://medium.com/ | D8: seo@thespeedtrain.com | E8: pooyaseo@thespeedtrain | F8: Vital mobility | G8: https://www.vitalmobility.ca/ | H8: https://medium.com/@seo_66432 | I8: Live
B9: 3 | C9: http://www.folkd.com/ | D9: seo@thespeedtrain.com | E9: pooyaseo@thespeedtrain | F9: Vital mobility | G9: https://www.vitalmobility.ca/ | H9: https://folkd.com/profile/vitalmobality | I9: Live
B10: 4 | C10: https://wakelet.com/ | D10: seo@thespeedtrain.com | E10: pooyaseo@thespeedtrain | F10: Vital mobility | G10: https://www.vitalmobility.ca/ | H10: https://wakelet.com/@vitalmobility | I10: Live
B11: 5 | C11: https://www.tumblr.com/ | D11: seo@thespeedtrain.com | E11: pooyaseo@thespeedtrain | F11: Vital mobility | G11: https://www.vitalmobility.ca/ | H11: https://www.tumblr.com/hospitalbedsvit/722098665182887936/medical-equipment-supplier-rental-store-in?source=share | I11: Live
B13: Sr.No | C13: Website | D13: Gmail | E13: Password | F13: Target Keyword | G13: Target URL | H13: Live URL | I13: Status
B14: 1 | C14: https://evernote.com/ | D14: seo@thespeedtrain.com | E14: pooyaseo@thespeedtrain | F14: Vital mobility | G14: https://www.vitalmobility.ca/ | H14: https://www.evernote.com/client/web#/note/a170bb53-aeef-72c2-8990-a734d4b58339 | I14: Live
B15: 2 | C15: https://padlet.com/ | D15: seo@thespeedtrain.com | E15: pooyaseo@thespeedtrain | F15: Vital mobility | G15: https://www.vitalmobility.ca/ | H15: https://padlet.com/vitalmobility/my-fearless-padlet-ufq3jpn1hzcivktg | I15: Live
B16: 3 | C16: https://miro.com/ | D16: seo@thespeedtrain.com | E16: pooyaseo@thespeedtrain | F16: Vital mobility | G16: https://www.vitalmobility.ca/ | H16: https://miro.com/miroverse/submission/preview/3cRpX1VZc9uFoIVXQM7rXt/?backToUrl=%2Fconnected-health-kit-template%2F&id=3cRpX1VZc9uFoIVXQM7rXt | I16: Live
B17: 4 | C17: https://flipboard.com/ | D17: seo@thespeedtrain.com | E17: pooyaseo@thespeedtrain | F17: Vital mobility | G17: https://www.vitalmobility.ca/ | H17: https://flipboard.com/@vitalmobility?from=share&utm_source=flipboard&utm_medium=curator_share | I17: Live
B19: Sr.No | C19: Website | D19: Gmail | E19: Password | F19: Target Keyword | G19: Target URL | H19: Live URL | I19: Status
B20: 1 | C20: https://www.pinterest.com | D20: seo@thespeedtrain.com | E20: pooyaseo@thespeedtrain | F20: Vital mobility | G20: https://www.vitalmobility.ca/ | H20: https://www.pinterest.ca/pin/970807263411221643/ | I20: Live
B21: 2 | C21: https://www.instapaper.com/ | D21: seo@thespeedtrain.com | E21: pooyaseo@thespeedtrain | F21: Vital mobility | G21: https://www.vitalmobility.ca/ | H21: https://www.instapaper.com/u | I21: Live
B23: Sr.No | C23: Website | D23: Gmail | E23: Password | F23: Target Keyword | G23: Target URL | H23: Live URL | I23: Status
B24: 1 | C24: https://anotepad.com/ | D24: seo@thespeedtrain.com | E24: pooyaseo@thespeedtrain | F24: Vital mobility | G24: https://www.vitalmobility.ca/ | H24: https://anotepad.com/note/read/8w6yjw8f | I24: Live
B25: 2 | C25: https://www.pearltrees.com | D25: seo@thespeedtrain.com | E25: pooyaseo@thespeedtrain | F25: Vital mobility | G25: https://www.vitalmobility.ca/ | H25: https://www.pearltrees.com/vitalmoility | I25: Live
B26: 3 | C26: https://rentry.co/ | D26: seo@thespeedtrain.com | E26: pooyaseo@thespeedtrain | F26: Vital mobility | G26: https://www.vitalmobility.ca/ | H26: https://rentry.co/wa785 | I26: Live
B27: 4 | C27: https://www.zupyak.com/ | D27: seo@thespeedtrain.com | E27: pooyaseo@thespeedtrain | F27: Vital mobility | G27: https://www.vitalmobility.ca/ | H27: https://www.zupyak.com/profile | I27: Live
B29: Sr.No | C29: Website | D29: Gmail | E29: Password | F29: Target Keyword | G29: Target URL | H29: Live URL | I29: Status
B30: 1 | I30: Live
B31: 2 | I31: Live
B32: 3 | I32: Live
B33: 4 | I33: Live
B34: 5 | I34: Live
B36: Sr.No | C36: Website | D36: Gmail | E36: Password | F36: Target Keyword | G36: Target URL | H36: Live URL | I36: Status
B37: 1 | I37: Live
B38: 2 | I38: Live
B39: 3 | I39: Live
B40: 4 | I40: Live
B41: 5 | I41: Live
B42: 6 | I42: Live

Sheet Classified Ads
B2: Classified Submission
B3: Website - https://www.vitalmobility.ca/
B6: Sr.No | C6: Website | D6: Gmail | E6: Password | F6: Target Keyword | G6: Target URL | H6: Live URL | I6: Status
B7: 1 | C7: https://www.classifiedads.com | D7: seo@thespeedtrain.com | E7: pooyaseo@thespeedtrain | F7: Vital mobility | G7: https://www.vitalmobility.ca/ | H7: https://www.classifiedads.com/health_wellness/c8zb7y9km3dwd | I7: Live
B8: 2 | C8: https://www.muamat.com/ | I8: Live
B9: 3 | C9: www.adsthumb.com | I9: Live
B10: 4 | C10: https://freead1.net/ | I10: Live
B11: 5 | C11: https://www.adlandpro.com | I11: Live
B13: Sr.No | C13: Website | D13: Gmail | E13: Password | F13: Target Keyword | G13: Target URL | H13: Live URL | I13: Status
B14: 1 | C14: https://qwikad.com/ | I14: Live
B15: 2 | C15: https://www.expatriates.com/ | I15: Live
B16: 3 | C16: https://www.topclassifieds.com/ | I16: Live
B17: 4 | C17: https://www.adproceed.com/ | I17: Live
B18: 5 | C18: http://www.locanto.com/ | I18: Live
B20: Sr.No | C20: Website | D20: Gmail | E20: Password | F20: Target Keyword | G20: Target URL | H20: Live URL | I20: Status
B21: 1 | C21: https://classified4u.biz/ | I21: Live
B22: 2 | C22: https://www.classifiedads.com | I22: Live
B23: 3 | C23: https://classifieds4free.biz/ | I23: Live
B25: Sr.No | C25: Website | D25: Gmail | E25: Password | F25: Target Keyword | G25: Target URL | H25: Live URL | I25: Status
B26: 1 | C26: https://www.classifiedads.com | I26: Live
B27: 2 | C27: https://www.muamat.com/ | I27: Live
B28: 3 | C28: www.adsthumb.com | I28: Live
B29: 4 | C29: https://freead1.net/ | I29: Live
B30: 5 | C30: https://www.adlandpro.com | I30: Live
B32: Sr.No | C32: Website | D32: Gmail | E32: Password | F32: Target Keyword | G32: Target URL | H32: Live URL | I32: Status
B33: 1 | C33: https://www.expatriates.com/ | I33: Live
B34: 2 | C34: https://classified4u.biz/ | I34: Live
B35: 3 | C35: https://www.adproceed.com/ | I35: Live
B36: 4 | C36: https://www.adpost4u.com | I36: Live
B37: 5 | C37: http://www.usnetads.com/ | I37: Live
B38: 6 | C38: https://MyPetAds.com/ | I38: Live
B40: Sr.No | C40: Website | D40: Gmail | E40: Password | F40: Target Keyword | G40: Target URL | H40: Live URL | I40: Status
B41: 1 | C41: https://nextfreeads.com/ | I41: Live
B42: 2 | C42: https://us.classi4u.com/ | I42: Live
B43: 3 | C43: https://GlobalClassified.net/ | I43: Live
B44: 4 | C44: https://letspostfree.com/ | I44: Live
B45: 5 | C45: https://classifieds4free.biz/ | I45: Live

Sheet Article Submission
B2: Article submission
B3: Website - https://www.vitalmobility.ca/
B6: Sr.No | C6: Website | D6: Gmail | E6: Password | F6: Target URL | G6: Live URL | H6: Status
B7: 1 | C7: https://www.diigo.com/ | D7: seo@thespeedtrain.com | E7: pooyaseo@thespeedtrain | F7: https://www.vitalmobility.ca/ | G7: https://diigo.com/0v2dxc | H7: Live
B9: Sr.No | C9: Website | D9: Gmail | E9: Password | F9: Target URL | G9: Live URL | H9: Status
B10: 1 | C10: https://www.livejournal.com/ | D10: seo@thespeedtrain.com | E10: k$br5Zs89E@wRg- | F10: https://www.vitalmobility.ca/ | G10: https://vitalmobality.livejournal.com/750.html | H10: Live
B13: Sr.No | C13: Website | D13: Gmail | E13: Password | F13: Target URL | G13: Live URL | H13: Status
B14: 1 | C14: https://medium.com/ | D14: seo@thespeedtrain.com | E14: pooyaseo@thespeedtrain | F14: https://www.vitalmobility.ca/ | G14: https://medium.com/@seo_66432/the-ultimate-guide-to-cold-therapy-machine-rentals-0d5d86c7cae3 | H14: Live
B17: Sr.No | C17: Website | D17: Gmail | E17: Password | F17: Target URL | G17: Live URL | H17: Status
B18: 1 | C18: https://click4r.com/ | D18: seo@thespeedtrain.com | E18: pooyaseo@thespeedtrain | F18: https://www.vitalmobility.ca/ | G18: https://click4r.com/posts/u/6122497/Author-Vital | H18: Live

Sheet Article Promotion
B2: Article Promotion Promotion
B3: Website - https://www.vitalmobility.ca/
B6: Sr.No | C6: Website | D6: Gmail | E6: Password | F6: Target URL | G6: Live URL | H6: Status
B7: 1 | C7: https://linktr.ee/ | D7: seo@thespeedtrain.com | E7: pooyaseo@thespeedtrain | F7: https://www.vitalmobility.ca/ | G7: https://linktr.ee/vitalmobility | H7: Live
B8: 2 | C8: https://start.me/ | D8: seo@thespeedtrain.com | E8: pooyaseo@thespeedtrain | F8: https://www.vitalmobility.ca/ | G8: https://start.me/w/RQe99m | H8: Live
B9: 3 | C9: https://www.wibki.com/ | D9: seo@thespeedtrain.com | E9: pooyaseo@thespeedtrain | F9: https://www.vitalmobility.ca/ | G9: https://wibki.com/vitalmobality?tab=SeoTheSpeedTrain# | H9: Live
B10: 4 | C10: https://www.instapaper.com/ | D10: seo@thespeedtrain.com | E10: pooyaseo@thespeedtrain | F10: https://www.vitalmobility.ca/ | G10: https://www.instapaper.com/read/1653922788 | H10: Live
B12: Sr.No | C12: Website | D12: Gmail | E12: Password | F12: Target URL | G12: Live URL | H12: Status
B13: 1 | C13: https://raindrop.io | D13: seo@thespeedtrain.com | E13: pooyaseo@thespeedtrain | F13: https://www.vitalmobility.ca/ | G13: https://raindrop.io/vitalmobality/vital-41343443 | H13: Live
B14: 2 | C14: https://contentle.com/ | D14: seo@thespeedtrain.com | E14: pooyaseo@thespeedtrain | F14: https://www.vitalmobility.ca/ | G14: https://contentle.com/vitalmobality/items | H14: Live
B15: 3 | C15: https://list.ly/ | D15: seo@thespeedtrain.com | E15: pooyaseo@thespeedtrain | F15: https://www.vitalmobility.ca/ | G15: https://list.ly/list/9U6Y-vital-mobility-medical-equipment-toronto-medical-supply-toronto-wheelchair-rental?make_list_mode=true | H15: Live
B16: 4 | C16: https://www.symbaloo.com/ | D16: seo@thespeedtrain.com | E16: pooyaseo@thespeedtrain | F16: https://www.vitalmobility.ca/ | G16: https://www.symbaloo.com/shared/AAAABV8hRZUAA41_0gNuLQ== | H16: Live
B18: Sr.No | C18: Website | D18: Gmail | E18: Password | F18: Target URL | G18: Live URL | H18: Status
B19: 1 | C19: https://papaly.com | D19: seo@thespeedtrain.com | E19: pooyaseo@thespeedtrain | F19: https://www.vitalmobility.ca/ | G19: https://papaly.com/vitalmobility/akgjq/httpswww-vitalmobility-ca | H19: Live
B20: 2 | C20: https://www.rebrandly.com/ | D20: seo@thespeedtrain.com | E20: pooyaseo@thespeedtrain | F20: https://www.vitalmobility.ca/ | G20: https://Link.Gallery/vitalmobility | H20: Live
B21: 3 | C21: https://atavi.com/ | D21: seo@thespeedtrain.com | E21: pooyaseo@thespeedtrain | F21: https://www.vitalmobility.ca/ | G21: https://atavi.com/share/whbgbnz1l9wfx | H21: Live
B22: 4 | C22: https://www.exchangle.com/ | D22: seo@thespeedtrain.com | E22: pooyaseo@thespeedtrain | F22: https://www.vitalmobility.ca/ | G22: https://www.exchangle.com/vitalmobility | H22: Live
B24: Sr.No | C24: Website | D24: Gmail | E24: Password | F24: Target URL | G24: Live URL | H24: Status
B25: 1 | C25: https://allmylinks.com/ | D25: seo@thespeedtrain.com | E25: pooyaseo@thespeedtrain | F25: https://www.vitalmobility.ca/ | G25: https://allmylinks.com/vitalmobility | H25: Live
B26: 2 | C26: https://socialrus.com/ | D26: seo@thespeedtrain.com | E26: pooyaseo@thespeedtrain | F26: https://www.vitalmobility.ca/ | G26: https://socialrus.com/story16086945/vital-mobility-medical-equipment-toronto-medical-supply-toronto-wheelchair-rental#discuss | H26: Live
B28: Sr.No | C28: Website | D28: Gmail | E28: Password | F28: Target URL | G28: Live URL | H28: Status
B29: 1 | C29: https://app.heylink.me/ | D29: seo@thespeedtrain.com | E29: pooyaseo@thespeedtrain | F29: https://www.vitalmobility.ca/ | G29: https://heylink.me/seo424 | H29: Live

Sheet Guest Post Submission
B2: Guest Post Submission
B5: Website: https://houseremovalistsmelbourne.net.au/
B9: Sr.No | C9: Submission Site | D9: Gmail Id | E9: Password | F9: Post URL | G9: Keyword | H9: Target URL | I9: Status
B10: 1 | C10: https://beforeitsnews.com/ | I10: Live

Sheet Press Release Submission
B2: Press Release Submission
B3: Website - https://www.vitalmobility.ca/
B6: Sr.No | C6: Website | D6: Gmail | E6: Password | F6: Target URL | G6: Live URL | H6: Status
B7: 1 | C7: https://www.issuewire.com/ | G7: Paid
B8: 45244
B9: Sr.No | C9: Website | D9: Gmail | E9: Password | F9: Target URL | G9: Live URL | H9: Status
B10: 1 | C10: https://www.pressnews.biz/ | D10: seo@thespeedtrain.com | E10: vital123 | F10: https://www.vitalmobility.ca/ | G10: https://pressnews.biz/@vitalmobality/vital-mobility-medical-equipment-toronto-medical-supply-toronto-wheelchair-rental-afhn4ahstxbt | H10: Live
B11: 45253
B12: Sr.No | C12: Website | D12: Gmail | E12: Password | F12: Target URL | G12: Live URL | H12: Status
B13: 1 | C13: https://express-press-release.net/ | D13: seo@thespeedtrain.com | F13: https://www.vitalmobility.ca/ | G13: In Draft | H13: Live

Sheet Web 2.0 Blog Submission
B2: Web 2.0 Submission
B3: Website - https://www.vitalmobility.ca/
B6: Sr.No | C6: Website | D6: Gmail | E6: Password | F6: Target URL | G6: Live URL | H6: Status
B7: 1 | C7: https://www.blogger.com/ | H7: Live
B9: Sr.No | C9: Website | D9: Gmail | E9: Password | F9: Target URL | G9: Live URL | H9: Status
B10: 1 | C10: https://techplanet.today/ | H10: Live
B12: Sr.No | C12: Website | D12: Gmail | E12: Password | F12: Target URL | G12: Live URL | H12: Status
B13: 1 | C13: https://www.notion.so/ | H13: Live
B15: Sr.No | C15: Website | D15: Gmail | E15: Password | F15: Target URL | G15: Live URL | H15: Status
B16: 1 | C16: https://www.reddit.com/ | H16: Live

Sheet Local Citation
B2: Local Citation submissions
B3: Website - https://www.vitalmobility.ca/
B6: Sr.No | C6: Website | D6: Gmail | E6: Password | F6: Live URL | G6: Status
B7: 1 | C7: https://www.provenexpert.com/ | D7: seo@thespeedtrain.com | E7: pooyaseo@thespeedtrain | F7: https://www.provenexpert.com/vital-mobility/?_gl=1*14rhb1t*_ga*NDYxMTA4OTA4LjE3MDM1MDU5NTc.*_ga_9JZ6KME51R*MTcwMzUwNTk1Ni4xLjEuMTcwMzUwNzQwNC42LjAuMA.. | G7: Live
B8: 2 | C8: https://www.brownbook.net/ | D8: seo@thespeedtrain.com | E8: pooyaseo@thespeedtrain | F8: https://www.brownbook.net/business/52338609/vital-mobility/ | G8: Live
B11: Sr.No | C11: Website | D11: Gmail | E11: Password | F11: Live URL | G11: Status
B12: 1 | C12: https://www.techdirectory.io | D12: seo@thespeedtrain.com | E12: pooyaseo@thespeedtrain | F12: https://www.techdirectory.io/canada/health-technology/vital-mobility | G12: Live
B13: 2 | C13: https://au.enrollbusiness.com/ | D13: seo@thespeedtrain.com | E13: pooyaseo@thespeedtrain | F13: https://au.enrollbusiness.com/BusinessProfile/6506847/Vital%20Mobility | G13: Live
B15: Sr.No | C15: Website | D15: Gmail | E15: Password | F15: Live URL | G15: Status
B16: 1 | C16: https://www.localbusinesslisting.org/ | D16: seo@thespeedtrain.com | E16: pooyaseo@thespeedtrain | F16: https://www.localbusinesslisting.org/vital-mobility | G16: Live
B17: 2 | C17: http://www.golocalezservices.com/ | D17: seo@thespeedtrain.com | E17: pooyaseo@thespeedtrain | F17: http://www.golocalezservices.com/canada/health-fitness/vital-mobility | G17: Live
B19: Sr.No | C19: Website | D19: Gmail | E19: Password | F19: Live URL | G19: Status
B20: 1 | C20: https://foursquare.com/ | D20: seo@thespeedtrain.com | E20: pooyaseo@thespeedtrain | F20: https://foursquare.com/vitalm7735738/list/vital-mobility-home-health-care-equipment-supplier | G20: Live
B23: Sr.No | C23: Website | D23: Gmail | E23: Password | F23: Live URL | G23: Status
B24: 1 | C24: https://www.cargodirectory.co/ | D24: seo@thespeedtrain.com | E24: pooyaseo@thespeedtrain | F24: https://www.cargodirectory.co/canada/health-care-services/vital-mobility | G24: Live
B25: 2 | C25: https://www.successcenter.com/ | D25: seo@thespeedtrain.com | E25: pooyaseo@thespeedtrain | F25: https://www.successcenter.com/ontario/concord/services/vital-mobility | G25: Live
B26: 3 | C26: https://www.localhomeservicepros.com | D26: seo@thespeedtrain.com | E26: pooyaseo@thespeedtrain | F26: https://www.localhomeservicepros.com/canada/health-care/vital-mobility | G26: Live
B27: 4 | C27: https://www.bestincom.com/ | D27: seo@thespeedtrain.com | E27: pooyaseo@thespeedtrain | F27: https://www.bestincom.com/canada/health-care/vital-mobility | G27: Live

Sheet Press Release Promotion
B2: Press Release Promotion
B3: Website - https://www.vitalmobility.ca/
B6: Sr.No | C6: Website | D6: Gmail | E6: Password | F6: Target URL | G6: Live URL | H6: Status
B7: 1 | C7: https://papaly.com | H7: Live
B8: 2 | C8: https://www.rebrandly.com/ | H8: Live
B9: 3 | C9: https://atavi.com/ | H9: Live
B10: 4 | C10: https://www.symbaloo.com/ | H10: Live
B12: Sr.No | C12: Website | D12: Gmail | E12: Password | F12: Target URL | G12: Live URL | H12: Status
B13: 1 | C13: https://www.exchangle.com/ | H13: Live
B14: 2 | C14: https://raindrop.io | H14: Live
B15: 3 | C15: https://www.scoop.it | H15: Live
B17: Sr.No | C17: Website | D17: Gmail | E17: Password | F17: Target URL | G17: Live URL | H17: Status
B18: 1 | C18: https://linktr.ee/ | H18: Live
B19: 2 | C19: https://start.me/ | H19: Live
B20: 3 | C20: https://www.wibki.com/ | H20: Live
B21: 4 | C21: https://allmylinks.com/ | H21: Live

Sheet Web 2.0 Blog Promotion
B2: Web 2.0 Blog Promotion
B3: Website - https://www.vitalmobility.ca/
B6: Sr.No | C6: Website | D6: Gmail | E6: Password | F6: Target URL | G6: Live URL | H6: Status
B7: 1 | C7: https://papaly.com | H7: Live
B8: 2 | C8: https://www.rebrandly.com/ | H8: Live
B9: 3 | C9: https://www.symbaloo.com/ | H9: Live
B10: 4 | C10: https://www.exchangle.com/ | H10: Live
B11: 5 | C11: https://raindrop.io | H11: Live
B13: Sr.No | C13: Website | D13: Gmail | E13: Password | F13: Target URL | G13: Live URL | H13: Status
B14: 1 | C14: https://linktr.ee/ | H14: Live
B15: 2 | C15: https://www.scoop.it/ | H15: Live
B16: 3 | C16: https://atavi.com/ | H16: Live
B17: 4 | C17: https://allmylinks.com/ | H17: Live
B19: Sr.No | C19: Website | D19: Gmail | E19: Password | F19: Target URL | G19: Live URL | H19: Status
B20: 1 | C20: https://www.instapaper.com/ | H20: Live
B21: 2 | C21: https://start.me/ | H21: Live
B22: 3 | C22: https://www.wibki.com/ | H22: Live
B23: 4 | C23: https://www.pearltrees.com/ | H23: Live
B25: Sr.No | C25: Website | D25: Gmail | E25: Password | F25: Target URL | G25: Live URL | H25: Status
B26: 1 | C26: https://papaly.com | H26: Live
B27: 2 | C27: https://www.rebrandly.com/ | H27: Live
B28: 3 | C28: https://www.symbaloo.com/ | H28: Live
B29: 4 | C29: https://www.exchangle.com/ | H29: Live
B30: 4 | C30: https://raindrop.io | H30: Live

Sheet Image Submission
B3: Image Sharing
B4: Website - https://www.vitalmobility.ca
B7: Sr.No | C7: Website | D7: Gmail | E7: Password | F7: Target Keyword | G7: Target URL | H7: Live URL | I7: Status
B8: 1 | C8: https://www.pinterest.com/ | I8: Live
B9: 2 | C9: https://www.behance.net | I9: Live
B10: 3 | C10: https://justpaste.it/ | I10: Live
B11: 4 | C11: https://gab.com/ | I11: Live
B12: 5 | C12: http://www.mediafire.com/ | I12: Live
B14: Sr.No | C14: Website | D14: Gmail | E14: Password | F14: Target Keyword | G14: Target URL | H14: Live URL | I14: Status
B15: 1 | C15: https://imgur.com/ | I15: Live
B16: 2 | C16: https://wakelet.com/ | I16: Live
B17: 3 | C17: https://www.imagevenue.com/ | I17: Live
B18: 4 | C18: https://www.diigo.com/ | I18: Live
B19: 5 | C19: https://www.tumblr.com/ | I19: Live
B24: 3 | C24: https://www.4shared.com/ | I24: Live
B25: 4 | C25: https://imgbb.com/ | I25: Live
B26: 5 | C26: https://wakelet.com/ | I26: Live
B28: 45272
B29: Sr.No | C29: Website | D29: Gmail | E29: Password | F29: Target Keyword | G29: Target URL | H29: Live URL | I29: Status
B30: 1 | C30: https://500px.com/ | I30: Live
B33: 45273
B34: Sr.No | C34: Website | D34: Gmail | E34: Password | F34: Target Keyword | G34: Target URL | H34: Live URL | I34: Status
B35: 1 | C35: https://dribbble.com/ | I35: Live
B36: 2 | C36: https://www.scoop.it/ | I36: Live
B37: 2 | C37: https://justpaste.me/ | I37: Live

Sheet Profile Creation
B2: Profile Creation
B3: Website - https://www.vitalmobility.ca/
B6: Sr.No | C6: Website | D6: Gmail | E6: Password | F6: Target Url | G6: Profile Link | H6: Status
B7: 1 | C7: https://medium.com/ | D7: seo@thespeedtrain.com | E7: pooyaseo@thespeedtrain | F7: https://www.vitalmobility.ca/ | G7: https://medium.com/@seo_66432 | H7: Live
B8: 2 | C8: https://www.behance.net/ | D8: seo@thespeedtrain.com | E8: pooyaseo@thespeedtrain | F8: https://www.vitalmobility.ca/ | G8: https://www.behance.net/vitalmobility | H8: Live
B9: 3 | C9: https://justpaste.it/ | D9: seo@thespeedtrain.com | E9: pooyaseo@thespeedtrain | F9: https://www.vitalmobility.ca/ | G9: https://justpaste.it/u/Vital_Mobility | H9: Live
B11: Sr.No | C11: Website | D11: Gmail | E11: Password | F11: Target Url | G11: Profile Link | H11: Status
B12: 1 | C12: https://imgur.com/ | D12: seo@thespeedtrain.com | E12: pooyaseo@thespeedtrain | F12: https://www.vitalmobility.ca/ | G12: https://imgur.com/gallery/otT7uU8 | H12: Live
B13: 2 | C13: https://folkd.com/ | D13: seo@thespeedtrain.com | E13: pooyaseo@thespeedtrain | F13: https://www.vitalmobility.ca/ | G13: https://folkd.com/profile/vitalmobality | H13: Live
B14: 3 | C14: https://www.tumblr.com/ | D14: seo@thespeedtrain.com | E14: pooyaseo@thespeedtrain | F14: https://www.vitalmobility.ca/ | G14: https://www.tumblr.com/hospitalbedsvit/722098665182887936/medical-equipment-supplier-rental-store-in?source=share | H14: Live
B16: Sr.No | C16: Website | D16: Gmail | E16: Password | F16: Target Url | G16: Profile Link | H16: Status
B17: 1 | C17: https://www.provenexpert.com/ | D17: seo@thespeedtrain.com | E17: pooyaseo@thespeedtrain | F17: https://www.vitalmobility.ca/ | G17: https://www.provenexpert.com/vital-mobility/?_gl=1*14rhb1t*_ga*NDYxMTA4OTA4LjE3MDM1MDU5NTc.*_ga_9JZ6KME51R*MTcwMzUwNTk1Ni4xLjEuMTcwMzUwNzQwNC42LjAuMA.. | H17: Live
B18: 2 | C18: https://www.reddit.com/ | D18: seo@thespeedtrain.com | E18: pooyaseo@thespeedtrain | F18: https://www.vitalmobility.ca/ | G18: https://www.reddit.com/user/vitalmobality/ | H18: Live
B20: Sr.No | C20: Website | D20: Gmail | E20: Password | F20: Target Url | G20: Profile Link | H20: Status
B21: 1 | C21: https://imgur.com/ | D21: seo@thespeedtrain.com | E21: pooyaseo@thespeedtrain | F21: https://www.vitalmobility.ca/ | H21: Live
B22: 2 | C22: https://voiccing.com/ | H22: Live
B23: 3 | C23: https://about.me/ | H23: Live
B26: Sr.No | C26: Website | D26: Gmail | E26: Password | F26: Target Url | G26: Profile Link | H26: Status
B27: 1 | C27: https://gitea.blesmrt.net/ | D27: seo@thespeedtrain.com | E27: pooyaseo@thespeedtrain | F27: https://www.vitalmobility.ca/ | H27: Live
B28: 2 | C28: https://land-book.com/ | H28: Live
B29: 3 | C29: https://club.vexanium.com/ | H29: Live
B30: 4 | C30: https://community.theconstructor.org/ | H30: Live
B31: 5 | C31: https://packinsider.com/ | H31: Live
B32: 6 | C32: https://www.notebook.ai/ | H32: Live

Sheet Profile Link Updation
B2: Profile Link Updation
B3: Website - https://www.vitalmobility.ca/
B6: Sr.No | C6: Website | D6: Gmail | E6: Password | F6: Profile Link | G6: Status
B7: 1 | C7: https://medium.com/ | D7: seo@thespeedtrain.com | E7: pooyaseo@thespeedtrain | F7: https://medium.com/@seo_66432 | G7: Live
B8: 2 | C8: https://www.behance.net/ | D8: seo@thespeedtrain.com | E8: pooyaseo@thespeedtrain | F8: https://www.behance.net/vitalmobility | G8: Live
B9: 3 | C9: https://justpaste.it/ | D9: seo@thespeedtrain.com | E9: pooyaseo@thespeedtrain | F9: https://justpaste.it/u/Vital_Mobility | G9: Live
B10: 4 | C10: https://imgur.com/ | D10: seo@thespeedtrain.com | E10: pooyaseo@thespeedtrain | F10: https://imgur.com/gallery/otT7uU8 | G10: Live
B12: Sr.No | C12: Website | D12: Gmail | E12: Password | F12: Profile Link | G12: Live
B13: 1 | C13: https://folkd.com/ | D13: seo@thespeedtrain.com | E13: pooyaseo@thespeedtrain | F13: https://folkd.com/profile/vitalmobality | G13: Live
B14: 2 | C14: https://www.tumblr.com/ | D14: seo@thespeedtrain.com | E14: pooyaseo@thespeedtrain | F14: https://www.tumblr.com/hospitalbedsvit/722098665182887936/medical-equipment-supplier-rental-store-in?source=share | G14: Live
B15: 3 | C15: https://www.provenexpert.com/ | D15: seo@thespeedtrain.com | E15: pooyaseo@thespeedtrain | F15: https://www.provenexpert.com/vital-mobility/?_gl=1*14rhb1t*_ga*NDYxMTA4OTA4LjE3MDM1MDU5NTc.*_ga_9JZ6KME51R*MTcwMzUwNTk1Ni4xLjEuMTcwMzUwNzQwNC42LjAuMA.. | G15: Live
B16: 4 | C16: https://www.reddit.com/ | D16: seo@thespeedtrain.com | E16: pooyaseo@thespeedtrain | F16: https://www.reddit.com/user/vitalmobality | G16: Live

Sheet Forum Submission
B2: Forum Submission
B3: Website - https://www.vitalmobility.ca/
B6: Sr.No | C6: Website | D6: Gmail | E6: Password | F6: Target Url | G6: Profile Link | H6: Status
B7: 1 | C7: https://forums.beyondunreal.com/ | H7: Live
B8: 2 | C8: https://forum.promise.com/ | H8: Live
B9: 3 | C9: https://www.warriorforum.com/ | H9: Live

Sheet SEO+SMO Conjugation
B2: SEO+SMO Conjugation
B3: Website - https://www.vitalmobility.ca/
B6: Sr.No | C6: Website | D6: Gmail | E6: Password | F6: Target Keyword | G6: Target URL | H6: Live URL | I6: Status
B7: 1 | C7: https://www.reddit.com/ | D7: seo@thespeedtrain.com | E7: vital321 | F7: vital mobility | G7: https://www.vitalmobility.ca/electric-hospital-bed.php | H7: https://www.reddit.com/r/chemicalreactiongifs/comments/1ajggs0/vitalmobility/?utm_source=share&utm_medium=web2x&context=3 | I7: Live
B8: 2 | C8: https://www.livejournal.com/ | D8: seo@thespeedtrain.com | E8: vital321 | F8: vital mobility | G8: https://www.vitalmobility.ca/electric-hospital-bed.php | H8: https://vitalmobality.livejournal.com/943.html | I8: Live
B9: 3 | C9: https://evernote.com/ | D9: seo@thespeedtrain.com | E9: vital321 | F9: vital mobility | G9: https://www.vitalmobility.ca/electric-hospital-bed.php | H9: https://www.evernote.com/shard/s630/sh/23790f0b-3d29-ddf4-bda0-a69312c445f7/C8umoHaRePm7hU1bINXkE6j8_O7E5YXsiMsr4CFihGWmTjU_dpgpKWobqQ | I9: Live
B11: Sr.No | C11: Website | D11: Gmail | E11: Password | F11: Target Keyword | G11: Target URL | H11: Live URL | I11: Status
B12: 1 | I12: Live
B13: 2 | I13: Live
B14: 3 | I14: Live
B16: Sr.No | C16: Website | D16: Gmail | E16: Password | F16: Target Keyword | G16: Target URL | H16: Live URL | I16: Status
B17: 1 | C17: https://medium.com/ | D17: seo@thespeedtrain.com | E17: vital321 | F17: vital mobility | G17: https://www.vitalmobility.ca/electric-hospital-bed.php | H17: https://medium.com/@vitalmobility/vital-mobility-c175f9b5b142 | I17: Live
B18: 2 | C18: https://www.diigo.com/ | D18: seo@thespeedtrain.com | E18: vital321 | F18: vital mobility | G18: https://www.vitalmobility.ca/electric-hospital-bed.php | H18: https://diigo.com/0v9u2q | I18: Live

Sheet Quora
B2: Quora
B3: Website - https://www.vitalmobility.ca/
B6: Sr.No | C6: Website | D6: Live URL | E6: Status
B7: 1 | C7: https://www.quora.com/ | D7: https://qr.ae/pKd9yW | E7: Live
B8: 2 | C8: https://www.quora.com/ | D8: https://qr.ae/pKd9yc | E8: Live
B10: Sr.No | C10: Website | D10: Live URL | E10: Status
B11: 1 | C11: https://www.quora.com/ | D11: https://qr.ae/pKd9sc | E11: Live
B12: 2 | C12: https://www.quora.com/ | D12: https://qr.ae/pKd9YX | E12: Live
B14: Sr.No | C14: Website | D14: Live URL | E14: Status
B15: 1 | C15: https://www.quora.com/ | D15: https://qr.ae/pKd9YP | E15: Live
B16: 2 | C16: https://www.quora.com/ | D16: https://qr.ae/pKd9Fh | E16: Live
B18: Sr.No | C18: Website | D18: Live URL | E18: Status
B19: 1 | C19: https://www.quora.com/ | D19: https://qr.ae/pKd9oj | E19: Live
B20: 2 | C20: https://www.quora.com/ | D20: https://qr.ae/pKd9PK | E20: Live
B21: 3 | C21: https://www.quora.com/ | D21: https://qr.ae/pKd9oO | E21: Live

Sheet Blog Social Bookmarking
B2: Blog Social Bookmarking
B3: Website -https://www.vitalmobility.ca/
B6: Sr.No | C6: Website | D6: Gmail | E6: Password | F6: Target URL | G6: Live URL | H6: Status
B7: 1 | C7: https://papaly.com | H7: Live
B8: 2 | C8: https://www.rebrandly.com/ | H8: Live
B9: 3 | C9: https://atavi.com/ | H9: Live
B10: 4 | C10: https://www.symbaloo.com/ | H10: Live
B11: 5 | C11: https://www.instapaper.com/ | H11: Live
B13: Sr.No | C13: Website | D13: Gmail | E13: Password | F13: Target URL | G13: Live URL | H13: Status
B14: 1 | C14: https://linktr.ee/ | H14: Live
B15: 2 | C15: https://www.scoop.it/ | H15: Live
B16: 3 | C16: https://allmylinks.com/ | H16: Live
B17: 4 | C17: https://contentle.com/ | H17: Live
B18: 5 | C18: https://www.exchangle.com/ | H18: Live
B20: Sr.No | C20: Website | D20: Gmail | E20: Password | F20: Target URL | G20: Live URL | H20: Status
B21: 1 | C21: https://start.me/ | H21: Live
B22: 2 | C22: https://www.wibki.com/ | H22: Live
B23: 3 | C23: https://raindrop.io | H23: Live
B24: 4 | C24: https://homepage.ninja/ | H24: Live
B25: 5 | C25: https://app.rebrandly.com/ | H25: Live
B27: Sr.No | C27: Website | D27: Gmail | E27: Password | F27: Target URL | G27: Live URL | H27: Status
B28: 1 | C28: https://atavi.com/ | H28: Live
B29: 2 | C29: https://www.symbaloo.com/ | H29: Live
B30: 3 | C30: https://www.instapaper.com/ | H30: Live
B31: 4 | C31: https://papaly.com | H31: Live
B32: 5 | C32: https://www.rebrandly.com/ | H32: Live

Sheet Infographic Submission
B2: Infographic Submission
B3: Website - https://www.vitalmobility.ca/
B6: Sr.No | C6: Website | D6: Gmail | E6: Password | F6: Target URL | G6: Live URL | H6: Status
B7: 1 | C7: https://www.pinterest.com | D7: seo@thespeedtrain.com | E7: pooyaseo@thespeedtrain | F7: https://www.vitalmobility.ca/ | G7: https://pin.it/75p05GLXA | H7: Live
B8: 2 | C8: https://www.4shared.com/ | D8: seo@thespeedtrain.com | E8: pooyaseo@thespeedtrain | F8: https://www.vitalmobility.ca/ | G8: https://www.4shared.com/s/flMlRJo0Cfa | H8: Live
B9: 3 | C9: https://app.mediafire.com/ | D9: seo@thespeedtrain.com | E9: pooyaseo@thespeedtrain | F9: https://www.vitalmobility.ca/ | G9: https://www.mediafire.com/file/mx34z35w86rjtxo/Green_Modern_Medical_Service_Poster.pdf/file | H9: Live
B10: 4 | C10: https://www.dropbox.com/ | D10: seo@thespeedtrain.com | E10: pooyaseo@thespeedtrain | F10: https://www.vitalmobility.ca/ | G10: https://www.dropbox.com/scl/fi/bupldepe5h15dppl6osbm/Green-Modern-Medical-Service-Poster.pdf?rlkey=myjt958b8nr2i0la8k5jx5poy&dl=0 | H10: Live
B11: 5 | C11: https://postimg.cc/ | D11: seo@thespeedtrain.com | E11: sPpxxZwFQKVr | F11: https://www.vitalmobility.ca/ | G11: https://i.postimg.cc/44Qv6YmQ/Green-Modern-Medical-Service-Poster.png | H11: Live
B13: Sr.No | C13: Website | D13: Gmail | E13: Password | F13: Target URL | G13: Live URL | H13: Status
B14: 1 | C14: https://wakelet.com/ | D14: seo@thespeedtrain.com | E14: pooyaseo@thespeedtrain | F14: https://www.vitalmobility.ca/ | G14: https://wakelet.com/i/invite?code=3ruzahid | H14: Live
B15: 2 | C15: https://photos.google.com/ | D15: seo@thespeedtrain.com | E15: pooyaseo@thespeedtrain | F15: https://www.vitalmobility.ca/ | G15: https://photos.app.goo.gl/RTej94ZqSjCqJB4d7 | H15: Live
B16: 3 | C16: https://docs.zoho.com | D16: seo@thespeedtrain.com | E16: pooyaseo@thespeedtrain | F16: https://www.vitalmobility.ca/ | G16: https://workdrive.zoho.com/file/4594wf2e1a707178a4411966a01acc30e5c42 | H16: Live
B17: 4 | C17: https://www.edocr.com/ | D17: seo@thespeedtrain.com | E17: pooyaseo@thespeedtrain | F17: https://www.vitalmobility.ca/ | G17: https://www.edocr.com/v/9x7gmxb5/vitalmobility1/green-modern-medical-service-poster | H17: Live
B18: 5 | C18: https://www.diigo.com/ | D18: seo@thespeedtrain.com | E18: pooyaseo@thespeedtrain | F18: https://www.vitalmobility.ca/ | G18: https://diigo.com/0v7l0r | H18: Live
B20: Sr.No | C20: Website | D20: Gmail | E20: Password | F20: Target URL | G20: Live URL | H20: Status
B21: 1 | C21: https://www.tumblr.com/ | D21: seo@thespeedtrain.com | E21: pooyaseo@thespeedtrain | F21: https://www.vitalmobility.ca/ | G21: https://www.tumblr.com/vitalmobality/740949560387633152?source=share | H21: Live
B22: 2 | C22: https://www.4shared.com/ | D22: seo@thespeedtrain.com | E22: pooyaseo@thespeedtrain | F22: https://www.vitalmobility.ca/ | G22: https://www.4shared.com/s/flMlRJo0Cfa | H22: Live
B23: 3 | C23: https://photos.google.com/ | D23: seo@thespeedtrain.com | E23: pooyaseo@thespeedtrain | F23: https://www.vitalmobility.ca/ | G23: https://photos.app.goo.gl/RTej94ZqSjCqJB4d7 | H23: Live

Sheet Infographic Promotion
B2: Infographic Submission
B3: Website - https://www.vitalmobility.ca/
B6: Sr.No | C6: Website | D6: Gmail | E6: Password | F6: Target URL | G6: Live URL | H6: Status
B7: 1 | C7: https://justpaste.it/ | D7: seo@thespeedtrain.com | E7: pooyaseo@thespeedtrain | F7: https://www.vitalmobility.ca/ | G7: https://jpst.it/3zpeY | H7: Live
B8: 2 | C8: https://www.tumblr.com | D8: seo@thespeedtrain.com | E8: pooyaseo@thespeedtrain | F8: https://www.vitalmobility.ca/ | G8: https://www.tumblr.com/vitalmobality/741044396498272256/vital-mobility-medical-equipment-toronto?source=share | H8: Live
B9: 3 | C9: https://www.pearltrees.com | D9: seo@thespeedtrain.com | E9: pooyaseo@thespeedtrain | F9: https://www.vitalmobility.ca/ | G9: https://www.pearltrees.com/vitalmoility | H9: Live
B10: 4 | C10: https://www.scribd.com | D10: seo@thespeedtrain.com | E10: pooyaseo@thespeedtrain | F10: https://www.vitalmobility.ca/ | G10: https://www.scribd.com/document/702727975/Blue-and-White-Home-based-Health-Service-Instagram-Post-1 | H10: Live
B12: Sr.No | C12: Website | D12: Gmail | E12: Password | F12: Target URL | G12: Live URL | H12: Status
B13: 1 | C13: https://wakelet.com | D13: seo@thespeedtrain.com | E13: pooyaseo@thespeedtrain | F13: https://www.vitalmobility.ca/ | G13: https://wakelet.com/wake/n2JuUciEJb21-Dx7oZTsR | H13: Live
B14: 2 | C14: https://www.diigo.com | D14: seo@thespeedtrain.com | E14: pooyaseo@thespeedtrain | F14: https://www.vitalmobility.ca/ | G14: https://www.diigo.com/user/vitalmoblity | H14: Live
B15: 3 | C15: https://imgbb.com/ | D15: seo@thespeedtrain.com | E15: pooyaseo@thespeedtrain | F15: https://www.vitalmobility.ca/ | G15: https://vitalmobility.imgbb.com/ | H15: Live
B16: 4 | C16: https://500px.com/ | D16: seo@thespeedtrain.com | E16: pooyaseo@thespeedtrain | F16: https://www.vitalmobility.ca/ | G16: https://500px.com/photo/1084798718/blue-and-white-home-based-health-service-instagram-post-1-by-vital-mobility | H16: Live

Sheet PDF Submission
B2: PDF Submission
B3: Website - https://www.vitalmobility.ca/
B6: Sr.No | C6: Website | D6: Gmail | E6: Password | F6: Target URL | G6: Live URL | H6: Status
B7: 1 | C7: https://www.4shared.com/ | D7: seo@thespeedtrain.com | E7: vital321 | F7: https://www.vitalmobility.ca/electric-hospital-bed.php | G7: https://www.4shared.com/s/fNk3PmP3gge | H7: Live
B8: 2 | C8: https://files.fm/ | D8: seo@thespeedtrain.com | E8: vital321 | F8: https://www.vitalmobility.ca/electric-hospital-bed.php | G8: https://files.fm/u/kr8kvkn4rk | H8: Live
B9: 3 | C9: https://www.diigo.com/ | D9: seo@thespeedtrain.com | E9: vital321 | F9: https://www.vitalmobility.ca/electric-hospital-bed.php | G9: https://diigo.com/0v9u2q | H9: Live
B12: Sr.No | C12: Website | D12: Gmail | E12: Password | F12: Target URL | G12: Live URL | H12: Status
B13: 1 | C13: https://www.slideserve.com/ | D13: seo@thespeedtrain.com | E13: vital321 | F13: https://www.vitalmobility.ca/electric-hospital-bed.php | G13: https://www.slideserve.com/Seo517/blue-illustration-medical-service-flyer | H13: Live
B14: 2 | C14: https://issuu.com/ | D14: seo@thespeedtrain.com | E14: vital321 | F14: https://www.vitalmobility.ca/electric-hospital-bed.php | G14: https://issuu.com/vitalmobility1/docs/blue_illustration_medical_service_flyer | H14: Live
B15: 3 | C15: https://houseremovalists22.dropmark.com/ | D15: seo@thespeedtrain.com | E15: vital321 | F15: https://www.vitalmobility.ca/electric-hospital-bed.php | G15: https://vitalmobility1.dropmark.com/1638291 | H15: Live

Sheet PDF Promotion
B2: PDF Promotion
B3: Website - https://www.vitalmobility.ca/
B6: Sr.No | C6: Website | D6: Gmail | E6: Password | F6: Target URL | G6: Live URL | H6: Status
B7: 1 | C7: https://www.scoop.it/ | H7: Live
B8: 2 | C8: https://www.instapaper.com | H8: Live
B9: 3 | C9: https://start.me/ | H9: Live
B10: 4 | C10: https://www.wibki.com/ | H10: Live
B12: Sr.No | C12: Website | D12: Gmail | E12: Password | F12: Target URL | G12: Live URL | H12: Status
B13: 1 | C13: https://papaly.com | H13: Live
B14: 2 | C14: https://www.rebrandly.com/ | H14: Live
B15: 3 | C15: https://atavi.com/ | H15: Live
B16: 4 | C16: https://www.symbaloo.com/ | H16: Live
B17: 5 | C17: https://www.instapaper.com/ | H17: Live
B19: Sr.No | C19: Website | D19: Gmail | E19: Password | F19: Target URL | G19: Live URL | H19: Status
B20: 1 | C20: https://linktr.ee/ | H20: Live
B21: 2 | C21: https://raindrop.io | H21: Live
B22: 3 | C22: https://contentle.com/ | H22: Live
B23: 4 | C23: https://www.exchangle.com/ | H23: Live
B24: 5 | C24: https://list.ly/ | H24: Live
B26: 45273
B27: Sr.No | C27: Website | D27: Gmail | E27: Password | F27: Target URL | G27: Live URL | H27: Status
B28: 1 | C28: https://www.instapaper.com/ | H28: Live
B29: 2 | C29: https://www.diigo.com/ | H29: Live
B30: 3 | C30: https://flipboard.com/ | H30: Live
B31: 4 | C31: https://manylink.co/ | H31: Live
B32: 5 | C32: https://papaly.com/ | H32: Live
B33: 6 | C33: https://folkd.com/ | H33: Live
B34: 7 | C34: https://heylink.me/ | H34: Live
B35: 8 | C35: https://linktr.ee/ | H35: Live
B36: 9 | C36: https://atavi.com/ | H36: Live
B37: 10 | C37: https://symbaloo.page.link/ | H37: Live
B38: 11
B39: 12
B40: 13
B41: 14 | H41: Live
B42: 15 | H42: Live

Sheet PPT Submission
B2: PPT Submission
B3: Website - https://www.vitalmobility.ca/
B6: Sr.No | C6: Website | D6: Gmail | E6: Password | F6: Target URL | G6: Live URL | H6: Status
B7: 1 | C7: https://www.dropbox.com | D7: seo@thespeedtrain.com | E7: vital321 | F7: https://www.vitalmobility.ca/electric-hospital-bed.php | G7: https://www.dropbox.com/scl/fi/vco48a5h0jrwgvr6fd9mj/Blue-Illustration-Medical-Service-Flyer.pdf?rlkey=lty6lhnck05erh8ruv1u3cjsv&dl=0 | H7: Live
B8: 2 | C8: https://www.slideserve.com | D8: seo@thespeedtrain.com | E8: vital321 | F8: https://www.vitalmobility.ca/electric-hospital-bed.php | G8: https://www.slideserve.com/Seo517/blue-illustration-medical-service-flyer-12893423 | H8: Live
B9: 3 | C9: https://www.mediafire.com/ | D9: seo@thespeedtrain.com | E9: vital321 | F9: https://www.vitalmobility.ca/electric-hospital-bed.php | G9: https://www.mediafire.com/file/z08m4bfmg8ef65v/Blue+Illustration+Medical+Service+Flyer.pdf/file | H9: Live

Sheet PPT Promotion
B2: PPT Promotion
B3: Website - https://www.vitalmobility.ca/
B6: Sr.No | C6: Website | D6: Gmail | E6: Password | F6: Target URL | G6: Live URL | H6: Status
B7: 1 | C7: https://linktr.ee/ | H7: Live
B8: 2 | C8: https://www.scoop.it/ | H8: Live
B9: 3 | C9: https://contentle.com/ | H9: Live
B10: 4 | C10: https://www.exchangle.com/ | H10: Live
B11: 5 | C11: https://atavi.com/ | H11: Live
B13: Sr.No | C13: Website | D13: Gmail | E13: Password | F13: Target URL | G13: Live URL | H13: Status
B14: 1 | C14: https://www.scoop.it/ | H14: Live
B15: 2 | C15: https://www.instapaper.com | H15: Live
B16: 3 | C16: https://start.me/ | H16: Live
B17: 4 | C17: https://www.wibki.com/ | H17: Live
B18: 5 | C18: https://raindrop.io | H18: Live
B20: Sr.No | C20: Website | D20: Gmail | E20: Password | F20: Target URL | G20: Live URL | H20: Status
B21: 1 | C21: https://papaly.com | H21: Live
B22: 2 | C22: https://www.rebrandly.com/ | H22: Live
B23: 3 | C23: https://list.ly/ | H23: Live
B24: 4 | C24: https://www.symbaloo.com/ | H24: Live
B25: 5 | C25: https://www.pearltrees.com/r | H25: Live

Sheet Blog Comment
B2: Blog Comment
B3: Website - https://www.vitalmobility.ca/
B6: Sr.No | C6: Website | D6: Target Url | E6: Live Link | F6: Status
B7: 1 | C7: https://www.getngoremovals.com.au/ | F7: Pending
B8: 2 | C8: https://melbournemoverspackers.com.au/ | F8: Pending
B9: 3 | C9: https://homemove.com.au/ | F9: Pending
B10: 4 | C10: https://movermelbourne.com.au/ | F10: Pending
B11: 5 | C11: https://hafizamovers.com.au/ | F11: Pending
B13: Sr.No | C13: Website | D13: Target Url | E13: Live Link | F13: Status
B14: 1 | C14: https://www.dawsonmoving.com.au/ | F14: Pending
B15: 2 | C15: https://www.dawson.sharptest.com.au/ | F15: Pending
B16: 3 | C16: https://mistermoverblog.wordpress.com/ | F16: Pending
B17: 4 | C17: https://www.austate.com.au/ | F17: Pending
B18: 5 | C18: https://www.jdmovers.com.au/ | F18: Pending
B20: Sr.No | C20: Website | D20: Target Url | E20: Live Link | F20: Status
B21: 1 | C21: https://sunshineremovals.com.au/ | F21: Pending | G21: https://prnt.sc/SmtlyhhYUmz1
B22: 2 | C22: https://melbournestarmovers.com.au/ | F22: Pending
B23: 3 | C23: https://www.melbournehouseremovalists.com.au/ | F23: Pending
B24: 4 | C24: https://menthatmove.com/ | F24: Pending
B25: 5 | C25: https://removalistsmelbourn.weebly.com/ | F25: Live

Sheet Directory Submission
B2: Directory Submission
B3: Website - https://www.vitalmobility.ca/
B6: Sr.No | C6: Website | D6: Gmail | E6: Password | F6: Live URL | G6: Status
B7: 1 | C7: https://www.247webdirectory.com/ | G7: Submit
B8: 2 | C8: https://abstractdirectory.net/ | G8: Live
B9: 3 | C9: https://activdirectory.net/ | G9: Submit
B10: 4 | C10: https://www.bing-directory.com | G10: Submit
B11: 5 | C11: http://www.businessfreedirectory.com/ | G11: Submit
B13: Sr.No | C13: Website | D13: Gmail | E13: Password | F13: Live URL | G13: Status
B14: 1 | C14: https://www.expansiondirectory.com/ | G14: Live
B15: 2 | C15: https://www.bluebook-directory.com/ | G15: Live
B16: 3 | C16: https://craigslistdirectory.net/ | G16: Live
B17: 4 | C17: https://directory6.org/ | G17: Live

Sheet Video submission
B2: Video Submission
B3: Website - https://www.vitalmobility.ca/
B6: Sr.No | C6: Website | D6: Gmail | E6: Password | F6: Target URL | G6: Live URL | H6: Status
B7: 1 | C7: https://www.tumblr.com/ | H7: Live
B8: 2 | C8: https://www.4shared.com/ | H8: Live
B9: 3 | C9: https://vimeo.com/ | H9: Live
B10: 4 | C10: https://www.pearltrees.com/ | H10: Live
B11: 5 | C11: https://gab.com | H11: Live

Sheet Audio Sharing 
B2: Audio Sharing
B3: Website - https://www.vitalmobility.ca/
B6: Sr.No | C6: Website | D6: Gmail | E6: Password | F6: Target Keyword | G6: Live URL | H6: Status
B7: 1 | C7: https://www.reverbnation.com | H7: Live
B8: 2 | C8: https://podbean.com/ | H8: Live
B9: 3 | C9: https://www.4shared.com/ | H9: Live
B10: 4 | C10: https://www.mediafire.com/ | H10: Live

Sheet SEO Plan
A3: Month 1 - Initial Setup and Optimization
A5: Week | B5: Task | C5: On-Page SEO | D5: Off-Page SEO | E5: Technical SEO | F5: Content Writing
A6: 1 | B6: Conduct market research | F6: Updating previous content
A7: 2 | B7: Set up website and optimize for SEO | C7: Optimize titles, meta descriptions, URLs | E7: Optimize site speed, site structure, etc.
A8: 3 | B8: Keyword research and analysis | C8: Identify target keywords
A9: 4 | B9: Monitor website performance | C9: Analyze initial SEO results | E9: Identify and fix technical issues
B10: descriptions, URLs | D10: site structure, etc.
A11: Month 2 - Content Development and On-Page SEO
A13: Week | B13: Task | C13: On-Page SEO | D13: Off-Page SEO | E13: Technical SEO | F13: Content Writing
A14: 5 | B14: Develop content strategy and produce content | C14: Optimize content for keywords, headings | D14: Get 100 Backlinks to Main Home page to increase authority | F14: High Quality 15 ArƟcles with valuable content (Recommended length 1500+ words)
A15: 6 | B15: Continue to produce high-quality content | C15: Optimize content for keywords, headings | D15:  Get 30 Profile Backlinks to homepage | F15: 15 more(optional)
B16: Optimize content for | D16:  Get 30 Forum Backlinks to homepage (HIGH DA Niche relevant)
A17: Month 3 - Content Optimization and Off-Page SEO | B17: keywords, headings, | D17:  Get 10 Social Bookmarking to homepage
D18: Extra commenƟng backlinks 50 these are just to look organic
A19: Week | B19: Task | C19: On-Page SEO | D19: Off-Page SEO | E19: Technical SEO
A20: 7 | B20: Optimize existing content for SEO | C20: Revise and improve existing content | F20: High Quality 15 ArƟcles with commercial content (Recommended length 1500+ words)
A21: 8 | B21: Begin building backlinks | D21: Start building quality backlinks
A22: 9 | B22: Monitor and analyze backlink performance | D22: Track backlink quality and impact
B23: Optimize content for | D23:  15 Guest Post on website with DA, DR 50+ Minimum Traffic 2k+ (30 Links)
A24: Month 4 - Continuous Improvement | B24: keywords, headings, | D24: Get 100 Backlinks to Main Home page to increase authority
A26: Week | B26: Task | C26: On-Page SEO | D26: Off-Page SEO | E26: Technical SEO
A27: 10 | B27: Monitor and adjust SEO strategy | C27: Update strategy based on results | E27: Identify and resolve technical issues | F27: High Quality 15 ArƟcles with valuable content (Recommended length 1500+ words)
A28: 11 | B28: Content audit and optimization | C28: Review and optimize existing content
A29: 12 | B29: Backlink audit and outreach | C29: Review and improve backlink profile | D29: Continue building quality backlinks
B30: keywords, headings,
A31: Months 5-6 - Ongoing Optimization and Growth
A33: Repeat the tasks from Month 4 while continuing to monitor, optimize, and build on your SEO efforts.

Sheet 📊  Overview
C1: Overview
A2: 📈 | B2: Pages | C2: Checkpoints | D2: Can be Improved | E2: To Do | F2: Improved | G2: % | H2: % | I2: Progress Bar | J2: Factor | K2: Page Significance
B3: 🚨 General Website | C3: =COUNTIF(INDIRECT($B3&"!$A:$A"),TRUE)+COUNTIF(INDIRECT($B3&"!$A:$A"),FALSE) -> #REF! | D3: =COUNTIF(INDIRECT($B3&"!$E:$E"),"Bad")+COUNTIF(INDIRECT($B3&"!$E:$E"),"Could be Better") -> #REF! | E3: =COUNTIFS(INDIRECT($B3&"!$A:$A"),TRUE,INDIRECT($B3&"!$E:$E"),"Bad")+COUNTIFS(INDIRECT($B3&"!$A:$A"),FALSE,INDIRECT($B3&"!$E:$E"),"Could be Better") -> #REF! | F3: =COUNTIF(INDIRECT($B3&"!$A:$A"),TRUE) -> #REF! | G3: =IFERROR(F3/C3,0) -> 0 | H3: 1 | I3: =IFERROR(__xludf.DUMMYFUNCTION("SPARKLINE(G3:H3,{""charttype"",""bar"";""max"",1;""color1"",""fbcb75"";""color2"",""#eeeeee""})"),"") | J3: 3 | K3: =IFERROR(__xludf.DUMMYFUNCTION("SPARKLINE(J3,{""charttype"",""bar"";""max"",5;""min"",1;""color1"",""fbcb75""})"),"")
B4: 🏠 Home Page | C4: =COUNTIF(INDIRECT($B4&"!$A:$A"),TRUE)+COUNTIF(INDIRECT($B4&"!$A:$A"),FALSE) -> #REF! | D4: =COUNTIF(INDIRECT($B4&"!$E:$E"),"Bad")+COUNTIF(INDIRECT($B4&"!$E:$E"),"Could be Better") -> #REF! | E4: =COUNTIFS(INDIRECT($B4&"!$A:$A"),TRUE,INDIRECT($B4&"!$E:$E"),"Bad")+COUNTIFS(INDIRECT($B4&"!$A:$A"),FALSE,INDIRECT($B4&"!$E:$E"),"Could be Better") -> #REF! | F4: =COUNTIF(INDIRECT($B4&"!$A:$A"),TRUE) -> #REF! | G4: =IFERROR(F4/C4,0) -> 0 | H4: 1 | I4: =IFERROR(__xludf.DUMMYFUNCTION("SPARKLINE(G4:H4,{""charttype"",""bar"";""max"",1;""color1"",""fbcb75"";""color2"",""#eeeeee""})"),"") | J4: 2 | K4: =IFERROR(__xludf.DUMMYFUNCTION("SPARKLINE(J4,{""charttype"",""bar"";""max"",5;""min"",1;""color1"",""fbcb75""})"),"")
B5: 📰 Landing Page | C5: =COUNTIF(INDIRECT($B5&"!$A:$A"),TRUE)+COUNTIF(INDIRECT($B5&"!$A:$A"),FALSE) -> #REF! | D5: =COUNTIF(INDIRECT($B5&"!$E:$E"),"Bad")+COUNTIF(INDIRECT($B5&"!$E:$E"),"Could be Better") -> #REF! | E5: =COUNTIFS(INDIRECT($B5&"!$A:$A"),TRUE,INDIRECT($B5&"!$E:$E"),"Bad")+COUNTIFS(INDIRECT($B5&"!$A:$A"),FALSE,INDIRECT($B5&"!$E:$E"),"Could be Better") -> #REF! | F5: =COUNTIF(INDIRECT($B5&"!$A:$A"),TRUE) -> #REF! | G5: =IFERROR(F5/C5,0) -> 0 | H5: 1 | I5: =IFERROR(__xludf.DUMMYFUNCTION("SPARKLINE(G5:H5,{""charttype"",""bar"";""max"",1;""color1"",""fbcb75"";""color2"",""#eeeeee""})"),"") | J5: 3 | K5: =IFERROR(__xludf.DUMMYFUNCTION("SPARKLINE(J5,{""charttype"",""bar"";""max"",5;""min"",1;""color1"",""fbcb75""})"),"")
B6: 🏪 Category Page | C6: =COUNTIF(INDIRECT($B6&"!$A:$A"),TRUE)+COUNTIF(INDIRECT($B6&"!$A:$A"),FALSE) -> #REF! | D6: =COUNTIF(INDIRECT($B6&"!$E:$E"),"Bad")+COUNTIF(INDIRECT($B6&"!$E:$E"),"Could be Better") -> #REF! | E6: =COUNTIFS(INDIRECT($B6&"!$A:$A"),TRUE,INDIRECT($B6&"!$E:$E"),"Bad")+COUNTIFS(INDIRECT($B6&"!$A:$A"),FALSE,INDIRECT($B6&"!$E:$E"),"Could be Better") -> #REF! | F6: =COUNTIF(INDIRECT($B6&"!$A:$A"),TRUE) -> #REF! | G6: =IFERROR(F6/C6,0) -> 0 | H6: 1 | I6: =IFERROR(__xludf.DUMMYFUNCTION("SPARKLINE(G6:H6,{""charttype"",""bar"";""max"",1;""color1"",""fbcb75"";""color2"",""#eeeeee""})"),"") | J6: 5 | K6: =IFERROR(__xludf.DUMMYFUNCTION("SPARKLINE(J6,{""charttype"",""bar"";""max"",5;""min"",1;""color1"",""fbcb75""})"),"")
B7: 🧵 Product Page | C7: =COUNTIF(INDIRECT($B7&"!$A:$A"),TRUE)+COUNTIF(INDIRECT($B7&"!$A:$A"),FALSE) -> #REF! | D7: =COUNTIF(INDIRECT($B7&"!$E:$E"),"Bad")+COUNTIF(INDIRECT($B7&"!$E:$E"),"Could be Better") -> #REF! | E7: =COUNTIFS(INDIRECT($B7&"!$A:$A"),TRUE,INDIRECT($B7&"!$E:$E"),"Bad")+COUNTIFS(INDIRECT($B7&"!$A:$A"),FALSE,INDIRECT($B7&"!$E:$E"),"Could be Better") -> #REF! | F7: =COUNTIF(INDIRECT($B7&"!$A:$A"),TRUE) -> #REF! | G7: =IFERROR(F7/C7,0) -> 0 | H7: 1 | I7: =IFERROR(__xludf.DUMMYFUNCTION("SPARKLINE(G7:H7,{""charttype"",""bar"";""max"",1;""color1"",""fbcb75"";""color2"",""#eeeeee""})"),"") | J7: 5 | K7: =IFERROR(__xludf.DUMMYFUNCTION("SPARKLINE(J7,{""charttype"",""bar"";""max"",5;""min"",1;""color1"",""fbcb75""})"),"")
B8: 🛒 Add to Cart Page | C8: =COUNTIF(INDIRECT($B8&"!$A:$A"),TRUE)+COUNTIF(INDIRECT($B8&"!$A:$A"),FALSE) -> #REF! | D8: =COUNTIF(INDIRECT($B8&"!$E:$E"),"Bad")+COUNTIF(INDIRECT($B8&"!$E:$E"),"Could be Better") -> #REF! | E8: =COUNTIFS(INDIRECT($B8&"!$A:$A"),TRUE,INDIRECT($B8&"!$E:$E"),"Bad")+COUNTIFS(INDIRECT($B8&"!$A:$A"),FALSE,INDIRECT($B8&"!$E:$E"),"Could be Better") -> #REF! | F8: =COUNTIF(INDIRECT($B8&"!$A:$A"),TRUE) -> #REF! | G8: =IFERROR(F8/C8,0) -> 0 | H8: 1 | I8: =IFERROR(__xludf.DUMMYFUNCTION("SPARKLINE(G8:H8,{""charttype"",""bar"";""max"",1;""color1"",""fbcb75"";""color2"",""#eeeeee""})"),"") | J8: 4 | K8: =IFERROR(__xludf.DUMMYFUNCTION("SPARKLINE(J8,{""charttype"",""bar"";""max"",5;""min"",1;""color1"",""fbcb75""})"),"")
B9: 💳 Checkout Page | C9: =COUNTIF(INDIRECT($B9&"!$A:$A"),TRUE)+COUNTIF(INDIRECT($B9&"!$A:$A"),FALSE) -> #REF! | D9: =COUNTIF(INDIRECT($B9&"!$E:$E"),"Bad")+COUNTIF(INDIRECT($B9&"!$E:$E"),"Could be Better") -> #REF! | E9: =COUNTIFS(INDIRECT($B9&"!$A:$A"),TRUE,INDIRECT($B9&"!$E:$E"),"Bad")+COUNTIFS(INDIRECT($B9&"!$A:$A"),FALSE,INDIRECT($B9&"!$E:$E"),"Could be Better") -> #REF! | F9: =COUNTIF(INDIRECT($B9&"!$A:$A"),TRUE) -> #REF! | G9: =IFERROR(F9/C9,0) -> 0 | H9: 1 | I9: =IFERROR(__xludf.DUMMYFUNCTION("SPARKLINE(G9:H9,{""charttype"",""bar"";""max"",1;""color1"",""fbcb75"";""color2"",""#eeeeee""})"),"") | J9: 5 | K9: =IFERROR(__xludf.DUMMYFUNCTION("SPARKLINE(J9,{""charttype"",""bar"";""max"",5;""min"",1;""color1"",""fbcb75""})"),"")
B10: 🙏 Thank You Page | C10: =COUNTIF(INDIRECT($B10&"!$A:$A"),TRUE)+COUNTIF(INDIRECT($B10&"!$A:$A"),FALSE) -> #REF! | D10: =COUNTIF(INDIRECT($B10&"!$E:$E"),"Bad")+COUNTIF(INDIRECT($B10&"!$E:$E"),"Could be Better") -> #REF! | E10: =COUNTIFS(INDIRECT($B10&"!$A:$A"),TRUE,INDIRECT($B10&"!$E:$E"),"Bad")+COUNTIFS(INDIRECT($B10&"!$A:$A"),FALSE,INDIRECT($B10&"!$E:$E"),"Could be Better") -> #REF! | F10: =COUNTIF(INDIRECT($B10&"!$A:$A"),TRUE) -> #REF! | G10: =IFERROR(F10/C10,0) -> 0 | H10: 1 | I10: =IFERROR(__xludf.DUMMYFUNCTION("SPARKLINE(G10:H10,{""charttype"",""bar"";""max"",1;""color1"",""fbcb75"";""color2"",""#eeeeee""})"),"") | J10: 3 | K10: =IFERROR(__xludf.DUMMYFUNCTION("SPARKLINE(J10,{""charttype"",""bar"";""max"",5;""min"",1;""color1"",""fbcb75""})"),"")
B11: Total | C11: =SUM(C3:C10) -> #REF! | D11: =SUM(D3:D10) -> #REF! | E11: =SUM(E3:E10) -> #REF! | F11: =SUM(F3:F10) -> #REF! | G11: =IFERROR(F11/C11,0) -> 0 | H11: 1 | I11: =IFERROR(__xludf.DUMMYFUNCTION("SPARKLINE(G11:H11,{""charttype"",""bar"";""max"",1;""color1"",""180c56"";""color2"",""#eeeeee""})"),"")
A13: 🔥 | B13: Instantly Access ALL our Products + The Whitelabel License for FREE here👇 We are gifting all our products and the license to whitelabel them to the first 1000 members who join our private membership. Click here if you'd like to take the all our products for a test drive!
A15: 🛍️ | B15: Conversion Rate Optimiation SOPs | L15: SOP
A16: FALSE | B16: SOP 007: How to Generate the Necessary Legal Policies for Your Shopify Store | L16: SOP
A17: FALSE | B17: SOP 005: How to Build a Customized Knowledge Base with HelpDocs | L17: SOP
A18: FALSE | B18: SOP 018: How to Build a Branded Knowledge Base Using Help Scout | L18: SOP
A19: FALSE | B19: SOP 022: How to Use Optimizely to Set up and Analyze A/B Tests on Your Site | L19: SOP
A20: FALSE | B20: SOP 024: A Guide to Increasing Your Shopify Site’s Speed | L20: SOP
A21: FALSE | B21: SOP 023: How to Use Convert to Set Up and Analyze A/B Tests on Your Site | L21: SOP
A22: FALSE | B22: SOP 027: How to Use Shopify's Multi-language Feature | L22: SOP
A23: FALSE | B23: SOP 028: Setting up the BOGO (Buy One Get One) Feature on Shopify | L23: SOP
A24: FALSE | B24: SOP 029: Syncing Discounts to Sales Channels in Shopify | L24: SOP
A25: FALSE | B25: SOP 030: Conducting a URL Audit on Your Site | L25: SOP
A26: FALSE | B26: SOP 031: Exporting Discount Codes in Shopify | L26: SOP
A27: FALSE | B27: SOP 032: Pre-filling Customer Information in Shopify | L27: SOP
... A50: FALSE | B50: SOP 266: A Guide to Optimizing your Emails for Dark Mode | L50: SOP
A52: 🛍️ | B52: **Bonus** - 30 Email Marketing SOPs | L52: SOP
A53: FALSE | B53: SOP 400: How to Build An Effective Welcome Flow Series on Klaviyo | L53: SOP 400
A54: FALSE | B54: SOP 228: Maximizing Conversions with an Abandoned Cart Flow in Klaviyo | L54: SOP 201
A55: FALSE | B55: SOP 229: How to Set a Successful Browse Abandonment Flow on Klaviyo | L55: SOP 229
A56: FALSE | B56: SOP 230: Optimizing Customer Retention with a First-Time Post-Purchase Flow on Klaviyo | L56: SOP 230
A57: FALSE | B57: SOP 231: Maximizing Repeat Business with a Post-Purchase Returning Flow on Klaviyo | L57: SOP 231
A58: FALSE | B58: SOP 232: Regaining Lost Customers with a Win-Back Flow on Klaviyo | L58: SOP 232
A59: FALSE | B59: SOP 233: Boosting Repeat Business with a Replenishment Flow on Klaviyo | L59: SOP 233
A60: FALSE | B60: SOP 234: Encouraging Customer Reviews with a Review Request Flow on Klaviyo | L60: SOP 234
A61: FALSE | B61: SOP 235: Setting Up an Order Shipment Flow on Klaviyo to Keep Your Customers Informed | L61: SOP 235
A62: FALSE | B62: SOP 236: Building Customer Loyalty by Setting a Loyalty Flow on Klaviyo | L62: SOP 236
A63: FALSE | B63: SOP 237: Setting Up a Dedicated Sending Domain to Enhance Email Deliverability | L63: SOP 237
A64: FALSE | B64: SOP 241: A Guide to Creating a BIMI | L64: SOP 241
... A83: FALSE | B83: SOP 256: Adding Dynamic Banners to Your Emails | L83: SOP 256

Sheet 🚨 General Website
B1: General Website Checklist
A2: 🚨 | B2: General Website | C2: Desktop Example | D2: Mobile Example | E2: Status | F2: Factor | G2: Measure of Imporance | H2: Priority
A3: 🛍️ | B3: Header
A4: FALSE | B4: On hover, the empty cart widget displays the "Shop our best-sellers" button. | C4: Case | D4: Case | E4: To Do | F4: =IF(E4="Not Relevant","",IF(E4="Good","",IF(E4="Bad",2,1)))+G4 -> 3 | G4: 2 | H4: =IFERROR(__xludf.DUMMYFUNCTION("SPARKLINE(F4,{""charttype"",""bar"";""max"",5;""min"",1;""color1"",""#180c56""})"),"")
A5: FALSE | B5: Mini-cart widget displays prominent links to the basket and purchase confirmation page. | C5: Case | D5: Case | E5: To Do | F5: =IF(E5="Not Relevant","",IF(E5="Good","",IF(E5="Bad",2,1)))+G5 -> 2 | G5: 1 | H5: =IFERROR(__xludf.DUMMYFUNCTION("SPARKLINE(F5,{""charttype"",""bar"";""max"",5;""min"",1;""color1"",""#180c56""})"),"")
A6: FALSE | B6: A prominent mini-cart widget is displayed on every page showing the current total, discount, number of products, and item list on hover. | C6: Case | D6: Case | E6: To Do | F6: =IF(E6="Not Relevant","",IF(E6="Good","",IF(E6="Bad",2,1)))+G6 -> 2 | G6: 1 | H6: =IFERROR(__xludf.DUMMYFUNCTION("SPARKLINE(F6,{""charttype"",""bar"";""max"",5;""min"",1;""color1"",""#180c56""})"),"")
A7: FALSE | B7: The shopping cart widget clearly informs customers of how much more they need to spend to qualify for the current promos offered by the store. | C7: Case | D7: Case | E7: To Do | F7: =IF(E7="Not Relevant","",IF(E7="Good","",IF(E7="Bad",2,1)))+G7 -> 3 | G7: 2 | H7: =IFERROR(__xludf.DUMMYFUNCTION("SPARKLINE(F7,{""charttype"",""bar"";""max"",5;""min"",1;""color1"",""#180c56""})"),"")
A8: FALSE | B8: The widget for managing your shopping cart is visibly located in the upper right corner of every page. | C8: Case | D8: Case | E8: To Do | F8: =IF(E8="Not Relevant","",IF(E8="Good","",IF(E8="Bad",2,1)))+G8 -> 5 | G8: 4 | H8: =IFERROR(__xludf.DUMMYFUNCTION("SPARKLINE(F8,{""charttype"",""bar"";""max"",5;""min"",1;""color1"",""#180c56""})"),"")
A9: 👁️ | B9: User Experience
A10: FALSE | B10: Heatmaps are used to continuously monitor and enhance customer experience. | C10: Case | D10: Case | E10: To Do | F10: =IF(E10="Not Relevant","",IF(E10="Good","",IF(E10="Bad",2,1)))+G10 -> 3 | G10: 2 | H10: =IFERROR(__xludf.DUMMYFUNCTION("SPARKLINE(F10,{""charttype"",""bar"";""max"",5;""min"",1;""color1"",""#180c56""})"),"")
A11: FALSE | B11: The main menu does not contain additional tabs or links for the privacy policy, return policy, or terms and conditions. | C11: Case | D11: Case | E11: To Do | F11: =IF(E11="Not Relevant","",IF(E11="Good","",IF(E11="Bad",2,1)))+G11 -> 3 | G11: 2 | H11: =IFERROR(__xludf.DUMMYFUNCTION("SPARKLINE(F11,{""charttype"",""bar"";""max"",5;""min"",1;""color1"",""#180c56""})"),"")
A12: FALSE | B12: Fixed store navigation for easy access to categories, Home Page, Search Bar, and Shopping Cart widgets. | C12: Case | D12: Case | E12: To Do | F12: =IF(E12="Not Relevant","",IF(E12="Good","",IF(E12="Bad",2,1)))+G12 -> 2 | G12: 1 | H12: =IFERROR(__xludf.DUMMYFUNCTION("SPARKLINE(F12,{""charttype"",""bar"";""max"",5;""min"",1;""color1"",""#180c56""})"),"")
A13: FALSE | B13: The navigation bar tabs are organized based on user activity, with less important corporate information at the bottom. | C13: Case | D13: Case | E13: To Do | F13: =IF(E13="Not Relevant","",IF(E13="Good","",IF(E13="Bad",2,1)))+G13 -> 4 | G13: 3 | H13: =IFERROR(__xludf.DUMMYFUNCTION("SPARKLINE(F13,{""charttype"",""bar"";""max"",5;""min"",1;""color1"",""#180c56""})"),"")
A14: FALSE | B14: Accurate category labels describe the content. | C14: Case | D14: Case | E14: To Do | F14: =IF(E14="Not Relevant","",IF(E14="Good","",IF(E14="Bad",2,1)))+G14 -> 4 | G14: 3 | H14: =IFERROR(__xludf.DUMMYFUNCTION("SPARKLINE(F14,{""charttype"",""bar"";""max"",5;""min"",1;""color1"",""#180c56""})"),"")
A15: FALSE | B15: Detailed navigational feedback indicating the user's current location on the site. | C15: Case | D15: Case | E15: To Do | F15: =IF(E15="Not Relevant","",IF(E15="Good","",IF(E15="Bad",2,1)))+G15 -> 4 | G15: 3 | H15: =IFERROR(__xludf.DUMMYFUNCTION("SPARKLINE(F15,{""charttype"",""bar"";""max"",5;""min"",1;""color1"",""#180c56""})"),"")
A16: FALSE | B16: The menu structure is wide and shallow with several options per level, instead of deep with limited options. | C16: Case | D16: Case | E16: To Do | F16: =IF(E16="Not Relevant","",IF(E16="Good","",IF(E16="Bad",2,1)))+G16 -> 4 | G16: 3 | H16: =IFERROR(__xludf.DUMMYFUNCTION("SPARKLINE(F16,{""charttype"",""bar"";""max"",5;""min"",1;""color1"",""#180c56""})"),"")
A17: 👇 | B17: Footer
A18: FALSE | B18: A link for "Back to Top" is available in the footer for quick page navigation. | C18: Case | D18: Case | E18: To Do | F18: =IF(E18="Not Relevant","",IF(E18="Good","",IF(E18="Bad",2,1)))+G18 -> 3 | G18: 2 | H18: =IFERROR(__xludf.DUMMYFUNCTION("SPARKLINE(F18,{""charttype"",""bar"";""max"",5;""min"",1;""color1"",""#180c56""})"),"")
A19: FALSE | B19: Social media buttons and the number of likes or followers are in the footer, allowing the user to verify trust. | C19: Case | D19: Case | E19: To Do | F19: =IF(E19="Not Relevant","",IF(E19="Good","",IF(E19="Bad",2,1)))+G19 -> 3 | G19: 2 | H19: =IFERROR(__xludf.DUMMYFUNCTION("SPARKLINE(F19,{""charttype"",""bar"";""max"",5;""min"",1;""color1"",""#180c56""})"),"")
A20: FALSE | B20: Trust badges and icons, such as Norton Secured, with reassuring text like "Shop with confidence," are displayed in the footer. | C20: Case | D20: Case | E20: To Do | F20: =IF(E20="Not Relevant","",IF(E20="Good","",IF(E20="Bad",2,1)))+G20 -> 3 | G20: 2 | H20: =IFERROR(__xludf.DUMMYFUNCTION("SPARKLINE(F20,{""charttype"",""bar"";""max"",5;""min"",1;""color1"",""#180c56""})"),"")
A21: FALSE | B21: Evidence of legitimate business is displayed, such as a physical address or office photo. | C21: Case | D21: Case | E21: To Do | F21: =IF(E21="Not Relevant","",IF(E21="Good","",IF(E21="Bad",2,1)))+G21 -> 3 | G21: 2 | H21: =IFERROR(__xludf.DUMMYFUNCTION("SPARKLINE(F21,{""charttype"",""bar"";""max"",5;""min"",1;""color1"",""#180c56""})"),"")
A22: FALSE | B22: Advantages of shopping from the store, such as free shipping, returns, money back, products shipped this month, and contact information are highlighted in the footer. | C22: Case | D22: Case | E22: To Do | F22: =IF(E22="Not Relevant","",IF(E22="Good","",IF(E22="Bad",2,1)))+G22 -> 3 | G22: 2 | H22: =IFERROR(__xludf.DUMMYFUNCTION("SPARKLINE(F22,{""charttype"",""bar"";""max"",5;""min"",1;""color1"",""#180c56""})"),"")
A23: FALSE | B23: Links for store's privacy policy, return policy, and terms and conditions are available at any time for easy viewing. | C23: Case | D23: Case | E23: To Do | F23: =IF(E23="Not Relevant","",IF(E23="Good","",IF(E23="Bad",2,1)))+G23 -> 3 | G23: 2 | H23: =IFERROR(__xludf.DUMMYFUNCTION("SPARKLINE(F23,{""charttype"",""bar"";""max"",5;""min"",1;""color1"",""#180c56""})"),"")
A24: FALSE | B24: Navigation links to various sections are available in the footer. | C24: Case | D24: Case | E24: To Do | F24: =IF(E24="Not Relevant","",IF(E24="Good","",IF(E24="Bad",2,1)))+G24 -> 3 | G24: 2 | H24: =IFERROR(__xludf.DUMMYFUNCTION("SPARKLINE(F24,{""charttype"",""bar"";""max"",5;""min"",1;""color1"",""#180c56""})"),"")
A25: 🧿 | B25: Search Bar
A26: FALSE | B26: A magnifying glass icon represents the search feature in the search box. | C26: Case | D26: Case | E26: To Do | F26: =IF(E26="Not Relevant","",IF(E26="Good","",IF(E26="Bad",2,1)))+G26 -> 2 | G26: 1 | H26: =IFERROR(__xludf.DUMMYFUNCTION("SPARKLINE(F26,{""charttype"",""bar"";""max"",5;""min"",1;""color1"",""#180c56""})"),"")
A27: FALSE | B27: A search bar is located at the top or top-right of the homepage. | C27: Case | D27: Case | E27: To Do | F27: =IF(E27="Not Relevant","",IF(E27="Good","",IF(E27="Bad",2,1)))+G27 -> 2 | G27: 1 | H27: =IFERROR(__xludf.DUMMYFUNCTION("SPARKLINE(F27,{""charttype"",""bar"";""max"",5;""min"",1;""color1"",""#180c56""})"),"")
A28: FALSE | B28: The search query is displayed on the results page and can be easily modified. | C28: Case | D28: Case | E28: To Do | F28: =IF(E28="Not Relevant","",IF(E28="Good","",IF(E28="Bad",2,1)))+G28 -> 3 | G28: 2 | H28: =IFERROR(__xludf.DUMMYFUNCTION("SPARKLINE(F28,{""charttype"",""bar"";""max"",5;""min"",1;""color1"",""#180c56""})"),"")
A29: FALSE | B29: Suggestions based on previous queries and current trends appear as soon as the search bar is clicked. | C29: Case | D29: Case | E29: To Do | F29: =IF(E29="Not Relevant","",IF(E29="Good","",IF(E29="Bad",2,1)))+G29 -> 3 | G29: 2 | H29: =IFERROR(__xludf.DUMMYFUNCTION("SPARKLINE(F29,{""charttype"",""bar"";""max"",5;""min"",1;""color1"",""#180c56""})"),"")
A30: FALSE | B30: Search results are ranked by relevancy and the number of results. | C30: Case | D30: Case | E30: To Do | F30: =IF(E30="Not Relevant","",IF(E30="Good","",IF(E30="Bad",2,1)))+G30 -> 4 | G30: 3 | H30: =IFERROR(__xludf.DUMMYFUNCTION("SPARKLINE(F30,{""charttype"",""bar"";""max"",5;""min"",1;""color1"",""#180c56""})"),"")
A31: FALSE | B31: An auto-complete and auto-suggest feature is present in the search box. | C31: Case | D31: Case | E31: To Do | F31: =IF(E31="Not Relevant","",IF(E31="Good","",IF(E31="Bad",2,1)))+G31 -> 3 | G31: 2 | H31: =IFERROR(__xludf.DUMMYFUNCTION("SPARKLINE(F31,{""charttype"",""bar"";""max"",5;""min"",1;""color1"",""#180c56""})"),"")
A32: FALSE | B32: If no results are found, the engine suggests ways to fix the query. | C32: Case | D32: Case | E32: To Do | F32: =IF(E32="Not Relevant","",IF(E32="Good","",IF(E32="Bad",2,1)))+G32 -> 3 | G32: 2 | H32: =IFERROR(__xludf.DUMMYFUNCTION("SPARKLINE(F32,{""charttype"",""bar"";""max"",5;""min"",1;""color1"",""#180c56""})"),"")
A33: FALSE | B33: Popular searches provide relevant data as shown by analytics. | C33: Case | D33: Case | E33: To Do | F33: =IF(E33="Not Relevant","",IF(E33="Good","",IF(E33="Bad",2,1)))+G33 -> 4 | G33: 3 | H33: =IFERROR(__xludf.DUMMYFUNCTION("SPARKLINE(F33,{""charttype"",""bar"";""max"",5;""min"",1;""color1"",""#180c56""})"),"")
A34: FALSE | B34: Instructions on how to use the search engine's features are provided with examples. | C34: Case | D34: Case | E34: To Do | F34: =IF(E34="Not Relevant","",IF(E34="Good","",IF(E34="Bad",2,1)))+G34 -> 3 | G34: 2 | H34: =IFERROR(__xludf.DUMMYFUNCTION("SPARKLINE(F34,{""charttype"",""bar"";""max"",5;""min"",1;""color1"",""#180c56""})"),"")
A35: FALSE | B35: The search bar has enough room for typical-length queries. | C35: Case | D35: Case | E35: To Do | F35: =IF(E35="Not Relevant","",IF(E35="Good","",IF(E35="Bad",2,1)))+G35 -> 2 | G35: 1 | H35: =IFERROR(__xludf.DUMMYFUNCTION("SPARKLINE(F35,{""charttype"",""bar"";""max"",5;""min"",1;""color1"",""#180c56""})"),"")
A36: FALSE | B36: Typing in the search bar and hitting the "Enter" button brings up results. | C36: Case | D36: Case | E36: To Do | F36: =IF(E36="Not Relevant","",IF(E36="Good","",IF(E36="Bad",2,1)))+G36 -> 2 | G36: 1 | H36: =IFERROR(__xludf.DUMMYFUNCTION("SPARKLINE(F36,{""charttype"",""bar"";""max"",5;""min"",1;""color1"",""#180c56""})"),"")
A37: FALSE | B37: Related categories and item suggestions are provided automatically. | C37: Case | D37: Case | E37: To Do | F37: =IF(E37="Not Relevant","",IF(E37="Good","",IF(E37="Bad",2,1)))+G37 -> 3 | G37: 2 | H37: =IFERROR(__xludf.DUMMYFUNCTION("SPARKLINE(F37,{""charttype"",""bar"";""max"",5;""min"",1;""color1"",""#180c56""})"),"")
A38: FALSE | B38: Spelling errors and related terms are checked in all searches. | C38: Case | D38: Case | E38: To Do | F38: =IF(E38="Not Relevant","",IF(E38="Good","",IF(E38="Bad",2,1)))+G38 -> 4 | G38: 3 | H38: =IFERROR(__xludf.DUMMYFUNCTION("SPARKLINE(F38,{""charttype"",""bar"";""max"",5;""min"",1;""color1"",""#180c56""})"),"")
A39: 🚨 | B39: Overall
A40: FALSE | B40: Every page has a visible Store Logo in same location. Upon clicking on the Logo, the customer is redirected to the Home Page. | C40: Case | D40: Case | E40: To Do | F40: =IF(E40="Not Relevant","",IF(E40="Good","",IF(E40="Bad",2,1)))+G40 -> 4 | G40: 3 | H40: =IFERROR(__xludf.DUMMYFUNCTION("SPARKLINE(F40,{""charttype"",""bar"";""max"",5;""min"",1;""color1"",""#180c56""})"),"")
A41: FALSE | B41: The top bar promoting the site-wide discount is highly noticeable and contains a clear call to action. | C41: Case | D41: Case | E41: To Do | F41: =IF(E41="Not Relevant","",IF(E41="Good","",IF(E41="Bad",2,1)))+G41 -> 4 | G41: 3 | H41: =IFERROR(__xludf.DUMMYFUNCTION("SPARKLINE(F41,{""charttype"",""bar"";""max"",5;""min"",1;""color1"",""#180c56""})"),"")
A42: FALSE | B42: Each page loads within 5 seconds (home page, landing page, product page). | C42: Case | D42: Case | E42: To Do | F42: =IF(E42="Not Relevant","",IF(E42="Good","",IF(E42="Bad",2,1)))+G42 -> 4 | G42: 3 | H42: =IFERROR(__xludf.DUMMYFUNCTION("SPARKLINE(F42,{""charttype"",""bar"";""max"",5;""min"",1;""color1"",""#180c56""})"),"")
A43: FALSE | B43: The primary Calls to Action on website pages are emphasized through minor micro-animations. | C43: Case | D43: Case | E43: To Do | F43: =IF(E43="Not Relevant","",IF(E43="Good","",IF(E43="Bad",2,1)))+G43 -> 4 | G43: 3 | H43: =IFERROR(__xludf.DUMMYFUNCTION("SPARKLINE(F43,{""charttype"",""bar"";""max"",5;""min"",1;""color1"",""#180c56""})"),"")
A44: FALSE | B44: A Call to Action (CTA) is shown on every page, including those with 0 views, 404 error pages, blog posts, and the About Us page. | C44: Case | D44: Case | E44: To Do | F44: =IF(E44="Not Relevant","",IF(E44="Good","",IF(E44="Bad",2,1)))+G44 -> 4 | G44: 3 | H44: =IFERROR(__xludf.DUMMYFUNCTION("SPARKLINE(F44,{""charttype"",""bar"";""max"",5;""min"",1;""color1"",""#180c56""})"),"")
A45: FALSE | B45: Links and button labels start with a verb and time component, for example: "Shop Now." | C45: Case | D45: Case | E45: To Do | F45: =IF(E45="Not Relevant","",IF(E45="Good","",IF(E45="Bad",2,1)))+G45 -> 2 | G45: 1 | H45: =IFERROR(__xludf.DUMMYFUNCTION("SPARKLINE(F45,{""charttype"",""bar"";""max"",5;""min"",1;""color1"",""#180c56""})"),"")
A46: FALSE | B46: The site has a wishlist feature for a convenient initial purchase. | C46: Case | D46: Case | E46: To Do | F46: =IF(E46="Not Relevant","",IF(E46="Good","",IF(E46="Bad",2,1)))+G46 -> 4 | G46: 3 | H46: =IFERROR(__xludf.DUMMYFUNCTION("SPARKLINE(F46,{""charttype"",""bar"";""max"",5;""min"",1;""color1"",""#180c56""})"),"")
A47: FALSE | B47: Buttons are interactive and the animations are functional, including rounded corners, a subtle gradient, hover states, and blue underlined links. | C47: Case | D47: Case | E47: To Do | F47: =IF(E47="Not Relevant","",IF(E47="Good","",IF(E47="Bad",2,1)))+G47 -> 3 | G47: 2 | H47: =IFERROR(__xludf.DUMMYFUNCTION("SPARKLINE(F47,{""charttype"",""bar"";""max"",5;""min"",1;""color1"",""#180c56""})"),"")
A48: FALSE | B48: Buttons and forms are placed far enough apart to prevent accidental clicks on unintended targets. | C48: Case | D48: Case | E48: To Do | F48: =IF(E48="Not Relevant","",IF(E48="Good","",IF(E48="Bad",2,1)))+G48 -> 2 | G48: 1 | H48: =IFERROR(__xludf.DUMMYFUNCTION("SPARKLINE(F48,{""charttype"",""bar"";""max"",5;""min"",1;""color1"",""#180c56""})"),"")
A49: FALSE | B49: Additional item upsell options are available between the checkout and Thank You pages, allowing the customer to avoid re-entering payment information if they want to make further purchases. | C49: Case | D49: Case | E49: To Do | F49: =IF(E49="Not Relevant","",IF(E49="Good","",IF(E49="Bad",2,1)))+G49 -> 3 | G49: 2 | H49: =IFERROR(__xludf.DUMMYFUNCTION("SPARKLINE(F49,{""charttype"",""bar"";""max"",5;""min"",1;""color1"",""#180c56""})"),"")
A50: FALSE | B50: Urgency and scarcity ("Only Today") are utilized with a corresponding CTA to promote site-wide offers, such as free shipping, at the top of the home page with phrases like "Shop best-sellers now". | C50: Case | D50: Case | E50: To Do | F50: =IF(E50="Not Relevant","",IF(E50="Good","",IF(E50="Bad",2,1)))+G50 -> 5 | G50: 4 | H50: =IFERROR(__xludf.DUMMYFUNCTION("SPARKLINE(F50,{""charttype"",""bar"";""max"",5;""min"",1;""color1"",""#180c56""})"),"")
A51: FALSE | B51: Simplified options for dismissing or accepting the cookie alert bar under 2 seconds are provided | C51: Case | D51: Case | E51: To Do | F51: =IF(E51="Not Relevant","",IF(E51="Good","",IF(E51="Bad",2,1)))+G51 -> 2 | G51: 1 | H51: =IFERROR(__xludf.DUMMYFUNCTION("SPARKLINE(F51,{""charttype"",""bar"";""max"",5;""min"",1;""color1"",""#180c56""})"),"")
A52: FALSE | B52: This site does not feature disruptive pop-ups that show up upon initial landing on the site. | C52: Case | D52: Case | E52: To Do | F52: =IF(E52="Not Relevant","",IF(E52="Good","",IF(E52="Bad",2,1)))+G52 -> 3 | G52: 2 | H52: =IFERROR(__xludf.DUMMYFUNCTION("SPARKLINE(F52,{""charttype"",""bar"";""max"",5;""min"",1;""color1"",""#180c56""})"),"")
A53: FALSE | B53: Non-clickable items do not imply clickability. | C53: Case | D53: Case | E53: To Do | F53: =IF(E53="Not Relevant","",IF(E53="Good","",IF(E53="Bad",2,1)))+G53 -> 2 | G53: 1 | H53: =IFERROR(__xludf.DUMMYFUNCTION("SPARKLINE(F53,{""charttype"",""bar"";""max"",5;""min"",1;""color1"",""#180c56""})"),"")

Sheet 🏠 Home Page
B1: Home Page
A2: 🏠 | B2: Home Page | C2: Desktop Example | D2: Mobile Example | E2: Status | F2: Factor | G2: Measure of Imporance | H2: Priority
A3: ⚙️ | B3: General Website
A4: FALSE | B4: The Founder's story, mission, and vision are displayed on the home page. | C4: Case | D4: Case | E4: To Do | F4: =IF(E4="Not Relevant","",IF(E4="Good","",IF(E4="Bad",2,1)))+G4 -> 4 | G4: 3 | H4: =IFERROR(__xludf.DUMMYFUNCTION("SPARKLINE(F4,{""charttype"",""bar"";""max"",5;""min"",1;""color1"",""#180c56""})"),"")
A5: FALSE | B5: The home page has a professional design that creates a positive first impression without being overloaded. | C5: Case | D5: Case | E5: To Do | F5: =IF(E5="Not Relevant","",IF(E5="Good","",IF(E5="Bad",2,1)))+G5 -> 3 | G5: 2 | H5: =IFERROR(__xludf.DUMMYFUNCTION("SPARKLINE(F5,{""charttype"",""bar"";""max"",5;""min"",1;""color1"",""#180c56""})"),"")
A6: FALSE | B6: Site-wide offers are prominently displayed at the top of the home page with urgency and scarcity triggers. | C6: Case | D6: Case | E6: To Do | F6: =IF(E6="Not Relevant","",IF(E6="Good","",IF(E6="Bad",2,1)))+G6 -> 3 | G6: 2 | H6: =IFERROR(__xludf.DUMMYFUNCTION("SPARKLINE(F6,{""charttype"",""bar"";""max"",5;""min"",1;""color1"",""#180c56""})"),"")
A7: FALSE | B7: Products sold by the store are easily noticeable when you land on the home page. | C7: Case | D7: Case | E7: To Do | F7: =IF(E7="Not Relevant","",IF(E7="Good","",IF(E7="Bad",2,1)))+G7 -> 2 | G7: 1 | H7: =IFERROR(__xludf.DUMMYFUNCTION("SPARKLINE(F7,{""charttype"",""bar"";""max"",5;""min"",1;""color1"",""#180c56""})"),"")
A8: FALSE | B8: The home page uses meaningful, high-quality graphics, not clip art or pictures of models. | C8: Case | D8: Case | E8: To Do | F8: =IF(E8="Not Relevant","",IF(E8="Good","",IF(E8="Bad",2,1)))+G8 -> 4 | G8: 3 | H8: =IFERROR(__xludf.DUMMYFUNCTION("SPARKLINE(F8,{""charttype"",""bar"";""max"",5;""min"",1;""color1"",""#180c56""})"),"")
A9: FALSE | B9: The value proposition is prominently stated on the home page with a tagline or welcome blurb. | C9: Case | D9: Case | E9: To Do | F9: =IF(E9="Not Relevant","",IF(E9="Good","",IF(E9="Bad",2,1)))+G9 -> 3 | G9: 2 | H9: =IFERROR(__xludf.DUMMYFUNCTION("SPARKLINE(F9,{""charttype"",""bar"";""max"",5;""min"",1;""color1"",""#180c56""})"),"")
A10: FALSE | B10: Special deals, offers, and urgency offers are highlighted near the top of the home page. | C10: Case | D10: Case | E10: To Do | F10: =IF(E10="Not Relevant","",IF(E10="Good","",IF(E10="Bad",2,1)))+G10 -> 2 | G10: 1 | H10: =IFERROR(__xludf.DUMMYFUNCTION("SPARKLINE(F10,{""charttype"",""bar"";""max"",5;""min"",1;""color1"",""#180c56""})"),"")
A11: FALSE | B11: Visually prominent CTAs are found above the fold on the home page with relevant copy such as "Start shopping." | C11: Case | D11: Case | E11: To Do | F11: =IF(E11="Not Relevant","",IF(E11="Good","",IF(E11="Bad",2,1)))+G11 -> 3 | G11: 2 | H11: =IFERROR(__xludf.DUMMYFUNCTION("SPARKLINE(F11,{""charttype"",""bar"";""max"",5;""min"",1;""color1"",""#180c56""})"),"")
A12: FALSE | B12: The most important product categories are displayed near the top of the home page with descriptive photos. | C12: Case | D12: Case | E12: To Do | F12: =IF(E12="Not Relevant","",IF(E12="Good","",IF(E12="Bad",2,1)))+G12 -> 3 | G12: 2 | H12: =IFERROR(__xludf.DUMMYFUNCTION("SPARKLINE(F12,{""charttype"",""bar"";""max"",5;""min"",1;""color1"",""#180c56""})"),"")
A13: FALSE | B13: Main benefits of shopping with the store are highlighted on the home page, such as being "Vegan friendly" or "Not tested on animals." | C13: Case | D13: Case | E13: To Do | F13: =IF(E13="Not Relevant","",IF(E13="Good","",IF(E13="Bad",2,1)))+G13 -> 4 | G13: 3 | H13: =IFERROR(__xludf.DUMMYFUNCTION("SPARKLINE(F13,{""charttype"",""bar"";""max"",5;""min"",1;""color1"",""#180c56""})"),"")
A14: FALSE | B14: A short list of the most important products with links is available on the home page. | C14: Case | D14: Case | E14: To Do | F14: =IF(E14="Not Relevant","",IF(E14="Good","",IF(E14="Bad",2,1)))+G14 -> 3 | G14: 2 | H14: =IFERROR(__xludf.DUMMYFUNCTION("SPARKLINE(F14,{""charttype"",""bar"";""max"",5;""min"",1;""color1"",""#180c56""})"),"")
A15: FALSE | B15: The store has special category pages, such as best-sellers and sales, to help users start shopping. | C15: Case | D15: Case | E15: To Do | F15: =IF(E15="Not Relevant","",IF(E15="Good","",IF(E15="Bad",2,1)))+G15 -> 4 | G15: 3 | H15: =IFERROR(__xludf.DUMMYFUNCTION("SPARKLINE(F15,{""charttype"",""bar"";""max"",5;""min"",1;""color1"",""#180c56""})"),"")
A16: FALSE | B16: Recently viewed items are displayed for returning visitors on the home page. | C16: Case | D16: Case | E16: To Do | F16: =IF(E16="Not Relevant","",IF(E16="Good","",IF(E16="Bad",2,1)))+G16 -> 4 | G16: 3 | H16: =IFERROR(__xludf.DUMMYFUNCTION("SPARKLINE(F16,{""charttype"",""bar"";""max"",5;""min"",1;""color1"",""#180c56""})"),"")
A17: FALSE | B17: The home page includes options for customers to contact the store, such as live chat or email. | C17: Case | D17: Case | E17: To Do | F17: =IF(E17="Not Relevant","",IF(E17="Good","",IF(E17="Bad",2,1)))+G17 -> 3 | G17: 2 | H17: =IFERROR(__xludf.DUMMYFUNCTION("SPARKLINE(F17,{""charttype"",""bar"";""max"",5;""min"",1;""color1"",""#180c56""})"),"")
A18: 📱 | B18: Testimonials
A19: FALSE | B19: Customer reviews or product details with links to products on the home page. | C19: Case | D19: Case | E19: To Do | F19: =IF(E19="Not Relevant","",IF(E19="Good","",IF(E19="Bad",2,1)))+G19 -> 4 | G19: 3 | H19: =IFERROR(__xludf.DUMMYFUNCTION("SPARKLINE(F19,{""charttype"",""bar"";""max"",5;""min"",1;""color1"",""#180c56""})"),"")
A20: FALSE | B20: Home page displays overall store ratings from authoritative review sites (e.g. Trustpilot, Reviews.com, Yotpo, Podium). | C20: Case | D20: Case | E20: To Do | F20: =IF(E20="Not Relevant","",IF(E20="Good","",IF(E20="Bad",2,1)))+G20 -> 4 | G20: 3 | H20: =IFERROR(__xludf.DUMMYFUNCTION("SPARKLINE(F20,{""charttype"",""bar"";""max"",5;""min"",1;""color1"",""#180c56""})"),"")
A21: FALSE | B21: The home page showcases awards, trust badges, and certificates earned by the store. | C21: Case | D21: Case | E21: To Do | F21: =IF(E21="Not Relevant","",IF(E21="Good","",IF(E21="Bad",2,1)))+G21 -> 4 | G21: 3 | H21: =IFERROR(__xludf.DUMMYFUNCTION("SPARKLINE(F21,{""charttype"",""bar"";""max"",5;""min"",1;""color1"",""#180c56""})"),"")
A22: FALSE | B22: The PR exposures of the product/brand are highlighted on the home page, with logos of news sites/blogs/celebrities. | C22: Case | D22: Case | E22: To Do | F22: =IF(E22="Not Relevant","",IF(E22="Good","",IF(E22="Bad",2,1)))+G22 -> 4 | G22: 3 | H22: =IFERROR(__xludf.DUMMYFUNCTION("SPARKLINE(F22,{""charttype"",""bar"";""max"",5;""min"",1;""color1"",""#180c56""})"),"")
A23: FALSE | B23: Logos of well-known brands are displayed on the home page. | C23: Case | D23: Case | E23: To Do | F23: =IF(E23="Not Relevant","",IF(E23="Good","",IF(E23="Bad",2,1)))+G23 -> 4 | G23: 3 | H23: =IFERROR(__xludf.DUMMYFUNCTION("SPARKLINE(F23,{""charttype"",""bar"";""max"",5;""min"",1;""color1"",""#180c56""})"),"")
A24: FALSE | B24: Home page features user-generated photos (e.g. from Instagram). | C24: Case | D24: Case | E24: To Do | F24: =IF(E24="Not Relevant","",IF(E24="Good","",IF(E24="Bad",2,1)))+G24 -> 3 | G24: 2 | H24: =IFERROR(__xludf.DUMMYFUNCTION("SPARKLINE(F24,{""charttype"",""bar"";""max"",5;""min"",1;""color1"",""#180c56""})"),"")

Sheet 📰 Landing Page
B1: Landing Page
A2: 📰 | B2: Landing Page | C2: Desktop Example | D2: Mobile Example | E2: Status | F2: Factor | G2: Measure of Imporance | H2: Priority
A3: 📈 | B3: Website Overview
A4: FALSE | B4: Customers can ask questions through live chat or a provided phone number on the landing page. | C4: Case | D4: Case | E4: To Do | F4: =IF(E4="Not Relevant","",IF(E4="Good","",IF(E4="Bad",2,1)))+G4 -> 4 | G4: 3 | H4: =IFERROR(__xludf.DUMMYFUNCTION("SPARKLINE(F4,{""charttype"",""bar"";""max"",5;""min"",1;""color1"",""#180c56""})"),"")
A5: FALSE | B5: No external links on landing page, such as a clickable logo or navigation menu. | C5: Case | D5: Case | E5: To Do | F5: =IF(E5="Not Relevant","",IF(E5="Good","",IF(E5="Bad",2,1)))+G5 -> 3 | G5: 2 | H5: =IFERROR(__xludf.DUMMYFUNCTION("SPARKLINE(F5,{""charttype"",""bar"";""max"",5;""min"",1;""color1"",""#180c56""})"),"")
A6: FALSE | B6: Navigation bar sticks to the page and displays product name, image, sections, availability, original price, new price, discount, and call-to-action button. It hides when scrolling down and reappears when scrolling up. | C6: Case | D6: Case | E6: To Do | F6: =IF(E6="Not Relevant","",IF(E6="Good","",IF(E6="Bad",2,1)))+G6 -> 3 | G6: 2 | H6: =IFERROR(__xludf.DUMMYFUNCTION("SPARKLINE(F6,{""charttype"",""bar"";""max"",5;""min"",1;""color1"",""#180c56""})"),"")
A7: FALSE | B7: The "Buy" button leads straight to checkout, bypassing the cart page. | C7: Case | D7: Case | E7: To Do | F7: =IF(E7="Not Relevant","",IF(E7="Good","",IF(E7="Bad",2,1)))+G7 -> 3 | G7: 2 | H7: =IFERROR(__xludf.DUMMYFUNCTION("SPARKLINE(F7,{""charttype"",""bar"";""max"",5;""min"",1;""color1"",""#180c56""})"),"")
B8: Call To Action Section
A9: FALSE | B9: The CTA copy clearly explains what happens when clicked (e.g. "Proceed to Secure Checkout"). | C9: Case | D9: Case | E9: To Do | F9: =IF(E9="Not Relevant","",IF(E9="Good","",IF(E9="Bad",2,1)))+G9 -> 3 | G9: 2 | H9: =IFERROR(__xludf.DUMMYFUNCTION("SPARKLINE(F9,{""charttype"",""bar"";""max"",5;""min"",1;""color1"",""#180c56""})"),"")
A10: FALSE | B10: Availability of product shown near main CTA. | C10: Case | D10: Case | E10: To Do | F10: =IF(E10="Not Relevant","",IF(E10="Good","",IF(E10="Bad",2,1)))+G10 -> 4 | G10: 3 | H10: =IFERROR(__xludf.DUMMYFUNCTION("SPARKLINE(F10,{""charttype"",""bar"";""max"",5;""min"",1;""color1"",""#180c56""})"),"")
A11: FALSE | B11: Primary CTA background color differs from other elements. | C11: Case | D11: Case | E11: To Do | F11: =IF(E11="Not Relevant","",IF(E11="Good","",IF(E11="Bad",2,1)))+G11 -> 4 | G11: 3 | H11: =IFERROR(__xludf.DUMMYFUNCTION("SPARKLINE(F11,{""charttype"",""bar"";""max"",5;""min"",1;""color1"",""#180c56""})"),"")
A12: FALSE | B12: The old and new price displayed with savings when on sale. | C12: Case | D12: Case | E12: To Do | F12: =IF(E12="Not Relevant","",IF(E12="Good","",IF(E12="Bad",2,1)))+G12 -> 3 | G12: 2 | H12: =IFERROR(__xludf.DUMMYFUNCTION("SPARKLINE(F12,{""charttype"",""bar"";""max"",5;""min"",1;""color1"",""#180c56""})"),"")
A13: FALSE | B13: Interactive selectors used for product variants update the gallery image and price in real-time. | C13: Case | D13: Case | E13: To Do | F13: =IF(E13="Not Relevant","",IF(E13="Good","",IF(E13="Bad",2,1)))+G13 -> 3 | G13: 2 | H13: =IFERROR(__xludf.DUMMYFUNCTION("SPARKLINE(F13,{""charttype"",""bar"";""max"",5;""min"",1;""color1"",""#180c56""})"),"")
A14: FALSE | B14: Express payment options are shown and available (e.g. PayPal, Amazon, Google Pay, Apple Pay) for direct-response landing pages. | C14: Case | D14: Case | E14: To Do | F14: =IF(E14="Not Relevant","",IF(E14="Good","",IF(E14="Bad",2,1)))+G14 -> 5 | G14: 4 | H14: =IFERROR(__xludf.DUMMYFUNCTION("SPARKLINE(F14,{""charttype"",""bar"";""max"",5;""min"",1;""color1"",""#180c56""})"),"")
A15: FALSE | B15: Localized units for product size are shown (e.g. cm, inches, kg) | C15: Case | D15: Case | E15: To Do | F15: =IF(E15="Not Relevant","",IF(E15="Good","",IF(E15="Bad",2,1)))+G15 -> 3 | G15: 2 | H15: =IFERROR(__xludf.DUMMYFUNCTION("SPARKLINE(F15,{""charttype"",""bar"";""max"",5;""min"",1;""color1"",""#180c56""})"),"")
A16: FALSE | B16: Apparel product descriptions mention the model and shirt size | C16: Case | D16: Case | E16: To Do | F16: =IF(E16="Not Relevant","",IF(E16="Good","",IF(E16="Bad",2,1)))+G16 -> 4 | G16: 3 | H16: =IFERROR(__xludf.DUMMYFUNCTION("SPARKLINE(F16,{""charttype"",""bar"";""max"",5;""min"",1;""color1"",""#180c56""})"),"")
A17: FALSE | B17: Interactive selectors used for quantity selection update price and quantity in real-time | C17: Case | D17: Case | E17: To Do | F17: =IF(E17="Not Relevant","",IF(E17="Good","",IF(E17="Bad",2,1)))+G17 -> 3 | G17: 2 | H17: =IFERROR(__xludf.DUMMYFUNCTION("SPARKLINE(F17,{""charttype"",""bar"";""max"",5;""min"",1;""color1"",""#180c56""})"),"")
A18: FALSE | B18: Product variants are accessible and large with white space on mobile to avoid misclicks | C18: Case | D18: Case | E18: To Do | F18: =IF(E18="Not Relevant","",IF(E18="Good","",IF(E18="Bad",2,1)))+G18 -> 4 | G18: 3 | H18: =IFERROR(__xludf.DUMMYFUNCTION("SPARKLINE(F18,{""charttype"",""bar"";""max"",5;""min"",1;""color1"",""#180c56""})"),"")
A19: FALSE | B19: Product price is prominently displayed, especially for discounted products | C19: Case | D19: Case | E19: To Do | F19: =IF(E19="Not Relevant","",IF(E19="Good","",IF(E19="Bad",2,1)))+G19 -> 4 | G19: 3 | H19: =IFERROR(__xludf.DUMMYFUNCTION("SPARKLINE(F19,{""charttype"",""bar"";""max"",5;""min"",1;""color1"",""#180c56""})"),"")
A20: FALSE | B20: Product price is placed near the main CTA | C20: Case | D20: Case | E20: To Do | F20: =IF(E20="Not Relevant","",IF(E20="Good","",IF(E20="Bad",2,1)))+G20 -> 3 | G20: 2 | H20: =IFERROR(__xludf.DUMMYFUNCTION("SPARKLINE(F20,{""charttype"",""bar"";""max"",5;""min"",1;""color1"",""#180c56""})"),"")
A21: FALSE | B21: Additional charges shown near main CTA (e.g. shipping, VAT). | C21: Case | D21: Case | E21: To Do | F21: =IF(E21="Not Relevant","",IF(E21="Good","",IF(E21="Bad",2,1)))+G21 -> 3 | G21: 2 | H21: =IFERROR(__xludf.DUMMYFUNCTION("SPARKLINE(F21,{""charttype"",""bar"";""max"",5;""min"",1;""color1"",""#180c56""})"),"")
A22: FALSE | B22: The product variant selection links with the product gallery and displays chosen variant images. | C22: Case | D22: Case | E22: To Do | F22: =IF(E22="Not Relevant","",IF(E22="Good","",IF(E22="Bad",2,1)))+G22 -> 4 | G22: 3 | H22: =IFERROR(__xludf.DUMMYFUNCTION("SPARKLINE(F22,{""charttype"",""bar"";""max"",5;""min"",1;""color1"",""#180c56""})"),"")
A23: FALSE | B23: Product price is localized. | C23: Case | D23: Case | E23: To Do | F23: =IF(E23="Not Relevant","",IF(E23="Good","",IF(E23="Bad",2,1)))+G23 -> 2 | G23: 1 | H23: =IFERROR(__xludf.DUMMYFUNCTION("SPARKLINE(F23,{""charttype"",""bar"";""max"",5;""min"",1;""color1"",""#180c56""})"),"")
A24: FALSE | B24: Free shipping highlighted near main CTA | C24: Case | D24: Case | E24: To Do | F24: =IF(E24="Not Relevant","",IF(E24="Good","",IF(E24="Bad",2,1)))+G24 -> 3 | G24: 2 | H24: =IFERROR(__xludf.DUMMYFUNCTION("SPARKLINE(F24,{""charttype"",""bar"";""max"",5;""min"",1;""color1"",""#180c56""})"),"")
A25: FALSE | B25: All shipping information shown near main CTA (delivery, cost, time) | C25: Case | D25: Case | E25: To Do | F25: =IF(E25="Not Relevant","",IF(E25="Good","",IF(E25="Bad",2,1)))+G25 -> 4 | G25: 3 | H25: =IFERROR(__xludf.DUMMYFUNCTION("SPARKLINE(F25,{""charttype"",""bar"";""max"",5;""min"",1;""color1"",""#180c56""})"),"")
A26: FALSE | B26: The CTA is the most visible element and has the "cart" icon. | C26: Case | D26: Case | E26: To Do | F26: =IF(E26="Not Relevant","",IF(E26="Good","",IF(E26="Bad",2,1)))+G26 -> 3 | G26: 2 | H26: =IFERROR(__xludf.DUMMYFUNCTION("SPARKLINE(F26,{""charttype"",""bar"";""max"",5;""min"",1;""color1"",""#180c56""})"),"")
A27: FALSE | B27: A reminder to select size/color is included before "add to cart" for customer convenience. | C27: Case | D27: Case | E27: To Do | F27: =IF(E27="Not Relevant","",IF(E27="Good","",IF(E27="Bad",2,1)))+G27 -> 4 | G27: 3 | H27: =IFERROR(__xludf.DUMMYFUNCTION("SPARKLINE(F27,{""charttype"",""bar"";""max"",5;""min"",1;""color1"",""#180c56""})"),"")
A28: FALSE | B28: Clear information on returns, refunds, and money-back guarantee shown | C28: Case | D28: Case | E28: To Do | F28: =IF(E28="Not Relevant","",IF(E28="Good","",IF(E28="Bad",2,1)))+G28 -> 4 | G28: 3 | H28: =IFERROR(__xludf.DUMMYFUNCTION("SPARKLINE(F28,{""charttype"",""bar"";""max"",5;""min"",1;""color1"",""#180c56""})"),"")
A29: FALSE | B29: A size chart or link with a small popup is provided near size selections for products with different sizes. | C29: Case | D29: Case | E29: To Do | F29: =IF(E29="Not Relevant","",IF(E29="Good","",IF(E29="Bad",2,1)))+G29 -> 3 | G29: 2 | H29: =IFERROR(__xludf.DUMMYFUNCTION("SPARKLINE(F29,{""charttype"",""bar"";""max"",5;""min"",1;""color1"",""#180c56""})"),"")
A30: FALSE | B30: Payment in installments option available (e.g. Klarna, AfterPay) for expensive products on direct-response landing pages. | C30: Case | D30: Case | E30: To Do | F30: =IF(E30="Not Relevant","",IF(E30="Good","",IF(E30="Bad",2,1)))+G30 -> 3 | G30: 2 | H30: =IFERROR(__xludf.DUMMYFUNCTION("SPARKLINE(F30,{""charttype"",""bar"";""max"",5;""min"",1;""color1"",""#180c56""})"),"")
A31: FALSE | B31: Highlights the main benefits of purchasing the products (e.g. environmental friendly, made from quality products, durability, etc.) | C31: Case | D31: Case | E31: To Do | F31: =IF(E31="Not Relevant","",IF(E31="Good","",IF(E31="Bad",2,1)))+G31 -> 4 | G31: 3 | H31: =IFERROR(__xludf.DUMMYFUNCTION("SPARKLINE(F31,{""charttype"",""bar"";""max"",5;""min"",1;""color1"",""#180c56""})"),"")
A32: 🗒️ | B32: Product Description
A33: FALSE | B33: Product information is organized in a scannable structure with grouped information and bullet points, highlighting important benefits. | C33: Case | D33: Case | E33: To Do | F33: =IF(E33="Not Relevant","",IF(E33="Good","",IF(E33="Bad",2,1)))+G33 -> 4 | G33: 3 | H33: =IFERROR(__xludf.DUMMYFUNCTION("SPARKLINE(F33,{""charttype"",""bar"";""max"",5;""min"",1;""color1"",""#180c56""})"),"")
A34: FALSE | B34: Embedded reviews or screenshots from social networks such as Facebook, Messenger, Whatsapp, Twitter, Instagram, Viber, and SMS are included on the product page. | C34: Case | D34: Case | E34: To Do | F34: =IF(E34="Not Relevant","",IF(E34="Good","",IF(E34="Bad",2,1)))+G34 -> 4 | G34: 3 | H34: =IFERROR(__xludf.DUMMYFUNCTION("SPARKLINE(F34,{""charttype"",""bar"";""max"",5;""min"",1;""color1"",""#180c56""})"),"")
A35: FALSE | B35: The product descriptions are easily readable with color, font type, contrast, font size, and a single-column format. It is structured in a maximum of 4 lines with a length limited to 75 characters and a line height of 1.5. | C35: Case | D35: Case | E35: To Do | F35: =IF(E35="Not Relevant","",IF(E35="Good","",IF(E35="Bad",2,1)))+G35 -> 4 | G35: 3 | H35: =IFERROR(__xludf.DUMMYFUNCTION("SPARKLINE(F35,{""charttype"",""bar"";""max"",5;""min"",1;""color1"",""#180c56""})"),"")
A36: FALSE | B36: Technical specifications are presented in a readable table with clear lines, a hover state, and easily distinguishable colors. | C36: Case | D36: Case | E36: To Do | F36: =IF(E36="Not Relevant","",IF(E36="Good","",IF(E36="Bad",2,1)))+G36 -> 4 | G36: 3 | H36: =IFERROR(__xludf.DUMMYFUNCTION("SPARKLINE(F36,{""charttype"",""bar"";""max"",5;""min"",1;""color1"",""#180c56""})"),"")
A37: FALSE | B37: The product page displays everything that is included with the product, including photos where possible. | C37: Case | D37: Case | E37: To Do | F37: =IF(E37="Not Relevant","",IF(E37="Good","",IF(E37="Bad",2,1)))+G37 -> 4 | G37: 3 | H37: =IFERROR(__xludf.DUMMYFUNCTION("SPARKLINE(F37,{""charttype"",""bar"";""max"",5;""min"",1;""color1"",""#180c56""})"),"")
A38: FALSE | B38: FAQs for each specific product and store-wide questions are available for customers. | C38: Case | D38: Case | E38: To Do | F38: =IF(E38="Not Relevant","",IF(E38="Good","",IF(E38="Bad",2,1)))+G38 -> 4 | G38: 3 | H38: =IFERROR(__xludf.DUMMYFUNCTION("SPARKLINE(F38,{""charttype"",""bar"";""max"",5;""min"",1;""color1"",""#180c56""})"),"")
A39: FALSE | B39: Section titles focus on the benefits of the product, not just its features. | C39: Case | D39: Case | E39: To Do | F39: =IF(E39="Not Relevant","",IF(E39="Good","",IF(E39="Bad",2,1)))+G39 -> 4 | G39: 3 | H39: =IFERROR(__xludf.DUMMYFUNCTION("SPARKLINE(F39,{""charttype"",""bar"";""max"",5;""min"",1;""color1"",""#180c56""})"),"")
A40: FALSE | B40: The product page offers product comparisons for customers. | C40: Case | D40: Case | E40: To Do | F40: =IF(E40="Not Relevant","",IF(E40="Good","",IF(E40="Bad",2,1)))+G40 -> 4 | G40: 3 | H40: =IFERROR(__xludf.DUMMYFUNCTION("SPARKLINE(F40,{""charttype"",""bar"";""max"",5;""min"",1;""color1"",""#180c56""})"),"")
A41: FALSE | B41: The product description includes instructions for use in three easy steps. | C41: Case | D41: Case | E41: To Do | F41: =IF(E41="Not Relevant","",IF(E41="Good","",IF(E41="Bad",2,1)))+G41 -> 4 | G41: 3 | H41: =IFERROR(__xludf.DUMMYFUNCTION("SPARKLINE(F41,{""charttype"",""bar"";""max"",5;""min"",1;""color1"",""#180c56""})"),"")
A42: FALSE | B42: Longer sections, such as "General" and "Technical info," are grouped in an accordion and easily scannable on mobile devices. | C42: Case | D42: Case | E42: To Do | F42: =IF(E42="Not Relevant","",IF(E42="Good","",IF(E42="Bad",2,1)))+G42 -> 4 | G42: 3 | H42: =IFERROR(__xludf.DUMMYFUNCTION("SPARKLINE(F42,{""charttype"",""bar"";""max"",5;""min"",1;""color1"",""#180c56""})"),"")
A43: FALSE | B43: Thumbnails of available images are prominently displayed in the photo gallery. | C43: Case | D43: Case | E43: To Do | F43: =IF(E43="Not Relevant","",IF(E43="Good","",IF(E43="Bad",2,1)))+G43 -> 3 | G43: 2 | H43: =IFERROR(__xludf.DUMMYFUNCTION("SPARKLINE(F43,{""charttype"",""bar"";""max"",5;""min"",1;""color1"",""#180c56""})"),"")
A44: FALSE | B44: There is an attractive main product photo. | C44: Case | D44: Case | E44: To Do | F44: =IF(E44="Not Relevant","",IF(E44="Good","",IF(E44="Bad",2,1)))+G44 -> 3 | G44: 2 | H44: =IFERROR(__xludf.DUMMYFUNCTION("SPARKLINE(F44,{""charttype"",""bar"";""max"",5;""min"",1;""color1"",""#180c56""})"),"")
A45: FALSE | B45: The product gallery includes product videos. | C45: Case | D45: Case | E45: To Do | F45: =IF(E45="Not Relevant","",IF(E45="Good","",IF(E45="Bad",2,1)))+G45 -> 4 | G45: 3 | H45: =IFERROR(__xludf.DUMMYFUNCTION("SPARKLINE(F45,{""charttype"",""bar"";""max"",5;""min"",1;""color1"",""#180c56""})"),"")
A46: FALSE | B46: Standardized layout with product photo gallery on the left and description and CTA on the right. | C46: Case | D46: Case | E46: To Do | F46: =IF(E46="Not Relevant","",IF(E46="Good","",IF(E46="Bad",2,1)))+G46 -> 4 | G46: 3 | H46: =IFERROR(__xludf.DUMMYFUNCTION("SPARKLINE(F46,{""charttype"",""bar"";""max"",5;""min"",1;""color1"",""#180c56""})"),"")
A47: FALSE | B47: There are swipe actions supported in the product gallery on mobile devices. | C47: Case | D47: Case | E47: To Do | F47: =IF(E47="Not Relevant","",IF(E47="Good","",IF(E47="Bad",2,1)))+G47 -> 4 | G47: 3 | H47: =IFERROR(__xludf.DUMMYFUNCTION("SPARKLINE(F47,{""charttype"",""bar"";""max"",5;""min"",1;""color1"",""#180c56""})"),"")
A48: FALSE | B48: There are images for different product variants/sizes. | C48: Case | D48: Case | E48: To Do | F48: =IF(E48="Not Relevant","",IF(E48="Good","",IF(E48="Bad",2,1)))+G48 -> 4 | G48: 3 | H48: =IFERROR(__xludf.DUMMYFUNCTION("SPARKLINE(F48,{""charttype"",""bar"";""max"",5;""min"",1;""color1"",""#180c56""})"),"")
A49: ✔️ | B49: Customer Testimonials
A50: FALSE | B50: Logos of news sites, blogs, and celebrities where the product/brand has had PR exposure are displayed on the product page (e.g. "Used by executives at Fortune 500"). | C50: Case | D50: Case | E50: To Do | F50: =IF(E50="Not Relevant","",IF(E50="Good","",IF(E50="Bad",2,1)))+G50 -> 4 | G50: 3 | H50: =IFERROR(__xludf.DUMMYFUNCTION("SPARKLINE(F50,{""charttype"",""bar"";""max"",5;""min"",1;""color1"",""#180c56""})"),"")
A51: FALSE | B51: Social media assets like Facebook and Twitter followers are displayed on the product page. | C51: Case | D51: Case | E51: To Do | F51: =IF(E51="Not Relevant","",IF(E51="Good","",IF(E51="Bad",2,1)))+G51 -> 4 | G51: 3 | H51: =IFERROR(__xludf.DUMMYFUNCTION("SPARKLINE(F51,{""charttype"",""bar"";""max"",5;""min"",1;""color1"",""#180c56""})"),"")
A52: FALSE | B52: Customer reviews stand out visually from other content, ideally with a slightly yellow background. | C52: Case | D52: Case | E52: To Do | F52: =IF(E52="Not Relevant","",IF(E52="Good","",IF(E52="Bad",2,1)))+G52 -> 4 | G52: 3 | H52: =IFERROR(__xludf.DUMMYFUNCTION("SPARKLINE(F52,{""charttype"",""bar"";""max"",5;""min"",1;""color1"",""#180c56""})"),"")
A53: FALSE | B53: The product page displays photos (with faces) of customers happily using the product. | C53: Case | D53: Case | E53: To Do | F53: =IF(E53="Not Relevant","",IF(E53="Good","",IF(E53="Bad",2,1)))+G53 -> 4 | G53: 3 | H53: =IFERROR(__xludf.DUMMYFUNCTION("SPARKLINE(F53,{""charttype"",""bar"";""max"",5;""min"",1;""color1"",""#180c56""})"),"")
A54: FALSE | B54: Overall product star ratings are displayed and can be filtered by star rating. | C54: Case | D54: Case | E54: To Do | F54: =IF(E54="Not Relevant","",IF(E54="Good","",IF(E54="Bad",2,1)))+G54 -> 4 | G54: 3 | H54: =IFERROR(__xludf.DUMMYFUNCTION("SPARKLINE(F54,{""charttype"",""bar"";""max"",5;""min"",1;""color1"",""#180c56""})"),"")
A55: FALSE | B55: The product page lists the number of customers who have made a purchase this week, month, or all-time (e.g. "17,885 products successfully shipped and delivered this month alone"). | C55: Case | D55: Case | E55: To Do | F55: =IF(E55="Not Relevant","",IF(E55="Good","",IF(E55="Bad",2,1)))+G55 -> 4 | G55: 3 | H55: =IFERROR(__xludf.DUMMYFUNCTION("SPARKLINE(F55,{""charttype"",""bar"";""max"",5;""min"",1;""color1"",""#180c56""})"),"")
A56: FALSE | B56: The product page features video testimonials from customers. | C56: Case | D56: Case | E56: To Do | F56: =IF(E56="Not Relevant","",IF(E56="Good","",IF(E56="Bad",2,1)))+G56 -> 4 | G56: 3 | H56: =IFERROR(__xludf.DUMMYFUNCTION("SPARKLINE(F56,{""charttype"",""bar"";""max"",5;""min"",1;""color1"",""#180c56""})"),"")
A57: FALSE | B57: Customer reviews on the product page include a review title, customer photos of the product, star rating, photo of the reviewer, name and last name, "verified" buyer status, occupation, and age. | C57: Case | D57: Case | E57: To Do | F57: =IF(E57="Not Relevant","",IF(E57="Good","",IF(E57="Bad",2,1)))+G57 -> 4 | G57: 3 | H57: =IFERROR(__xludf.DUMMYFUNCTION("SPARKLINE(F57,{""charttype"",""bar"";""max"",5;""min"",1;""color1"",""#180c56""})"),"")
A58: 💵 | B58: Conversion and AOV 'boosters'
A59: FALSE | B59: Visitors who viewed this product also viewed the section showing complementary/alternative products. | C59: Case | D59: Case | E59: To Do | F59: =IF(E59="Not Relevant","",IF(E59="Good","",IF(E59="Bad",2,1)))+G59 -> 4 | G59: 3 | H59: =IFERROR(__xludf.DUMMYFUNCTION("SPARKLINE(F59,{""charttype"",""bar"";""max"",5;""min"",1;""color1"",""#180c56""})"),"")
A60: FALSE | B60: Quantity discounts near main CTA: 1x $29.99 ["Top choice" badge], 2x 7.99€ ["Recommended" badge"], 3x $12.49 ["Best value" badge] | C60: Case | D60: Case | E60: To Do | F60: =IF(E60="Not Relevant","",IF(E60="Good","",IF(E60="Bad",2,1)))+G60 -> 4 | G60: 3 | H60: =IFERROR(__xludf.DUMMYFUNCTION("SPARKLINE(F60,{""charttype"",""bar"";""max"",5;""min"",1;""color1"",""#180c56""})"),"")
A61: FALSE | B61: User taken to upsell variant with a cheaper second item after clicking "Buy button". | C61: Case | D61: Case | E61: To Do | F61: =IF(E61="Not Relevant","",IF(E61="Good","",IF(E61="Bad",2,1)))+G61 -> 4 | G61: 3 | H61: =IFERROR(__xludf.DUMMYFUNCTION("SPARKLINE(F61,{""charttype"",""bar"";""max"",5;""min"",1;""color1"",""#180c56""})"),"")
A62: FALSE | B62: Urgency triggers (e.g. "Today only", "Black Friday offer", etc.) near main CTA. | C62: Case | D62: Case | E62: To Do | F62: =IF(E62="Not Relevant","",IF(E62="Good","",IF(E62="Bad",2,1)))+G62 -> 4 | G62: 3 | H62: =IFERROR(__xludf.DUMMYFUNCTION("SPARKLINE(F62,{""charttype"",""bar"";""max"",5;""min"",1;""color1"",""#180c56""})"),"")
A63: FALSE | B63: Relevant cross-sell/up-sell products offered. | C63: Case | D63: Case | E63: To Do | F63: =IF(E63="Not Relevant","",IF(E63="Good","",IF(E63="Bad",2,1)))+G63 -> 4 | G63: 3 | H63: =IFERROR(__xludf.DUMMYFUNCTION("SPARKLINE(F63,{""charttype"",""bar"";""max"",5;""min"",1;""color1"",""#180c56""})"),"")
A64: FALSE | B64: Store highlights small percentage of profit going to charity. | C64: Case | D64: Case | E64: To Do | F64: =IF(E64="Not Relevant","",IF(E64="Good","",IF(E64="Bad",2,1)))+G64 -> 4 | G64: 3 | H64: =IFERROR(__xludf.DUMMYFUNCTION("SPARKLINE(F64,{""charttype"",""bar"";""max"",5;""min"",1;""color1"",""#180c56""})"),"")
A65: FALSE | B65: Display of people who viewed/bought product in last 24 hours | C65: Case | D65: Case | E65: To Do | F65: =IF(E65="Not Relevant","",IF(E65="Good","",IF(E65="Bad",2,1)))+G65 -> 4 | G65: 3 | H65: =IFERROR(__xludf.DUMMYFUNCTION("SPARKLINE(F65,{""charttype"",""bar"";""max"",5;""min"",1;""color1"",""#180c56""})"),"")
A66: FALSE | B66: Use scarcity triggers (e.g. "Only 1 product left") near the main CTA. | C66: Case | D66: Case | E66: To Do | F66: =IF(E66="Not Relevant","",IF(E66="Good","",IF(E66="Bad",2,1)))+G66 -> 4 | G66: 3 | H66: =IFERROR(__xludf.DUMMYFUNCTION("SPARKLINE(F66,{""charttype"",""bar"";""max"",5;""min"",1;""color1"",""#180c56""})"),"")
A67: FALSE | B67: Bundle products with prominent discounts offered | C67: Case | D67: Case | E67: To Do | F67: =IF(E67="Not Relevant","",IF(E67="Good","",IF(E67="Bad",2,1)))+G67 -> 4 | G67: 3 | H67: =IFERROR(__xludf.DUMMYFUNCTION("SPARKLINE(F67,{""charttype"",""bar"";""max"",5;""min"",1;""color1"",""#180c56""})"),"")
A68: 🗒️ | B68: Product Description
A69: FALSE | B69: Embedded reviews or screenshots from social networks such as Facebook, Messenger, Whatsapp, Twitter, Instagram, Viber, and SMS are included on the product page. | C69: Case | D69: Case | E69: To Do | F69: =IF(E69="Not Relevant","",IF(E69="Good","",IF(E69="Bad",2,1)))+G69 -> 4 | G69: 3 | H69: =IFERROR(__xludf.DUMMYFUNCTION("SPARKLINE(F69,{""charttype"",""bar"";""max"",5;""min"",1;""color1"",""#180c56""})"),"")
A70: FALSE | B70: The product description is easy to read with font size, contrast, and a single column format. Line length is limited to 75 characters with a line-height of 1.5, and a maximum of 4 lines.. | C70: Case | D70: Case | E70: To Do | F70: =IF(E70="Not Relevant","",IF(E70="Good","",IF(E70="Bad",2,1)))+G70 -> 4 | G70: 3 | H70: =IFERROR(__xludf.DUMMYFUNCTION("SPARKLINE(F70,{""charttype"",""bar"";""max"",5;""min"",1;""color1"",""#180c56""})"),"")
A71: FALSE | B71: Organize product information in a scannable structure with grouped information and bullet points, highlighting important benefits. | C71: Case | D71: Case | E71: To Do | F71: =IF(E71="Not Relevant","",IF(E71="Good","",IF(E71="Bad",2,1)))+G71 -> 4 | G71: 3 | H71: =IFERROR(__xludf.DUMMYFUNCTION("SPARKLINE(F71,{""charttype"",""bar"";""max"",5;""min"",1;""color1"",""#180c56""})"),"")
A72: FALSE | B72: Technical specifications are presented in a readable table with clear lines, a hover state, and easily distinguishable colors. | C72: Case | D72: Case | E72: To Do | F72: =IF(E72="Not Relevant","",IF(E72="Good","",IF(E72="Bad",2,1)))+G72 -> 4 | G72: 3 | H72: =IFERROR(__xludf.DUMMYFUNCTION("SPARKLINE(F72,{""charttype"",""bar"";""max"",5;""min"",1;""color1"",""#180c56""})"),"")
A73: FALSE | B73: The product page displays everything that is included with the product, including photos where possible. | C73: Case | D73: Case | E73: To Do | F73: =IF(E73="Not Relevant","",IF(E73="Good","",IF(E73="Bad",2,1)))+G73 -> 4 | G73: 3 | H73: =IFERROR(__xludf.DUMMYFUNCTION("SPARKLINE(F73,{""charttype"",""bar"";""max"",5;""min"",1;""color1"",""#180c56""})"),"")
A74: FALSE | B74: FAQs for each specific product and store-wide questions are available for customers. | C74: Case | D74: Case | E74: To Do | F74: =IF(E74="Not Relevant","",IF(E74="Good","",IF(E74="Bad",2,1)))+G74 -> 4 | G74: 3 | H74: =IFERROR(__xludf.DUMMYFUNCTION("SPARKLINE(F74,{""charttype"",""bar"";""max"",5;""min"",1;""color1"",""#180c56""})"),"")
A75: FALSE | B75: Section titles focus on the benefits of the product, not just its features. | C75: Case | D75: Case | E75: To Do | F75: =IF(E75="Not Relevant","",IF(E75="Good","",IF(E75="Bad",2,1)))+G75 -> 4 | G75: 3 | H75: =IFERROR(__xludf.DUMMYFUNCTION("SPARKLINE(F75,{""charttype"",""bar"";""max"",5;""min"",1;""color1"",""#180c56""})"),"")
A76: FALSE | B76: The product page offers product comparisons for customers. | C76: Case | D76: Case | E76: To Do | F76: =IF(E76="Not Relevant","",IF(E76="Good","",IF(E76="Bad",2,1)))+G76 -> 4 | G76: 3 | H76: =IFERROR(__xludf.DUMMYFUNCTION("SPARKLINE(F76,{""charttype"",""bar"";""max"",5;""min"",1;""color1"",""#180c56""})"),"")
A77: FALSE | B77: The product description includes instructions for use in three simple steps. | C77: Case | D77: Case | E77: To Do | F77: =IF(E77="Not Relevant","",IF(E77="Good","",IF(E77="Bad",2,1)))+G77 -> 4 | G77: 3 | H77: =IFERROR(__xludf.DUMMYFUNCTION("SPARKLINE(F77,{""charttype"",""bar"";""max"",5;""min"",1;""color1"",""#180c56""})"),"")
A78: FALSE | B78: Longer sections, such as "General" and "Technical info," are grouped in an accordion and easily scannable on mobile devices. | C78: Case | D78: Case | E78: To Do | F78: =IF(E78="Not Relevant","",IF(E78="Good","",IF(E78="Bad",2,1)))+G78 -> 4 | G78: 3 | H78: =IFERROR(__xludf.DUMMYFUNCTION("SPARKLINE(F78,{""charttype"",""bar"";""max"",5;""min"",1;""color1"",""#180c56""})"),"")

Sheet 🏪 Category Page
B1: Category Page
A2: 🏪 | B2: Category Page | C2: Desktop Example | D2: Mobile Example | E2: Status | F2: Factor | G2: Measure of Imporance | H2: Priority
B3: Product List
A4: FALSE | B4: Put badges beside the product image to highlight special features like "Fast delivery", "Best-seller", "New", "Top choice", or "Trending". | C4: Case | D4: Case | E4: To Do | F4: =IF(E4="Not Relevant","",IF(E4="Good","",IF(E4="Bad",2,1)))+G4 -> 4 | G4: 3 | H4: =IFERROR(__xludf.DUMMYFUNCTION("SPARKLINE(F4,{""charttype"",""bar"";""max"",5;""min"",1;""color1"",""#180c56""})"),"")
A5: FALSE | B5: Upon mouse hover, additional product photos are displayed. | C5: Case | D5: Case | E5: To Do | F5: =IF(E5="Not Relevant","",IF(E5="Good","",IF(E5="Bad",2,1)))+G5 -> 4 | G5: 3 | H5: =IFERROR(__xludf.DUMMYFUNCTION("SPARKLINE(F5,{""charttype"",""bar"";""max"",5;""min"",1;""color1"",""#180c56""})"),"")
A6: FALSE | B6: Each row displays 3-4 relevant products. | C6: Case | D6: Case | E6: To Do | F6: =IF(E6="Not Relevant","",IF(E6="Good","",IF(E6="Bad",2,1)))+G6 -> 3 | G6: 2 | H6: =IFERROR(__xludf.DUMMYFUNCTION("SPARKLINE(F6,{""charttype"",""bar"";""max"",5;""min"",1;""color1"",""#180c56""})"),"")
A7: FALSE | B7: The product images have a consistent style. | C7: Case | D7: Case | E7: To Do | F7: =IF(E7="Not Relevant","",IF(E7="Good","",IF(E7="Bad",2,1)))+G7 -> 3 | G7: 2 | H7: =IFERROR(__xludf.DUMMYFUNCTION("SPARKLINE(F7,{""charttype"",""bar"";""max"",5;""min"",1;""color1"",""#180c56""})"),"")
A8: FALSE | B8: The best-selling items for each category are featured on the top page. | C8: Case | D8: Case | E8: To Do | F8: =IF(E8="Not Relevant","",IF(E8="Good","",IF(E8="Bad",2,1)))+G8 -> 3 | G8: 2 | H8: =IFERROR(__xludf.DUMMYFUNCTION("SPARKLINE(F8,{""charttype"",""bar"";""max"",5;""min"",1;""color1"",""#180c56""})"),"")
A9: FALSE | B9: The category page indicates the available variants (size, color) for each specific product. | C9: Case | D9: Case | E9: To Do | F9: =IF(E9="Not Relevant","",IF(E9="Good","",IF(E9="Bad",2,1)))+G9 -> 3 | G9: 2 | H9: =IFERROR(__xludf.DUMMYFUNCTION("SPARKLINE(F9,{""charttype"",""bar"";""max"",5;""min"",1;""color1"",""#180c56""})"),"")
A10: FALSE | B10: The product cards have uniform sizes and dimensions. | C10: Case | D10: Case | E10: To Do | F10: =IF(E10="Not Relevant","",IF(E10="Good","",IF(E10="Bad",2,1)))+G10 -> 3 | G10: 2 | H10: =IFERROR(__xludf.DUMMYFUNCTION("SPARKLINE(F10,{""charttype"",""bar"";""max"",5;""min"",1;""color1"",""#180c56""})"),"")
A11: FALSE | B11: The customer can see the product page as they hover over the CTA button. | C11: Case | D11: Case | E11: To Do | F11: =IF(E11="Not Relevant","",IF(E11="Good","",IF(E11="Bad",2,1)))+G11 -> 3 | G11: 2 | H11: =IFERROR(__xludf.DUMMYFUNCTION("SPARKLINE(F11,{""charttype"",""bar"";""max"",5;""min"",1;""color1"",""#180c56""})"),"")
A12: FALSE | B12: Clearly show the prominent product title, old price, new price, discount, review count, overall star rating, short description, product variants [size, color], short descriptions, and product attributes. | C12: Case | D12: Case | E12: To Do | F12: =IF(E12="Not Relevant","",IF(E12="Good","",IF(E12="Bad",2,1)))+G12 -> 3 | G12: 2 | H12: =IFERROR(__xludf.DUMMYFUNCTION("SPARKLINE(F12,{""charttype"",""bar"";""max"",5;""min"",1;""color1"",""#180c56""})"),"")
A13: FALSE | B13: Add urgency to your items by indicating if it is in limited stock and selling out fast. | C13: Case | D13: Case | E13: To Do | F13: =IF(E13="Not Relevant","",IF(E13="Good","",IF(E13="Bad",2,1)))+G13 -> 3 | G13: 2 | H13: =IFERROR(__xludf.DUMMYFUNCTION("SPARKLINE(F13,{""charttype"",""bar"";""max"",5;""min"",1;""color1"",""#180c56""})"),"")
A14: FALSE | B14: Show out-of-stock items Items to as proof of scarcity. | C14: Case | D14: Case | E14: To Do | F14: =IF(E14="Not Relevant","",IF(E14="Good","",IF(E14="Bad",2,1)))+G14 -> 3 | G14: 2 | H14: =IFERROR(__xludf.DUMMYFUNCTION("SPARKLINE(F14,{""charttype"",""bar"";""max"",5;""min"",1;""color1"",""#180c56""})"),"")
A15: FALSE | B15: Give options for the customer to input their email address if the product is currently not available to notify them when it becomes available | C15: Case | D15: Case | E15: To Do | F15: =IF(E15="Not Relevant","",IF(E15="Good","",IF(E15="Bad",2,1)))+G15 -> 3 | G15: 2 | H15: =IFERROR(__xludf.DUMMYFUNCTION("SPARKLINE(F15,{""charttype"",""bar"";""max"",5;""min"",1;""color1"",""#180c56""})"),"")
B16: Filters
A17: FALSE | B17: Clearly labeled and useful filters are shown in the category page but it is applicable only for stores with a large number of products. | C17: Case | D17: Case | E17: To Do | F17: =IF(E17="Not Relevant","",IF(E17="Good","",IF(E17="Bad",2,1)))+G17 -> 3 | G17: 2 | H17: =IFERROR(__xludf.DUMMYFUNCTION("SPARKLINE(F17,{""charttype"",""bar"";""max"",5;""min"",1;""color1"",""#180c56""})"),"")
A18: FALSE | B18: The filters are large enough to be visible (relevant only for stores where users are prone to use filters). | C18: Case | D18: Case | E18: To Do | F18: =IF(E18="Not Relevant","",IF(E18="Good","",IF(E18="Bad",2,1)))+G18 -> 3 | G18: 2 | H18: =IFERROR(__xludf.DUMMYFUNCTION("SPARKLINE(F18,{""charttype"",""bar"";""max"",5;""min"",1;""color1"",""#180c56""})"),"")
A19: FALSE | B19: At the top of the filters, the most popular filters are displayed. | C19: Case | D19: Case | E19: To Do | F19: =IF(E19="Not Relevant","",IF(E19="Good","",IF(E19="Bad",2,1)))+G19 -> 3 | G19: 2 | H19: =IFERROR(__xludf.DUMMYFUNCTION("SPARKLINE(F19,{""charttype"",""bar"";""max"",5;""min"",1;""color1"",""#180c56""})"),"")
A20: FALSE | B20: Each category features relevant filters (e.g. screen size for the "Laptop" category) | C20: Case | D20: Case | E20: To Do | F20: =IF(E20="Not Relevant","",IF(E20="Good","",IF(E20="Bad",2,1)))+G20 -> 3 | G20: 2 | H20: =IFERROR(__xludf.DUMMYFUNCTION("SPARKLINE(F20,{""charttype"",""bar"";""max"",5;""min"",1;""color1"",""#180c56""})"),"")
A21: FALSE | B21: It is very noticeable even on mobile that filters are applied, how many there are, and can be easily removed. | C21: Case | D21: Case | E21: To Do | F21: =IF(E21="Not Relevant","",IF(E21="Good","",IF(E21="Bad",2,1)))+G21 -> 3 | G21: 2 | H21: =IFERROR(__xludf.DUMMYFUNCTION("SPARKLINE(F21,{""charttype"",""bar"";""max"",5;""min"",1;""color1"",""#180c56""})"),"")
A22: FALSE | B22: Customers can select multiple filters at once | C22: Case | D22: Case | E22: To Do | F22: =IF(E22="Not Relevant","",IF(E22="Good","",IF(E22="Bad",2,1)))+G22 -> 3 | G22: 2 | H22: =IFERROR(__xludf.DUMMYFUNCTION("SPARKLINE(F22,{""charttype"",""bar"";""max"",5;""min"",1;""color1"",""#180c56""})"),"")
A23: FALSE | B23: Filters are displayed in a standard position on the left or on top of the page. | C23: Case | D23: Case | E23: To Do | F23: =IF(E23="Not Relevant","",IF(E23="Good","",IF(E23="Bad",2,1)))+G23 -> 3 | G23: 2 | H23: =IFERROR(__xludf.DUMMYFUNCTION("SPARKLINE(F23,{""charttype"",""bar"";""max"",5;""min"",1;""color1"",""#180c56""})"),"")
A24: FALSE | B24: The category page auto-updates in real-time (ajax) when a filter is selected. | C24: Case | D24: Case | E24: To Do | F24: =IF(E24="Not Relevant","",IF(E24="Good","",IF(E24="Bad",2,1)))+G24 -> 3 | G24: 2 | H24: =IFERROR(__xludf.DUMMYFUNCTION("SPARKLINE(F24,{""charttype"",""bar"";""max"",5;""min"",1;""color1"",""#180c56""})"),"")
A25: FALSE | B25: Product filters are sticky and are convenient for frequent use. | C25: Case | D25: Case | E25: To Do | F25: =IF(E25="Not Relevant","",IF(E25="Good","",IF(E25="Bad",2,1)))+G25 -> 3 | G25: 2 | H25: =IFERROR(__xludf.DUMMYFUNCTION("SPARKLINE(F25,{""charttype"",""bar"";""max"",5;""min"",1;""color1"",""#180c56""})"),"")
A26: FALSE | B26: Selectors can be used for various types of filters (e.g. color swatches instead of "black", a price range slider where users can input in the minimum and maximum price instead of a pre-made list of price ranges) | C26: Case | D26: Case | E26: To Do | F26: =IF(E26="Not Relevant","",IF(E26="Good","",IF(E26="Bad",2,1)))+G26 -> 3 | G26: 2 | H26: =IFERROR(__xludf.DUMMYFUNCTION("SPARKLINE(F26,{""charttype"",""bar"";""max"",5;""min"",1;""color1"",""#180c56""})"),"")
A27: 📈 | B27: Overall Website
A28: FALSE | B28: A user-friendly category page is available for customers to easily choose products (e.g. newest styles, lowest price, featured items, promo discounts, etc.) | C28: Case | D28: Case | E28: To Do | F28: =IF(E28="Not Relevant","",IF(E28="Good","",IF(E28="Bad",2,1)))+G28 -> 3 | G28: 2 | H28: =IFERROR(__xludf.DUMMYFUNCTION("SPARKLINE(F28,{""charttype"",""bar"";""max"",5;""min"",1;""color1"",""#180c56""})"),"")
A29: FALSE | B29: The option to show product categories is found in the top-right corner above the product list/grid | C29: Case | D29: Case | E29: To Do | F29: =IF(E29="Not Relevant","",IF(E29="Good","",IF(E29="Bad",2,1)))+G29 -> 3 | G29: 2 | H29: =IFERROR(__xludf.DUMMYFUNCTION("SPARKLINE(F29,{""charttype"",""bar"";""max"",5;""min"",1;""color1"",""#180c56""})"),"")
A30: FALSE | B30: The category page shows easily understandable (sub)category names | C30: Case | D30: Case | E30: To Do | F30: =IF(E30="Not Relevant","",IF(E30="Good","",IF(E30="Bad",2,1)))+G30 -> 3 | G30: 2 | H30: =IFERROR(__xludf.DUMMYFUNCTION("SPARKLINE(F30,{""charttype"",""bar"";""max"",5;""min"",1;""color1"",""#180c56""})"),"")
A31: FALSE | B31: Category page uses relevant category page design (grid view when images are the main decision factor and list view when product attributes are the main decision factor) | C31: Case | D31: Case | E31: To Do | F31: =IF(E31="Not Relevant","",IF(E31="Good","",IF(E31="Bad",2,1)))+G31 -> 3 | G31: 2 | H31: =IFERROR(__xludf.DUMMYFUNCTION("SPARKLINE(F31,{""charttype"",""bar"";""max"",5;""min"",1;""color1"",""#180c56""})"),"")
A32: FALSE | B32: Display an updated number of products available on each page (either if the page is filtered or not) | C32: Case | D32: Case | E32: To Do | F32: =IF(E32="Not Relevant","",IF(E32="Good","",IF(E32="Bad",2,1)))+G32 -> 3 | G32: 2 | H32: =IFERROR(__xludf.DUMMYFUNCTION("SPARKLINE(F32,{""charttype"",""bar"";""max"",5;""min"",1;""color1"",""#180c56""})"),"")
A33: FALSE | B33: On top of the page, a page description section is visibly displayed (cca. 400 words). | C33: Case | D33: Case | E33: To Do | F33: =IF(E33="Not Relevant","",IF(E33="Good","",IF(E33="Bad",2,1)))+G33 -> 3 | G33: 2 | H33: =IFERROR(__xludf.DUMMYFUNCTION("SPARKLINE(F33,{""charttype"",""bar"";""max"",5;""min"",1;""color1"",""#180c56""})"),"")
A34: FALSE | B34: If you go to the product page and then back to the category page, customers stay at the same vertical position. | C34: Case | D34: Case | E34: To Do | F34: =IF(E34="Not Relevant","",IF(E34="Good","",IF(E34="Bad",2,1)))+G34 -> 3 | G34: 2 | H34: =IFERROR(__xludf.DUMMYFUNCTION("SPARKLINE(F34,{""charttype"",""bar"";""max"",5;""min"",1;""color1"",""#180c56""})"),"")

Sheet 🧵 Product Page
B1: Product Page
A2: 🧵 | B2: Product Page | C2: Desktop Example | D2: Mobile Example | E2: Status | F2: Factor | G2: Measure of Imporance | H2: Priority
A3: 🚨 | B3: Overall Website
A4: FALSE | B4: Online shoppers can ask questions either via live chat or phone number with details on the product page. | C4: Case | D4: Case | E4: To Do | F4: =IF(E4="Not Relevant","",IF(E4="Good","",IF(E4="Bad",2,1)))+G4 -> 4 | G4: 3 | H4: =IFERROR(__xludf.DUMMYFUNCTION("SPARKLINE(F4,{""charttype"",""bar"";""max"",5;""min"",1;""color1"",""#180c56""})"),"")
A5: FALSE | B5: Navigation features product details (name, image, sections, availability, pricing) that remains visible when scrolling up, but hides when scrolling down. | C5: Case | D5: Case | E5: To Do | F5: =IF(E5="Not Relevant","",IF(E5="Good","",IF(E5="Bad",2,1)))+G5 -> 3 | G5: 2 | H5: =IFERROR(__xludf.DUMMYFUNCTION("SPARKLINE(F5,{""charttype"",""bar"";""max"",5;""min"",1;""color1"",""#180c56""})"),"")
A6: FALSE | B6: The back button takes the user to the previous page. | C6: Case | D6: Case | E6: To Do | F6: =IF(E6="Not Relevant","",IF(E6="Good","",IF(E6="Bad",2,1)))+G6 -> 4 | G6: 3 | H6: =IFERROR(__xludf.DUMMYFUNCTION("SPARKLINE(F6,{""charttype"",""bar"";""max"",5;""min"",1;""color1"",""#180c56""})"),"")
A7: FALSE | B7: There is an option for customers to enter their email for product availability notifications. | C7: Case | D7: Case | E7: To Do | F7: =IF(E7="Not Relevant","",IF(E7="Good","",IF(E7="Bad",2,1)))+G7 -> 3 | G7: 2 | H7: =IFERROR(__xludf.DUMMYFUNCTION("SPARKLINE(F7,{""charttype"",""bar"";""max"",5;""min"",1;""color1"",""#180c56""})"),"")
A8: FALSE | B8: The product page contains Breadcrumbs available (excluded for single-product stores and direct-response landing pages). | C8: Case | D8: Case | E8: To Do | F8: =IF(E8="Not Relevant","",IF(E8="Good","",IF(E8="Bad",2,1)))+G8 -> 4 | G8: 3 | H8: =IFERROR(__xludf.DUMMYFUNCTION("SPARKLINE(F8,{""charttype"",""bar"";""max"",5;""min"",1;""color1"",""#180c56""})"),"")
A9: 👜 | B9: Products Section
A10: FALSE | B10: Highlight the Main Product Title by making it look more prominent compared to other content. | C10: Case | D10: Case | E10: To Do | F10: =IF(E10="Not Relevant","",IF(E10="Good","",IF(E10="Bad",2,1)))+G10 -> 4 | G10: 3 | H10: =IFERROR(__xludf.DUMMYFUNCTION("SPARKLINE(F10,{""charttype"",""bar"";""max"",5;""min"",1;""color1"",""#180c56""})"),"")
A11: FALSE | B11: Do not exceed 65 characters in writing the Product Title so the Google search results will show the full title. | C11: Case | D11: Case | E11: To Do | F11: =IF(E11="Not Relevant","",IF(E11="Good","",IF(E11="Bad",2,1)))+G11 -> 3 | G11: 2 | H11: =IFERROR(__xludf.DUMMYFUNCTION("SPARKLINE(F11,{""charttype"",""bar"";""max"",5;""min"",1;""color1"",""#180c56""})"),"")
A12: FALSE | B12: Use descriptive words in the product titles to encourage shoppers to buy the item. | C12: Case | D12: Case | E12: To Do | F12: =IF(E12="Not Relevant","",IF(E12="Good","",IF(E12="Bad",2,1)))+G12 -> 2 | G12: 1 | H12: =IFERROR(__xludf.DUMMYFUNCTION("SPARKLINE(F12,{""charttype"",""bar"";""max"",5;""min"",1;""color1"",""#180c56""})"),"")
A13: FALSE | B13: Emphasize the key product benefit and use power words, e.g. limited, special, unique, durable, new, etc. | C13: Case | D13: Case | E13: To Do | F13: =IF(E13="Not Relevant","",IF(E13="Good","",IF(E13="Bad",2,1)))+G13 -> 3 | G13: 2 | H13: =IFERROR(__xludf.DUMMYFUNCTION("SPARKLINE(F13,{""charttype"",""bar"";""max"",5;""min"",1;""color1"",""#180c56""})"),"")
A14: FALSE | B14: Use green check arrow icons for the list of other key benefits of the product close to the main title and link to a detailed description. | C14: Case | D14: Case | E14: To Do | F14: =IF(E14="Not Relevant","",IF(E14="Good","",IF(E14="Bad",2,1)))+G14 -> 3 | G14: 2 | H14: =IFERROR(__xludf.DUMMYFUNCTION("SPARKLINE(F14,{""charttype"",""bar"";""max"",5;""min"",1;""color1"",""#180c56""})"),"")
A15: FALSE | B15: Display product rating overviews near product titles that are linked to their corresponding product reviews. | C15: Case | D15: Case | E15: To Do | F15: =IF(E15="Not Relevant","",IF(E15="Good","",IF(E15="Bad",2,1)))+G15 -> 4 | G15: 3 | H15: =IFERROR(__xludf.DUMMYFUNCTION("SPARKLINE(F15,{""charttype"",""bar"";""max"",5;""min"",1;""color1"",""#180c56""})"),"")
A16: 📷 | B16: Photo gallery
A17: FALSE | B17: A gallery showcases various product photos. | C17: Case | D17: Case | E17: To Do | F17: =IF(E17="Not Relevant","",IF(E17="Good","",IF(E17="Bad",2,1)))+G17 -> 4 | G17: 3 | H17: =IFERROR(__xludf.DUMMYFUNCTION("SPARKLINE(F17,{""charttype"",""bar"";""max"",5;""min"",1;""color1"",""#180c56""})"),"")
A18: FALSE | B18: The product gallery includes product videos. | C18: Case | D18: Case | E18: To Do | F18: =IF(E18="Not Relevant","",IF(E18="Good","",IF(E18="Bad",2,1)))+G18 -> 4 | G18: 3 | H18: =IFERROR(__xludf.DUMMYFUNCTION("SPARKLINE(F18,{""charttype"",""bar"";""max"",5;""min"",1;""color1"",""#180c56""})"),"")
A19: FALSE | B19: The main product photo is visually appealing. | C19: Case | D19: Case | E19: To Do | F19: =IF(E19="Not Relevant","",IF(E19="Good","",IF(E19="Bad",2,1)))+G19 -> 3 | G19: 2 | H19: =IFERROR(__xludf.DUMMYFUNCTION("SPARKLINE(F19,{""charttype"",""bar"";""max"",5;""min"",1;""color1"",""#180c56""})"),"")
A20: FALSE | B20: Thumbnail images of other available photos are displayed in the product gallery. | C20: Case | D20: Case | E20: To Do | F20: =IF(E20="Not Relevant","",IF(E20="Good","",IF(E20="Bad",2,1)))+G20 -> 3 | G20: 2 | H20: =IFERROR(__xludf.DUMMYFUNCTION("SPARKLINE(F20,{""charttype"",""bar"";""max"",5;""min"",1;""color1"",""#180c56""})"),"")
A21: FALSE | B21: The image zoom functionality is easily accessible for the main product photo, particularly on mobile. | C21: Case | D21: Case | E21: To Do | F21: =IF(E21="Not Relevant","",IF(E21="Good","",IF(E21="Bad",2,1)))+G21 -> 4 | G21: 3 | H21: =IFERROR(__xludf.DUMMYFUNCTION("SPARKLINE(F21,{""charttype"",""bar"";""max"",5;""min"",1;""color1"",""#180c56""})"),"")
A22: FALSE | B22: Images for different product variants/sizes are available. | C22: Case | D22: Case | E22: To Do | F22: =IF(E22="Not Relevant","",IF(E22="Good","",IF(E22="Bad",2,1)))+G22 -> 4 | G22: 3 | H22: =IFERROR(__xludf.DUMMYFUNCTION("SPARKLINE(F22,{""charttype"",""bar"";""max"",5;""min"",1;""color1"",""#180c56""})"),"")
A23: FALSE | B23: The product gallery supports swipe gestures on mobile devices. | C23: Case | D23: Case | E23: To Do | F23: =IF(E23="Not Relevant","",IF(E23="Good","",IF(E23="Bad",2,1)))+G23 -> 4 | G23: 3 | H23: =IFERROR(__xludf.DUMMYFUNCTION("SPARKLINE(F23,{""charttype"",""bar"";""max"",5;""min"",1;""color1"",""#180c56""})"),"")
A24: FALSE | B24: Arrows allow navigation between images in the product gallery. | C24: Case | D24: Case | E24: To Do | F24: =IF(E24="Not Relevant","",IF(E24="Good","",IF(E24="Bad",2,1)))+G24 -> 4 | G24: 3 | H24: =IFERROR(__xludf.DUMMYFUNCTION("SPARKLINE(F24,{""charttype"",""bar"";""max"",5;""min"",1;""color1"",""#180c56""})"),"")
A25: 📞 | B25: Call-to-Action Section
A26: FALSE | B26: Use ample white space for product variants to prevent misclicks and they should be easily accessible on mobile. | C26: Case | D26: Case | E26: To Do | F26: =IF(E26="Not Relevant","",IF(E26="Good","",IF(E26="Bad",2,1)))+G26 -> 4 | G26: 3 | H26: =IFERROR(__xludf.DUMMYFUNCTION("SPARKLINE(F26,{""charttype"",""bar"";""max"",5;""min"",1;""color1"",""#180c56""})"),"")
A27: FALSE | B27: The most visible element on the product page is the main CTA, featuring the "cart" icon. | C27: Case | D27: Case | E27: To Do | F27: =IF(E27="Not Relevant","",IF(E27="Good","",IF(E27="Bad",2,1)))+G27 -> 4 | G27: 3 | H27: =IFERROR(__xludf.DUMMYFUNCTION("SPARKLINE(F27,{""charttype"",""bar"";""max"",5;""min"",1;""color1"",""#180c56""})"),"")
A28: FALSE | B28: Show a prominent reminder to select size/color is displayed if the customer forgets and clicks "add to cart" too soon. | C28: Case | D28: Case | E28: To Do | F28: =IF(E28="Not Relevant","",IF(E28="Good","",IF(E28="Bad",2,1)))+G28 -> 4 | G28: 3 | H28: =IFERROR(__xludf.DUMMYFUNCTION("SPARKLINE(F28,{""charttype"",""bar"";""max"",5;""min"",1;""color1"",""#180c56""})"),"")
A29: FALSE | B29: Product details show localized units with varying sizes/measurements (e.g. kg, inches, and cm). | C29: Case | D29: Case | E29: To Do | F29: =IF(E29="Not Relevant","",IF(E29="Good","",IF(E29="Bad",2,1)))+G29 -> 4 | G29: 3 | H29: =IFERROR(__xludf.DUMMYFUNCTION("SPARKLINE(F29,{""charttype"",""bar"";""max"",5;""min"",1;""color1"",""#180c56""})"),"")
A30: FALSE | B30: The product variant selection links with the product gallery and displays images of chosen variants | C30: Case | D30: Case | E30: To Do | F30: =IF(E30="Not Relevant","",IF(E30="Good","",IF(E30="Bad",2,1)))+G30 -> 4 | G30: 3 | H30: =IFERROR(__xludf.DUMMYFUNCTION("SPARKLINE(F30,{""charttype"",""bar"";""max"",5;""min"",1;""color1"",""#180c56""})"),"")
A31: FALSE | B31: Display a size chart or popup link located near the size selections for products with different sizes. | C31: Case | D31: Case | E31: To Do | F31: =IF(E31="Not Relevant","",IF(E31="Good","",IF(E31="Bad",2,1)))+G31 -> 4 | G31: 3 | H31: =IFERROR(__xludf.DUMMYFUNCTION("SPARKLINE(F31,{""charttype"",""bar"";""max"",5;""min"",1;""color1"",""#180c56""})"),"")
A32: FALSE | B32: Interactive selectors are utilized for product variants, updating the gallery image and price in real-time without reloading the page. | C32: Case | D32: Case | E32: To Do | F32: =IF(E32="Not Relevant","",IF(E32="Good","",IF(E32="Bad",2,1)))+G32 -> 4 | G32: 3 | H32: =IFERROR(__xludf.DUMMYFUNCTION("SPARKLINE(F32,{""charttype"",""bar"";""max"",5;""min"",1;""color1"",""#180c56""})"),"")
A33: FALSE | B33: Product descriptions mention the clothing size and model size (apparel only) | C33: Case | D33: Case | E33: To Do | F33: =IF(E33="Not Relevant","",IF(E33="Good","",IF(E33="Bad",2,1)))+G33 -> 4 | G33: 3 | H33: =IFERROR(__xludf.DUMMYFUNCTION("SPARKLINE(F33,{""charttype"",""bar"";""max"",5;""min"",1;""color1"",""#180c56""})"),"")
A34: FALSE | B34: The product price is prominent, especially if discounted. | C34: Case | D34: Case | E34: To Do | F34: =IF(E34="Not Relevant","",IF(E34="Good","",IF(E34="Bad",2,1)))+G34 -> 4 | G34: 3 | H34: =IFERROR(__xludf.DUMMYFUNCTION("SPARKLINE(F34,{""charttype"",""bar"";""max"",5;""min"",1;""color1"",""#180c56""})"),"")
A35: FALSE | B35: Clearly state in the CTA copy clearly the outcome of clicking on it (e.g. "Review order and payment method") | C35: Case | D35: Case | E35: To Do | F35: =IF(E35="Not Relevant","",IF(E35="Good","",IF(E35="Bad",2,1)))+G35 -> 4 | G35: 3 | H35: =IFERROR(__xludf.DUMMYFUNCTION("SPARKLINE(F35,{""charttype"",""bar"";""max"",5;""min"",1;""color1"",""#180c56""})"),"")
A36: FALSE | B36: If any additional charges apply to the order, they should be prominently displayed near the main CTA (e.g. taxes, additional shipping fee for different locations). | C36: Case | D36: Case | E36: To Do | F36: =IF(E36="Not Relevant","",IF(E36="Good","",IF(E36="Bad",2,1)))+G36 -> 4 | G36: 3 | H36: =IFERROR(__xludf.DUMMYFUNCTION("SPARKLINE(F36,{""charttype"",""bar"";""max"",5;""min"",1;""color1"",""#180c56""})"),"")
A37: FALSE | B37: After a product is added to the cart, the main CTA should change state after 2 seconds. | C37: Case | D37: Case | E37: To Do | F37: =IF(E37="Not Relevant","",IF(E37="Good","",IF(E37="Bad",2,1)))+G37 -> 4 | G37: 3 | H37: =IFERROR(__xludf.DUMMYFUNCTION("SPARKLINE(F37,{""charttype"",""bar"";""max"",5;""min"",1;""color1"",""#180c56""})"),"")
A38: FALSE | B38: For choosing quantity options, use Interactive Selectors to update the price and quantity in real time without reloading the page. | C38: Case | D38: Case | E38: To Do | F38: =IF(E38="Not Relevant","",IF(E38="Good","",IF(E38="Bad",2,1)))+G38 -> 4 | G38: 3 | H38: =IFERROR(__xludf.DUMMYFUNCTION("SPARKLINE(F38,{""charttype"",""bar"";""max"",5;""min"",1;""color1"",""#180c56""})"),"")
A39: FALSE | B39: The product's availability is displayed near the main CTA (e.g. "In stock"). | C39: Case | D39: Case | E39: To Do | F39: =IF(E39="Not Relevant","",IF(E39="Good","",IF(E39="Bad",2,1)))+G39 -> 4 | G39: 3 | H39: =IFERROR(__xludf.DUMMYFUNCTION("SPARKLINE(F39,{""charttype"",""bar"";""max"",5;""min"",1;""color1"",""#180c56""})"),"")
A40: FALSE | B40: The product price is localized | C40: Case | D40: Case | E40: To Do | F40: =IF(E40="Not Relevant","",IF(E40="Good","",IF(E40="Bad",2,1)))+G40 -> 4 | G40: 3 | H40: =IFERROR(__xludf.DUMMYFUNCTION("SPARKLINE(F40,{""charttype"",""bar"";""max"",5;""min"",1;""color1"",""#180c56""})"),"")
A41: FALSE | B41: The primary CTA background color differs from other elements (e.g. slightly grey) | C41: Case | D41: Case | E41: To Do | F41: =IF(E41="Not Relevant","",IF(E41="Good","",IF(E41="Bad",2,1)))+G41 -> 4 | G41: 3 | H41: =IFERROR(__xludf.DUMMYFUNCTION("SPARKLINE(F41,{""charttype"",""bar"";""max"",5;""min"",1;""color1"",""#180c56""})"),"")
A42: FALSE | B42: Clear feedback is given when a product is added to the cart (e.g. increase in number in mini-cart widget). | C42: Case | D42: Case | E42: To Do | F42: =IF(E42="Not Relevant","",IF(E42="Good","",IF(E42="Bad",2,1)))+G42 -> 4 | G42: 3 | H42: =IFERROR(__xludf.DUMMYFUNCTION("SPARKLINE(F42,{""charttype"",""bar"";""max"",5;""min"",1;""color1"",""#180c56""})"),"")
A43: FALSE | B43: Information on returns, refunds, and money-back guarantee is clearly displayed | C43: Case | D43: Case | E43: To Do | F43: =IF(E43="Not Relevant","",IF(E43="Good","",IF(E43="Bad",2,1)))+G43 -> 4 | G43: 3 | H43: =IFERROR(__xludf.DUMMYFUNCTION("SPARKLINE(F43,{""charttype"",""bar"";""max"",5;""min"",1;""color1"",""#180c56""})"),"")
A44: FALSE | B44: All shipping information is displayed near the main CTA (location delivery, country flag, cost, time) | C44: Case | D44: Case | E44: To Do | F44: =IF(E44="Not Relevant","",IF(E44="Good","",IF(E44="Bad",2,1)))+G44 -> 4 | G44: 3 | H44: =IFERROR(__xludf.DUMMYFUNCTION("SPARKLINE(F44,{""charttype"",""bar"";""max"",5;""min"",1;""color1"",""#180c56""})"),"")
A45: FALSE | B45: The product price is placed near the main CTA. | C45: Case | D45: Case | E45: To Do | F45: =IF(E45="Not Relevant","",IF(E45="Good","",IF(E45="Bad",2,1)))+G45 -> 4 | G45: 3 | H45: =IFERROR(__xludf.DUMMYFUNCTION("SPARKLINE(F45,{""charttype"",""bar"";""max"",5;""min"",1;""color1"",""#180c56""})"),"")
A46: FALSE | B46: The old price with strike-through is displayed with the new price and savings amount (%, $) when the product is on sale | C46: Case | D46: Case | E46: To Do | F46: =IF(E46="Not Relevant","",IF(E46="Good","",IF(E46="Bad",2,1)))+G46 -> 4 | G46: 3 | H46: =IFERROR(__xludf.DUMMYFUNCTION("SPARKLINE(F46,{""charttype"",""bar"";""max"",5;""min"",1;""color1"",""#180c56""})"),"")
A47: FALSE | B47: If Free Shipping is offered, it must be highlighted near the main CTA. | C47: Case | D47: Case | E47: To Do | F47: =IF(E47="Not Relevant","",IF(E47="Good","",IF(E47="Bad",2,1)))+G47 -> 4 | G47: 3 | H47: =IFERROR(__xludf.DUMMYFUNCTION("SPARKLINE(F47,{""charttype"",""bar"";""max"",5;""min"",1;""color1"",""#180c56""})"),"")
A48: FALSE | B48: Commonly used express payment options (e.g. Apple Pay, PayPal, Google Pay, and Amazon) are shown and available for landing pages. | C48: Case | D48: Case | E48: To Do | F48: =IF(E48="Not Relevant","",IF(E48="Good","",IF(E48="Bad",2,1)))+G48 -> 4 | G48: 3 | H48: =IFERROR(__xludf.DUMMYFUNCTION("SPARKLINE(F48,{""charttype"",""bar"";""max"",5;""min"",1;""color1"",""#180c56""})"),"")
A49: FALSE | B49: The option for installment payments (e.g. Klarna, AfterPay) is available for expensive products on direct-response landing pages that do not encourage adding other products to the cart. | C49: Case | D49: Case | E49: To Do | F49: =IF(E49="Not Relevant","",IF(E49="Good","",IF(E49="Bad",2,1)))+G49 -> 4 | G49: 3 | H49: =IFERROR(__xludf.DUMMYFUNCTION("SPARKLINE(F49,{""charttype"",""bar"";""max"",5;""min"",1;""color1"",""#180c56""})"),"")
A50: 🤳 | B50: Testimonials
A51: FALSE | B51: The product page displays the record of customers this week, month, or all-time, for example, "7,795 products shipped and delivered this month". | C51: Case | D51: Case | E51: To Do | F51: =IF(E51="Not Relevant","",IF(E51="Good","",IF(E51="Bad",2,1)))+G51 -> 4 | G51: 3 | H51: =IFERROR(__xludf.DUMMYFUNCTION("SPARKLINE(F51,{""charttype"",""bar"";""max"",5;""min"",1;""color1"",""#180c56""})"),"")
A52: FALSE | B52: Filters by rating are available and display the product's overall star ratings. | C52: Case | D52: Case | E52: To Do | F52: =IF(E52="Not Relevant","",IF(E52="Good","",IF(E52="Bad",2,1)))+G52 -> 4 | G52: 3 | H52: =IFERROR(__xludf.DUMMYFUNCTION("SPARKLINE(F52,{""charttype"",""bar"";""max"",5;""min"",1;""color1"",""#180c56""})"),"")
A53: FALSE | B53: Customer reviews include review title, customer photos of the product, star rating, reviewer photo, name, "verified" status, occupation, and age. | C53: Case | D53: Case | E53: To Do | F53: =IF(E53="Not Relevant","",IF(E53="Good","",IF(E53="Bad",2,1)))+G53 -> 4 | G53: 3 | H53: =IFERROR(__xludf.DUMMYFUNCTION("SPARKLINE(F53,{""charttype"",""bar"";""max"",5;""min"",1;""color1"",""#180c56""})"),"")
A54: FALSE | B54: The product page features photos of customers using the product, with visible faces. | C54: Case | D54: Case | E54: To Do | F54: =IF(E54="Not Relevant","",IF(E54="Good","",IF(E54="Bad",2,1)))+G54 -> 4 | G54: 3 | H54: =IFERROR(__xludf.DUMMYFUNCTION("SPARKLINE(F54,{""charttype"",""bar"";""max"",5;""min"",1;""color1"",""#180c56""})"),"")
A55: FALSE | B55: Customer reviews are visually prominent, with a slightly yellow background to distinguish them from other content. | C55: Case | D55: Case | E55: To Do | F55: =IF(E55="Not Relevant","",IF(E55="Good","",IF(E55="Bad",2,1)))+G55 -> 4 | G55: 3 | H55: =IFERROR(__xludf.DUMMYFUNCTION("SPARKLINE(F55,{""charttype"",""bar"";""max"",5;""min"",1;""color1"",""#180c56""})"),"")
A56: FALSE | B56: The product page showcases logos of news outlets, blogs, and celebrities where the brand has received PR exposure, such as "used by executives at Fortune 500". | C56: Case | D56: Case | E56: To Do | F56: =IF(E56="Not Relevant","",IF(E56="Good","",IF(E56="Bad",2,1)))+G56 -> 4 | G56: 3 | H56: =IFERROR(__xludf.DUMMYFUNCTION("SPARKLINE(F56,{""charttype"",""bar"";""max"",5;""min"",1;""color1"",""#180c56""})"),"")
A57: FALSE | B57: Video testimonials are featured on the product page. | C57: Case | D57: Case | E57: To Do | F57: =IF(E57="Not Relevant","",IF(E57="Good","",IF(E57="Bad",2,1)))+G57 -> 4 | G57: 3 | H57: =IFERROR(__xludf.DUMMYFUNCTION("SPARKLINE(F57,{""charttype"",""bar"";""max"",5;""min"",1;""color1"",""#180c56""})"),"")
A58: FALSE | B58: To show that many people trust and purchased the products, display the social media followers from Facebook and Twitter. | C58: Case | D58: Case | E58: To Do | F58: =IF(E58="Not Relevant","",IF(E58="Good","",IF(E58="Bad",2,1)))+G58 -> 4 | G58: 3 | H58: =IFERROR(__xludf.DUMMYFUNCTION("SPARKLINE(F58,{""charttype"",""bar"";""max"",5;""min"",1;""color1"",""#180c56""})"),"")
A59: 🪙 | B59: Altering and AOV "boosters"
A60: FALSE | B60: Suggested upsells show the "Visitors who viewed this product also viewed..." section, to suggest complementary or alternative products in the product page. | C60: Case | D60: Case | E60: To Do | F60: =IF(E60="Not Relevant","",IF(E60="Good","",IF(E60="Bad",2,1)))+G60 -> 4 | G60: 3 | H60: =IFERROR(__xludf.DUMMYFUNCTION("SPARKLINE(F60,{""charttype"",""bar"";""max"",5;""min"",1;""color1"",""#180c56""})"),"")
A61: FALSE | B61: If the store donates a portion of profits to charity, highlight this information. | C61: Case | D61: Case | E61: To Do | F61: =IF(E61="Not Relevant","",IF(E61="Good","",IF(E61="Bad",2,1)))+G61 -> 4 | G61: 3 | H61: =IFERROR(__xludf.DUMMYFUNCTION("SPARKLINE(F61,{""charttype"",""bar"";""max"",5;""min"",1;""color1"",""#180c56""})"),"")
A62: FALSE | B62: The product page shows the number of customers who have viewed and bought the product in the past 24 hours. | C62: Case | D62: Case | E62: To Do | F62: =IF(E62="Not Relevant","",IF(E62="Good","",IF(E62="Bad",2,1)))+G62 -> 4 | G62: 3 | H62: =IFERROR(__xludf.DUMMYFUNCTION("SPARKLINE(F62,{""charttype"",""bar"";""max"",5;""min"",1;""color1"",""#180c56""})"),"")
A63: FALSE | B63: Use "Only 1 product is left," and other Scarcity Triggers beside the main CTA button. | C63: Case | D63: Case | E63: To Do | F63: =IF(E63="Not Relevant","",IF(E63="Good","",IF(E63="Bad",2,1)))+G63 -> 4 | G63: 3 | H63: =IFERROR(__xludf.DUMMYFUNCTION("SPARKLINE(F63,{""charttype"",""bar"";""max"",5;""min"",1;""color1"",""#180c56""})"),"")
A64: FALSE | B64: In the area near the CTA, use Urgency Triggers such as "Limited Offer", "Exclusive Discount", "Black Friday offer", and "Today only". | C64: Case | D64: Case | E64: To Do | F64: =IF(E64="Not Relevant","",IF(E64="Good","",IF(E64="Bad",2,1)))+G64 -> 4 | G64: 3 | H64: =IFERROR(__xludf.DUMMYFUNCTION("SPARKLINE(F64,{""charttype"",""bar"";""max"",5;""min"",1;""color1"",""#180c56""})"),"")
A65: FALSE | B65: Bundle products with prominent discounts are offered. | C65: Case | D65: Case | E65: To Do | F65: =IF(E65="Not Relevant","",IF(E65="Good","",IF(E65="Bad",2,1)))+G65 -> 4 | G65: 3 | H65: =IFERROR(__xludf.DUMMYFUNCTION("SPARKLINE(F65,{""charttype"",""bar"";""max"",5;""min"",1;""color1"",""#180c56""})"),"")
A66: FALSE | B66: Cross-sell and up-sell products are offered. | C66: Case | D66: Case | E66: To Do | F66: =IF(E66="Not Relevant","",IF(E66="Good","",IF(E66="Bad",2,1)))+G66 -> 4 | G66: 3 | H66: =IFERROR(__xludf.DUMMYFUNCTION("SPARKLINE(F66,{""charttype"",""bar"";""max"",5;""min"",1;""color1"",""#180c56""})"),"")
A67: FALSE | B67: The main CTA displays clear quantity discounts. For example: 1 piece for $7.99 with a "Best Seller" badge or 2 pieces for $27.49 with "Limited Offer" badge. | C67: Case | D67: Case | E67: To Do | F67: =IF(E67="Not Relevant","",IF(E67="Good","",IF(E67="Bad",2,1)))+G67 -> 4 | G67: 3 | H67: =IFERROR(__xludf.DUMMYFUNCTION("SPARKLINE(F67,{""charttype"",""bar"";""max"",5;""min"",1;""color1"",""#180c56""})"),"")
A68: 🗞️ | B68: Detailed Product Information
A69: FALSE | B69: The product information is structured for easy scanning, with bullet points, grouped information, and featured benefits. | C69: Case | D69: Case | E69: To Do | F69: =IF(E69="Not Relevant","",IF(E69="Good","",IF(E69="Bad",2,1)))+G69 -> 4 | G69: 3 | H69: =IFERROR(__xludf.DUMMYFUNCTION("SPARKLINE(F69,{""charttype"",""bar"";""max"",5;""min"",1;""color1"",""#180c56""})"),"")
A70: FALSE | B70: Section titles emphasize the benefits of the product, rather than its features. | C70: Case | D70: Case | E70: To Do | F70: =IF(E70="Not Relevant","",IF(E70="Good","",IF(E70="Bad",2,1)))+G70 -> 4 | G70: 3 | H70: =IFERROR(__xludf.DUMMYFUNCTION("SPARKLINE(F70,{""charttype"",""bar"";""max"",5;""min"",1;""color1"",""#180c56""})"),"")
A71: FALSE | B71: The product page offers product comparisons. | C71: Case | D71: Case | E71: To Do | F71: =IF(E71="Not Relevant","",IF(E71="Good","",IF(E71="Bad",2,1)))+G71 -> 4 | G71: 3 | H71: =IFERROR(__xludf.DUMMYFUNCTION("SPARKLINE(F71,{""charttype"",""bar"";""max"",5;""min"",1;""color1"",""#180c56""})"),"")
A72: FALSE | B72: The product description is designed for easy reading, with a font size suitable for contrast, a single-column layout, 75 characters per line, a line height of 1.5, and a maximum of 4 lines. | C72: Case | D72: Case | E72: To Do | F72: =IF(E72="Not Relevant","",IF(E72="Good","",IF(E72="Bad",2,1)))+G72 -> 4 | G72: 3 | H72: =IFERROR(__xludf.DUMMYFUNCTION("SPARKLINE(F72,{""charttype"",""bar"";""max"",5;""min"",1;""color1"",""#180c56""})"),"")
A73: FALSE | B73: Customers can see all items included with the product, accompanied by photos if possible. | C73: Case | D73: Case | E73: To Do | F73: =IF(E73="Not Relevant","",IF(E73="Good","",IF(E73="Bad",2,1)))+G73 -> 4 | G73: 3 | H73: =IFERROR(__xludf.DUMMYFUNCTION("SPARKLINE(F73,{""charttype"",""bar"";""max"",5;""min"",1;""color1"",""#180c56""})"),"")
A74: FALSE | B74: The product page includes customer FAQs, both specific to the product and store-wide. | C74: Case | D74: Case | E74: To Do | F74: =IF(E74="Not Relevant","",IF(E74="Good","",IF(E74="Bad",2,1)))+G74 -> 4 | G74: 3 | H74: =IFERROR(__xludf.DUMMYFUNCTION("SPARKLINE(F74,{""charttype"",""bar"";""max"",5;""min"",1;""color1"",""#180c56""})"),"")
A75: FALSE | B75: The technical specifications table is readable, with distinct line colors and a hover state, and is not too widely spaced. | C75: Case | D75: Case | E75: To Do | F75: =IF(E75="Not Relevant","",IF(E75="Good","",IF(E75="Bad",2,1)))+G75 -> 4 | G75: 3 | H75: =IFERROR(__xludf.DUMMYFUNCTION("SPARKLINE(F75,{""charttype"",""bar"";""max"",5;""min"",1;""color1"",""#180c56""})"),"")
A76: FALSE | B76: Longer sections, such as "General" and "Technical Info," are grouped together in an accordion format for easy scanning on mobile devices. | C76: Case | D76: Case | E76: To Do | F76: =IF(E76="Not Relevant","",IF(E76="Good","",IF(E76="Bad",2,1)))+G76 -> 4 | G76: 3 | H76: =IFERROR(__xludf.DUMMYFUNCTION("SPARKLINE(F76,{""charttype"",""bar"";""max"",5;""min"",1;""color1"",""#180c56""})"),"")
A77: FALSE | B77: The product description includes instructions for using the product in 3 easy steps. | C77: Case | D77: Case | E77: To Do | F77: =IF(E77="Not Relevant","",IF(E77="Good","",IF(E77="Bad",2,1)))+G77 -> 4 | G77: 3 | H77: =IFERROR(__xludf.DUMMYFUNCTION("SPARKLINE(F77,{""charttype"",""bar"";""max"",5;""min"",1;""color1"",""#180c56""})"),"")
A78: FALSE | B78: Show embedded reviews or screenshots from social networks such as Instagram, Quora, Facebook, Messenger, WhatsApp, Twitter, Viber, and text messages. | C78: Case | D78: Case | E78: To Do | F78: =IF(E78="Not Relevant","",IF(E78="Good","",IF(E78="Bad",2,1)))+G78 -> 4 | G78: 3 | H78: =IFERROR(__xludf.DUMMYFUNCTION("SPARKLINE(F78,{""charttype"",""bar"";""max"",5;""min"",1;""color1"",""#180c56""})"),"")

Sheet 🛒 Add to Cart Page
B1: Add-to-Cart Page
A2: 🛒 | B2: Add-to-Cart Page | C2: Desktop Example | D2: Mobile Example | E2: Status | F2: Factor | G2: Measure of Imporance | H2: Priority
A3: 🤙 | B3: Call-to-Action section
A4: FALSE | B4: Main CTA, "Proceed to a secure checkout," features a lock icon on a distinct gray background. | C4: Case | D4: Case | E4: To Do | F4: =IF(E4="Not Relevant","",IF(E4="Good","",IF(E4="Bad",2,1)))+G4 -> 3 | G4: 2 | H4: =IFERROR(__xludf.DUMMYFUNCTION("SPARKLINE(F4,{""charttype"",""bar"";""max"",5;""min"",1;""color1"",""#180c56""})"),"")
A5: FALSE | B5: Savings on the entire purchase are shown near the main CTA. | C5: Case | D5: Case | E5: To Do | F5: =IF(E5="Not Relevant","",IF(E5="Good","",IF(E5="Bad",2,1)))+G5 -> 3 | G5: 2 | H5: =IFERROR(__xludf.DUMMYFUNCTION("SPARKLINE(F5,{""charttype"",""bar"";""max"",5;""min"",1;""color1"",""#180c56""})"),"")
A6: FALSE | B6: Prominently display estimated taxes. | C6: Case | D6: Case | E6: To Do | F6: =IF(E6="Not Relevant","",IF(E6="Good","",IF(E6="Bad",2,1)))+G6 -> 3 | G6: 2 | H6: =IFERROR(__xludf.DUMMYFUNCTION("SPARKLINE(F6,{""charttype"",""bar"";""max"",5;""min"",1;""color1"",""#180c56""})"),"")
A7: FALSE | B7: The main CTA is duplicated at the top and bottom of the page and says "Proceed to a Secure Checkout". | C7: Case | D7: Case | E7: To Do | F7: =IF(E7="Not Relevant","",IF(E7="Good","",IF(E7="Bad",2,1)))+G7 -> 3 | G7: 2 | H7: =IFERROR(__xludf.DUMMYFUNCTION("SPARKLINE(F7,{""charttype"",""bar"";""max"",5;""min"",1;""color1"",""#180c56""})"),"")
A8: FALSE | B8: Display the subtotal price near the main CTA. | C8: Case | D8: Case | E8: To Do | F8: =IF(E8="Not Relevant","",IF(E8="Good","",IF(E8="Bad",2,1)))+G8 -> 3 | G8: 2 | H8: =IFERROR(__xludf.DUMMYFUNCTION("SPARKLINE(F8,{""charttype"",""bar"";""max"",5;""min"",1;""color1"",""#180c56""})"),"")
A9: FALSE | B9: On the Cart Page, display a secondary CTA button that says "Continue shopping". | C9: Case | D9: Case | E9: To Do | F9: =IF(E9="Not Relevant","",IF(E9="Good","",IF(E9="Bad",2,1)))+G9 -> 3 | G9: 2 | H9: =IFERROR(__xludf.DUMMYFUNCTION("SPARKLINE(F9,{""charttype"",""bar"";""max"",5;""min"",1;""color1"",""#180c56""})"),"")
A10: FALSE | B10: Amazon Pay, Google Pay, PayPal, and other most widely used payment options are displayed below the main CTA. | C10: Case | D10: Case | E10: To Do | F10: =IF(E10="Not Relevant","",IF(E10="Good","",IF(E10="Bad",2,1)))+G10 -> 3 | G10: 2 | H10: =IFERROR(__xludf.DUMMYFUNCTION("SPARKLINE(F10,{""charttype"",""bar"";""max"",5;""min"",1;""color1"",""#180c56""})"),"")
A11: FALSE | B11: Installment methods including Klarna, with detailed information are displayed and their icons or images are shown on the page. | C11: Case | D11: Case | E11: To Do | F11: =IF(E11="Not Relevant","",IF(E11="Good","",IF(E11="Bad",2,1)))+G11 -> 3 | G11: 2 | H11: =IFERROR(__xludf.DUMMYFUNCTION("SPARKLINE(F11,{""charttype"",""bar"";""max"",5;""min"",1;""color1"",""#180c56""})"),"")
A12: FALSE | B12: Trust icon/seal badge, such as "Verified by Norton," along with reassuring copy "Shop with confidence" is below the main CTA. | C12: Case | D12: Case | E12: To Do | F12: =IF(E12="Not Relevant","",IF(E12="Good","",IF(E12="Bad",2,1)))+G12 -> 3 | G12: 2 | H12: =IFERROR(__xludf.DUMMYFUNCTION("SPARKLINE(F12,{""charttype"",""bar"";""max"",5;""min"",1;""color1"",""#180c56""})"),"")
A13: 📈 | B13: Overall Website
A14: FALSE | B14: The items remain in the cart when user returns to site. | C14: Case | D14: Case | E14: To Do | F14: =IF(E14="Not Relevant","",IF(E14="Good","",IF(E14="Bad",2,1)))+G14 -> 4 | G14: 3 | H14: =IFERROR(__xludf.DUMMYFUNCTION("SPARKLINE(F14,{""charttype"",""bar"";""max"",5;""min"",1;""color1"",""#180c56""})"),"")
A15: FALSE | B15: Offers to upsell/cross-sell products with benefits, urgency, and discounts. | C15: Case | D15: Case | E15: To Do | F15: =IF(E15="Not Relevant","",IF(E15="Good","",IF(E15="Bad",2,1)))+G15 -> 3 | G15: 2 | H15: =IFERROR(__xludf.DUMMYFUNCTION("SPARKLINE(F15,{""charttype"",""bar"";""max"",5;""min"",1;""color1"",""#180c56""})"),"")
A16: FALSE | B16: Cart informs user's proximity to free shipping threshold or discount. | C16: Case | D16: Case | E16: To Do | F16: =IF(E16="Not Relevant","",IF(E16="Good","",IF(E16="Bad",2,1)))+G16 -> 4 | G16: 3 | H16: =IFERROR(__xludf.DUMMYFUNCTION("SPARKLINE(F16,{""charttype"",""bar"";""max"",5;""min"",1;""color1"",""#180c56""})"),"")
A17: FALSE | B17: Prominently notifies the customer if the free shipping limit is reached. | C17: Case | D17: Case | E17: To Do | F17: =IF(E17="Not Relevant","",IF(E17="Good","",IF(E17="Bad",2,1)))+G17 -> 3 | G17: 2 | H17: =IFERROR(__xludf.DUMMYFUNCTION("SPARKLINE(F17,{""charttype"",""bar"";""max"",5;""min"",1;""color1"",""#180c56""})"),"")
A18: FALSE | B18: Cart allows changing product quantity, updates automatically. | C18: Case | D18: Case | E18: To Do | F18: =IF(E18="Not Relevant","",IF(E18="Good","",IF(E18="Bad",2,1)))+G18 -> 2 | G18: 1 | H18: =IFERROR(__xludf.DUMMYFUNCTION("SPARKLINE(F18,{""charttype"",""bar"";""max"",5;""min"",1;""color1"",""#180c56""})"),"")
A19: FALSE | B19: The cart displays all important product info (title, image, chosen variant, quantity, price). | C19: Case | D19: Case | E19: To Do | F19: =IF(E19="Not Relevant","",IF(E19="Good","",IF(E19="Bad",2,1)))+G19 -> 4 | G19: 3 | H19: =IFERROR(__xludf.DUMMYFUNCTION("SPARKLINE(F19,{""charttype"",""bar"";""max"",5;""min"",1;""color1"",""#180c56""})"),"")
A20: FALSE | B20: Displays the correct image for the chosen variant. | C20: Case | D20: Case | E20: To Do | F20: =IF(E20="Not Relevant","",IF(E20="Good","",IF(E20="Bad",2,1)))+G20 -> 3 | G20: 2 | H20: =IFERROR(__xludf.DUMMYFUNCTION("SPARKLINE(F20,{""charttype"",""bar"";""max"",5;""min"",1;""color1"",""#180c56""})"),"")
A21: FALSE | B21: The cart design is clear and uncluttered. | C21: Case | D21: Case | E21: To Do | F21: =IF(E21="Not Relevant","",IF(E21="Good","",IF(E21="Bad",2,1)))+G21 -> 2 | G21: 1 | H21: =IFERROR(__xludf.DUMMYFUNCTION("SPARKLINE(F21,{""charttype"",""bar"";""max"",5;""min"",1;""color1"",""#180c56""})"),"")
A22: FALSE | B22: Easy to remove items from cart | C22: Case | D22: Case | E22: To Do | F22: =IF(E22="Not Relevant","",IF(E22="Good","",IF(E22="Bad",2,1)))+G22 -> 3 | G22: 2 | H22: =IFERROR(__xludf.DUMMYFUNCTION("SPARKLINE(F22,{""charttype"",""bar"";""max"",5;""min"",1;""color1"",""#180c56""})"),"")
A23: FALSE | B23: The customers can enter a coupon code but with a hidden input field (so they don't have to search for coupon codes on Google) | C23: Case | D23: Case | E23: To Do | F23: =IF(E23="Not Relevant","",IF(E23="Good","",IF(E23="Bad",2,1)))+G23 -> 3 | G23: 2 | H23: =IFERROR(__xludf.DUMMYFUNCTION("SPARKLINE(F23,{""charttype"",""bar"";""max"",5;""min"",1;""color1"",""#180c56""})"),"")
A24: FALSE | B24: Scarcity triggers displayed next to each item ("Only 1 in stock") in prominent color | C24: Case | D24: Case | E24: To Do | F24: =IF(E24="Not Relevant","",IF(E24="Good","",IF(E24="Bad",2,1)))+G24 -> 4 | G24: 3 | H24: =IFERROR(__xludf.DUMMYFUNCTION("SPARKLINE(F24,{""charttype"",""bar"";""max"",5;""min"",1;""color1"",""#180c56""})"),"")
A25: FALSE | B25: Help centers (e.g. live chat, email, phone number) are easily accessible through the Add to Cart page. | C25: Case | D25: Case | E25: To Do | F25: =IF(E25="Not Relevant","",IF(E25="Good","",IF(E25="Bad",2,1)))+G25 -> 3 | G25: 2 | H25: =IFERROR(__xludf.DUMMYFUNCTION("SPARKLINE(F25,{""charttype"",""bar"";""max"",5;""min"",1;""color1"",""#180c56""})"),"")
A26: FALSE | B26: Returns, refunds, and money-back guarantee information displayed | C26: Case | D26: Case | E26: To Do | F26: =IF(E26="Not Relevant","",IF(E26="Good","",IF(E26="Bad",2,1)))+G26 -> 4 | G26: 3 | H26: =IFERROR(__xludf.DUMMYFUNCTION("SPARKLINE(F26,{""charttype"",""bar"";""max"",5;""min"",1;""color1"",""#180c56""})"),"")
A27: FALSE | B27: Expected delivery date is displayed in cart. | C27: Case | D27: Case | E27: To Do | F27: =IF(E27="Not Relevant","",IF(E27="Good","",IF(E27="Bad",2,1)))+G27 -> 4 | G27: 3 | H27: =IFERROR(__xludf.DUMMYFUNCTION("SPARKLINE(F27,{""charttype"",""bar"";""max"",5;""min"",1;""color1"",""#180c56""})"),"")
A28: FALSE | B28: Urgency triggers are used in the cart. For example: "Your items are reserved for 10 minutes," or "Order in the next 12 mins to be shipped today". | C28: Case | D28: Case | E28: To Do | F28: =IF(E28="Not Relevant","",IF(E28="Good","",IF(E28="Bad",2,1)))+G28 -> 3 | G28: 2 | H28: =IFERROR(__xludf.DUMMYFUNCTION("SPARKLINE(F28,{""charttype"",""bar"";""max"",5;""min"",1;""color1"",""#180c56""})"),"")
A29: FALSE | B29: Include an option to save products/cart for later instead of deleting orders. | C29: Case | D29: Case | E29: To Do | F29: =IF(E29="Not Relevant","",IF(E29="Good","",IF(E29="Bad",2,1)))+G29 -> 3 | G29: 2 | H29: =IFERROR(__xludf.DUMMYFUNCTION("SPARKLINE(F29,{""charttype"",""bar"";""max"",5;""min"",1;""color1"",""#180c56""})"),"")

Sheet 💳 Checkout Page
B1: Checkout Page
A2: 💳 | B2: Checkout Page | C2: Desktop Example | D2: Mobile Example | E2: Status | F2: Factor | G2: Measure of Imporance | H2: Priority
A3: 👉 | B3: Login and Register
A4: FALSE | B4: Simple password selection process during registration. | C4: Case | D4: Case | E4: To Do | F4: =IF(E4="Not Relevant","",IF(E4="Good","",IF(E4="Bad",2,1)))+G4 -> 3 | G4: 2 | H4: =IFERROR(__xludf.DUMMYFUNCTION("SPARKLINE(F4,{""charttype"",""bar"";""max"",5;""min"",1;""color1"",""#180c56""})"),"")
A5: FALSE | B5: Create an easy way of recovering password. | C5: Case | D5: Case | E5: To Do | F5: =IF(E5="Not Relevant","",IF(E5="Good","",IF(E5="Bad",2,1)))+G5 -> 3 | G5: 2 | H5: =IFERROR(__xludf.DUMMYFUNCTION("SPARKLINE(F5,{""charttype"",""bar"";""max"",5;""min"",1;""color1"",""#180c56""})"),"")
A6: FALSE | B6: Checkout enables users to log in to avoid repeating information entries. | C6: Case | D6: Case | E6: To Do | F6: =IF(E6="Not Relevant","",IF(E6="Good","",IF(E6="Bad",2,1)))+G6 -> 3 | G6: 2 | H6: =IFERROR(__xludf.DUMMYFUNCTION("SPARKLINE(F6,{""charttype"",""bar"";""max"",5;""min"",1;""color1"",""#180c56""})"),"")
A7: 📝 | B7: Application Form
A8: FALSE | B8: The option to check "billing address is the same as shipping" on the checkout page is visible. | C8: Case | D8: Case | E8: To Do | F8: =IF(E8="Not Relevant","",IF(E8="Good","",IF(E8="Bad",2,1)))+G8 -> 4 | G8: 3 | H8: =IFERROR(__xludf.DUMMYFUNCTION("SPARKLINE(F8,{""charttype"",""bar"";""max"",5;""min"",1;""color1"",""#180c56""})"),"")
A9: FALSE | B9: The checkout page has minimum necessary input fields | C9: Case | D9: Case | E9: To Do | F9: =IF(E9="Not Relevant","",IF(E9="Good","",IF(E9="Bad",2,1)))+G9 -> 4 | G9: 3 | H9: =IFERROR(__xludf.DUMMYFUNCTION("SPARKLINE(F9,{""charttype"",""bar"";""max"",5;""min"",1;""color1"",""#180c56""})"),"")
A10: FALSE | B10: The credit card input fields have a gray background for perceived trust. | C10: Case | D10: Case | E10: To Do | F10: =IF(E10="Not Relevant","",IF(E10="Good","",IF(E10="Bad",2,1)))+G10 -> 4 | G10: 3 | H10: =IFERROR(__xludf.DUMMYFUNCTION("SPARKLINE(F10,{""charttype"",""bar"";""max"",5;""min"",1;""color1"",""#180c56""})"),"")
A11: FALSE | B11: User's email address is requested first for contact purposes | C11: Case | D11: Case | E11: To Do | F11: =IF(E11="Not Relevant","",IF(E11="Good","",IF(E11="Bad",2,1)))+G11 -> 4 | G11: 3 | H11: =IFERROR(__xludf.DUMMYFUNCTION("SPARKLINE(F11,{""charttype"",""bar"";""max"",5;""min"",1;""color1"",""#180c56""})"),"")
A12: FALSE | B12: Input fields have suggestions to reduce cognitive load | C12: Case | D12: Case | E12: To Do | F12: =IF(E12="Not Relevant","",IF(E12="Good","",IF(E12="Bad",2,1)))+G12 -> 4 | G12: 3 | H12: =IFERROR(__xludf.DUMMYFUNCTION("SPARKLINE(F12,{""charttype"",""bar"";""max"",5;""min"",1;""color1"",""#180c56""})"),"")
A13: FALSE | B13: Input fields layout is simple, in a single column | C13: Case | D13: Case | E13: To Do | F13: =IF(E13="Not Relevant","",IF(E13="Good","",IF(E13="Bad",2,1)))+G13 -> 4 | G13: 3 | H13: =IFERROR(__xludf.DUMMYFUNCTION("SPARKLINE(F13,{""charttype"",""bar"";""max"",5;""min"",1;""color1"",""#180c56""})"),"")
A14: FALSE | B14: Easy access to payment options on mobile | C14: Case | D14: Case | E14: To Do | F14: =IF(E14="Not Relevant","",IF(E14="Good","",IF(E14="Bad",2,1)))+G14 -> 4 | G14: 3 | H14: =IFERROR(__xludf.DUMMYFUNCTION("SPARKLINE(F14,{""charttype"",""bar"";""max"",5;""min"",1;""color1"",""#180c56""})"),"")
A15: FALSE | B15: The credit card details has visual prompts (e.g. CVV code image) | C15: Case | D15: Case | E15: To Do | F15: =IF(E15="Not Relevant","",IF(E15="Good","",IF(E15="Bad",2,1)))+G15 -> 4 | G15: 3 | H15: =IFERROR(__xludf.DUMMYFUNCTION("SPARKLINE(F15,{""charttype"",""bar"";""max"",5;""min"",1;""color1"",""#180c56""})"),"")
A16: FALSE | B16: Input fields have "floating labels" for name and contents display. | C16: Case | D16: Case | E16: To Do | F16: =IF(E16="Not Relevant","",IF(E16="Good","",IF(E16="Bad",2,1)))+G16 -> 4 | G16: 3 | H16: =IFERROR(__xludf.DUMMYFUNCTION("SPARKLINE(F16,{""charttype"",""bar"";""max"",5;""min"",1;""color1"",""#180c56""})"),"")
A17: FALSE | B17: Tab key for easy navigation between form input fields | C17: Case | D17: Case | E17: To Do | F17: =IF(E17="Not Relevant","",IF(E17="Good","",IF(E17="Bad",2,1)))+G17 -> 4 | G17: 3 | H17: =IFERROR(__xludf.DUMMYFUNCTION("SPARKLINE(F17,{""charttype"",""bar"";""max"",5;""min"",1;""color1"",""#180c56""})"),"")
A18: FALSE | B18: Numeric keyboard for number-only input fields (post code, phone number) on mobile | C18: Case | D18: Case | E18: To Do | F18: =IF(E18="Not Relevant","",IF(E18="Good","",IF(E18="Bad",2,1)))+G18 -> 4 | G18: 3 | H18: =IFERROR(__xludf.DUMMYFUNCTION("SPARKLINE(F18,{""charttype"",""bar"";""max"",5;""min"",1;""color1"",""#180c56""})"),"")
A19: FALSE | B19: Keyboard with dedicated buttons for @ and ".com" for email input on mobile | C19: Case | D19: Case | E19: To Do | F19: =IF(E19="Not Relevant","",IF(E19="Good","",IF(E19="Bad",2,1)))+G19 -> 4 | G19: 3 | H19: =IFERROR(__xludf.DUMMYFUNCTION("SPARKLINE(F19,{""charttype"",""bar"";""max"",5;""min"",1;""color1"",""#180c56""})"),"")
A20: FALSE | B20: Input field width shows data format and amount needed | C20: Case | D20: Case | E20: To Do | F20: =IF(E20="Not Relevant","",IF(E20="Good","",IF(E20="Bad",2,1)))+G20 -> 4 | G20: 3 | H20: =IFERROR(__xludf.DUMMYFUNCTION("SPARKLINE(F20,{""charttype"",""bar"";""max"",5;""min"",1;""color1"",""#180c56""})"),"")
A21: FALSE | B21: Does not ask to enter the same information multiple times. | C21: Case | D21: Case | E21: To Do | F21: =IF(E21="Not Relevant","",IF(E21="Good","",IF(E21="Bad",2,1)))+G21 -> 4 | G21: 3 | H21: =IFERROR(__xludf.DUMMYFUNCTION("SPARKLINE(F21,{""charttype"",""bar"";""max"",5;""min"",1;""color1"",""#180c56""})"),"")
A22: FALSE | B22: Phone number input has a label explaining it's for delivery purposes | C22: Case | D22: Case | E22: To Do | F22: =IF(E22="Not Relevant","",IF(E22="Good","",IF(E22="Bad",2,1)))+G22 -> 4 | G22: 3 | H22: =IFERROR(__xludf.DUMMYFUNCTION("SPARKLINE(F22,{""charttype"",""bar"";""max"",5;""min"",1;""color1"",""#180c56""})"),"")
A23: FALSE | B23: The checkout page uses street address database to avoid mistyping. | C23: Case | D23: Case | E23: To Do | F23: =IF(E23="Not Relevant","",IF(E23="Good","",IF(E23="Bad",2,1)))+G23 -> 4 | G23: 3 | H23: =IFERROR(__xludf.DUMMYFUNCTION("SPARKLINE(F23,{""charttype"",""bar"";""max"",5;""min"",1;""color1"",""#180c56""})"),"")
A24: FALSE | B24: There is an inline validation with green/red border and arrow/x sign for input field accuracy. | C24: Case | D24: Case | E24: To Do | F24: =IF(E24="Not Relevant","",IF(E24="Good","",IF(E24="Bad",2,1)))+G24 -> 4 | G24: 3 | H24: =IFERROR(__xludf.DUMMYFUNCTION("SPARKLINE(F24,{""charttype"",""bar"";""max"",5;""min"",1;""color1"",""#180c56""})"),"")
A25: FALSE | B25: Error state clearly states input field errors and corrections | C25: Case | D25: Case | E25: To Do | F25: =IF(E25="Not Relevant","",IF(E25="Good","",IF(E25="Bad",2,1)))+G25 -> 4 | G25: 3 | H25: =IFERROR(__xludf.DUMMYFUNCTION("SPARKLINE(F25,{""charttype"",""bar"";""max"",5;""min"",1;""color1"",""#180c56""})"),"")
A26: FALSE | B26: The optional and mandatory fields are distinguishable from each other. | C26: Case | D26: Case | E26: To Do | F26: =IF(E26="Not Relevant","",IF(E26="Good","",IF(E26="Bad",2,1)))+G26 -> 4 | G26: 3 | H26: =IFERROR(__xludf.DUMMYFUNCTION("SPARKLINE(F26,{""charttype"",""bar"";""max"",5;""min"",1;""color1"",""#180c56""})"),"")
A27: FALSE | B27: An auto-complete function is used where possible (e.g. auto-fill city from postal code) in the check out page. | C27: Case | D27: Case | E27: To Do | F27: =IF(E27="Not Relevant","",IF(E27="Good","",IF(E27="Bad",2,1)))+G27 -> 4 | G27: 3 | H27: =IFERROR(__xludf.DUMMYFUNCTION("SPARKLINE(F27,{""charttype"",""bar"";""max"",5;""min"",1;""color1"",""#180c56""})"),"")
A28: FALSE | B28: Input fields saved if user leaves and returns to checkout | C28: Case | D28: Case | E28: To Do | F28: =IF(E28="Not Relevant","",IF(E28="Good","",IF(E28="Bad",2,1)))+G28 -> 4 | G28: 3 | H28: =IFERROR(__xludf.DUMMYFUNCTION("SPARKLINE(F28,{""charttype"",""bar"";""max"",5;""min"",1;""color1"",""#180c56""})"),"")
A29: FALSE | B29: Option to delete content with one click using an "X" icon. | C29: Case | D29: Case | E29: To Do | F29: =IF(E29="Not Relevant","",IF(E29="Good","",IF(E29="Bad",2,1)))+G29 -> 4 | G29: 3 | H29: =IFERROR(__xludf.DUMMYFUNCTION("SPARKLINE(F29,{""charttype"",""bar"";""max"",5;""min"",1;""color1"",""#180c56""})"),"")
A30: 💹 | B30: Altering and AOV "boosters"
A31: FALSE | B31: Order bumps are available on the checkout page, such as "Skip the queue," "Urgent shipping," "Gift packaging," and "Package insurance" for less than $5. | C31: Case | D31: Case | E31: To Do | F31: =IF(E31="Not Relevant","",IF(E31="Good","",IF(E31="Bad",2,1)))+G31 -> 3 | G31: 2 | H31: =IFERROR(__xludf.DUMMYFUNCTION("SPARKLINE(F31,{""charttype"",""bar"";""max"",5;""min"",1;""color1"",""#180c56""})"),"")
A32: FALSE | B32: Urgency triggers are used including "Your items are reserved for 15 minutes" and "Order completion within next 20 minutes can be shipped today." | C32: Case | D32: Case | E32: To Do | F32: =IF(E32="Not Relevant","",IF(E32="Good","",IF(E32="Bad",2,1)))+G32 -> 3 | G32: 2 | H32: =IFERROR(__xludf.DUMMYFUNCTION("SPARKLINE(F32,{""charttype"",""bar"";""max"",5;""min"",1;""color1"",""#180c56""})"),"")
A33: FALSE | B33: Checkout includes an upsell step before the Thank You page, where users can add more products to their orders. | C33: Case | D33: Case | E33: To Do | F33: =IF(E33="Not Relevant","",IF(E33="Good","",IF(E33="Bad",2,1)))+G33 -> 3 | G33: 2 | H33: =IFERROR(__xludf.DUMMYFUNCTION("SPARKLINE(F33,{""charttype"",""bar"";""max"",5;""min"",1;""color1"",""#180c56""})"),"")
A34: 🚨 | B34: Overall Website
A35: FALSE | B35: The main CTA is the most prominent element on the checkout page. | C35: Case | D35: Case | E35: To Do | F35: =IF(E35="Not Relevant","",IF(E35="Good","",IF(E35="Bad",2,1)))+G35 -> 4 | G35: 3 | H35: =IFERROR(__xludf.DUMMYFUNCTION("SPARKLINE(F35,{""charttype"",""bar"";""max"",5;""min"",1;""color1"",""#180c56""})"),"")
A36: FALSE | B36: The checkout page offers easy access to the store's help center (e.g. live chat, email, phone number). | C36: Case | D36: Case | E36: To Do | F36: =IF(E36="Not Relevant","",IF(E36="Good","",IF(E36="Bad",2,1)))+G36 -> 3 | G36: 2 | H36: =IFERROR(__xludf.DUMMYFUNCTION("SPARKLINE(F36,{""charttype"",""bar"";""max"",5;""min"",1;""color1"",""#180c56""})"),"")
A37: FALSE | B37: No outgoing links (e.g. clickable logo, navigation, footer) are present the on checkout page. | C37: Case | D37: Case | E37: To Do | F37: =IF(E37="Not Relevant","",IF(E37="Good","",IF(E37="Bad",2,1)))+G37 -> 4 | G37: 3 | H37: =IFERROR(__xludf.DUMMYFUNCTION("SPARKLINE(F37,{""charttype"",""bar"";""max"",5;""min"",1;""color1"",""#180c56""})"),"")
A38: FALSE | B38: The checkout form lets the user continue the purchase even if an error occurs. | C38: Case | D38: Case | E38: To Do | F38: =IF(E38="Not Relevant","",IF(E38="Good","",IF(E38="Bad",2,1)))+G38 -> 3 | G38: 2 | H38: =IFERROR(__xludf.DUMMYFUNCTION("SPARKLINE(F38,{""charttype"",""bar"";""max"",5;""min"",1;""color1"",""#180c56""})"),"")
A39: FALSE | B39: Clear order summary displayed before committing to purchase. | C39: Case | D39: Case | E39: To Do | F39: =IF(E39="Not Relevant","",IF(E39="Good","",IF(E39="Bad",2,1)))+G39 -> 2 | G39: 1 | H39: =IFERROR(__xludf.DUMMYFUNCTION("SPARKLINE(F39,{""charttype"",""bar"";""max"",5;""min"",1;""color1"",""#180c56""})"),"")
A40: FALSE | B40: A privacy policy is easily accessible, especially on pages that request personal information, and is straightforward and clear. | C40: Case | D40: Case | E40: To Do | F40: =IF(E40="Not Relevant","",IF(E40="Good","",IF(E40="Bad",2,1)))+G40 -> 4 | G40: 3 | H40: =IFERROR(__xludf.DUMMYFUNCTION("SPARKLINE(F40,{""charttype"",""bar"";""max"",5;""min"",1;""color1"",""#180c56""})"),"")
A41: FALSE | B41: A multi-step checkout process is clear in terms of the actions after clicking the CTA. | C41: Case | D41: Case | E41: To Do | F41: =IF(E41="Not Relevant","",IF(E41="Good","",IF(E41="Bad",2,1)))+G41 -> 3 | G41: 2 | H41: =IFERROR(__xludf.DUMMYFUNCTION("SPARKLINE(F41,{""charttype"",""bar"";""max"",5;""min"",1;""color1"",""#180c56""})"),"")
A42: FALSE | B42: The Trust Icon/Seal Badge (e.g. verified by Norton) with "Shop with confidence" reassuring copy displayed near the main CTA. | C42: Case | D42: Case | E42: To Do | F42: =IF(E42="Not Relevant","",IF(E42="Good","",IF(E42="Bad",2,1)))+G42 -> 2 | G42: 1 | H42: =IFERROR(__xludf.DUMMYFUNCTION("SPARKLINE(F42,{""charttype"",""bar"";""max"",5;""min"",1;""color1"",""#180c56""})"),"")
A43: FALSE | B43: Clear feedback is provided during checkout with a progress bar indicating the user's position. | C43: Case | D43: Case | E43: To Do | F43: =IF(E43="Not Relevant","",IF(E43="Good","",IF(E43="Bad",2,1)))+G43 -> 3 | G43: 2 | H43: =IFERROR(__xludf.DUMMYFUNCTION("SPARKLINE(F43,{""charttype"",""bar"";""max"",5;""min"",1;""color1"",""#180c56""})"),"")
A44: FALSE | B44: Checkout enables guest purchase options. | C44: Case | D44: Case | E44: To Do | F44: =IF(E44="Not Relevant","",IF(E44="Good","",IF(E44="Bad",2,1)))+G44 -> 3 | G44: 2 | H44: =IFERROR(__xludf.DUMMYFUNCTION("SPARKLINE(F44,{""charttype"",""bar"";""max"",5;""min"",1;""color1"",""#180c56""})"),"")

Sheet 🙏 Thank You Page
B1: Thank You Page
A2: 🙏 | B2: Thank You Page | C2: Desktop Example | D2: Mobile Example | E2: Status | F2: Factor | G2: Measure of Imporance | H2: Priority
A3: 💸 | B3: Conversion and AOV 'boosters'
A4: FALSE | B4: The customer gets a Confirmation Email that includes the product summary, upsells, and the same coupon code from the Thank You page. | C4: Case | D4: Case | E4: To Do | F4: =IF(E4="Not Relevant","",IF(E4="Good","",IF(E4="Bad",2,1)))+G4 -> 4 | G4: 3 | H4: =IFERROR(__xludf.DUMMYFUNCTION("SPARKLINE(F4,{""charttype"",""bar"";""max"",5;""min"",1;""color1"",""#180c56""})"),"")
A5: FALSE | B5: Lower-priced additional items/quantities of the same product or complementary product are offered on the Thank You page. | C5: Case | D5: Case | E5: To Do | F5: =IF(E5="Not Relevant","",IF(E5="Good","",IF(E5="Bad",2,1)))+G5 -> 3 | G5: 2 | H5: =IFERROR(__xludf.DUMMYFUNCTION("SPARKLINE(F5,{""charttype"",""bar"";""max"",5;""min"",1;""color1"",""#180c56""})"),"")
A6: FALSE | B6: The Thank You page gives coupon codes for which can be used for the next purchase or share with friends. | C6: Case | D6: Case | E6: To Do | F6: =IF(E6="Not Relevant","",IF(E6="Good","",IF(E6="Bad",2,1)))+G6 -> 2 | G6: 1 | H6: =IFERROR(__xludf.DUMMYFUNCTION("SPARKLINE(F6,{""charttype"",""bar"";""max"",5;""min"",1;""color1"",""#180c56""})"),"")
A7: 📈 | B7: Overall Website
A8: FALSE | B8: Shows a clear summary of the customer's order. | C8: Case | D8: Case | E8: To Do | F8: =IF(E8="Not Relevant","",IF(E8="Good","",IF(E8="Bad",2,1)))+G8 -> 4 | G8: 3 | H8: =IFERROR(__xludf.DUMMYFUNCTION("SPARKLINE(F8,{""charttype"",""bar"";""max"",5;""min"",1;""color1"",""#180c56""})"),"")
A9: FALSE | B9: Displays information about the expected delivery time and which courier will deliver it. | C9: Case | D9: Case | E9: To Do | F9: =IF(E9="Not Relevant","",IF(E9="Good","",IF(E9="Bad",2,1)))+G9 -> 3 | G9: 2 | H9: =IFERROR(__xludf.DUMMYFUNCTION("SPARKLINE(F9,{""charttype"",""bar"";""max"",5;""min"",1;""color1"",""#180c56""})"),"")
A10: FALSE | B10: Clearly shows a successful purchase process and sends a "congratulations" message. | C10: Case | D10: Case | E10: To Do | F10: =IF(E10="Not Relevant","",IF(E10="Good","",IF(E10="Bad",2,1)))+G10 -> 4 | G10: 3 | H10: =IFERROR(__xludf.DUMMYFUNCTION("SPARKLINE(F10,{""charttype"",""bar"";""max"",5;""min"",1;""color1"",""#180c56""})"),"")
A11: FALSE | B11: Offers an easy way for the customer to get in touch with the store owner via live chat, email, or phone number. | C11: Case | D11: Case | E11: To Do | F11: =IF(E11="Not Relevant","",IF(E11="Good","",IF(E11="Bad",2,1)))+G11 -> 3 | G11: 2 | H11: =IFERROR(__xludf.DUMMYFUNCTION("SPARKLINE(F11,{""charttype"",""bar"";""max"",5;""min"",1;""color1"",""#180c56""})"),"")
A12: FALSE | B12: Sends a tracking number to enable customers to monitor package delivery. | C12: Case | D12: Case | E12: To Do | F12: =IF(E12="Not Relevant","",IF(E12="Good","",IF(E12="Bad",2,1)))+G12 -> 3 | G12: 2 | H12: =IFERROR(__xludf.DUMMYFUNCTION("SPARKLINE(F12,{""charttype"",""bar"";""max"",5;""min"",1;""color1"",""#180c56""})"),"")

Sheet Bonus - ⚒️ Tools You Need to Ga
C1: **Bonus** - ⚒️ Tools You Need to Gain an Edge ⚒️
